Workbook
Name value_list: коэф_произв[Значение]
Name value_list: коэф_произв[Значение]
Name value_list: коэф_произв[Значение]
Name value_list: коэф_произв[Значение]
Name value_list: коэф_произв[Значение]
Name value_list: коэф_произв[Значение]
Name value_list: коэф_произв[Значение]
Name value_list: коэф_произв[Значение]
Name value_list: коэф_произв[Значение]
Name долл: dict!$G$1
Name Класс: Таблица2[Класс]
Name Класс: Таблица2[Класс]
Name Класс: Таблица2[Класс]
Name Класс: Таблица2[Класс]
Name Класс: Таблица2[Класс]
Name Класс: Таблица2[Класс]
Name Класс: Таблица2[Класс]
Name Класс: Таблица2[Класс]
Name Класс: Таблица2[Класс]
Name Объект_оценки_аналог: Таблица2[Объект оценки/ аналог]
Name Объект_оценки_аналог: Таблица2[Объект оценки/ аналог]
Name Объект_оценки_аналог: Таблица2[Объект оценки/ аналог]
Name Объект_оценки_аналог: Таблица2[Объект оценки/ аналог]
Name Объект_оценки_аналог: Таблица2[Объект оценки/ аналог]
Name Объект_оценки_аналог: Таблица2[Объект оценки/ аналог]
Name Объект_оценки_аналог: Таблица2[Объект оценки/ аналог]
Name Объект_оценки_аналог: Таблица2[Объект оценки/ аналог]
Name Объект_оценки_аналог: Таблица2[Объект оценки/ аналог]
Name Площадь: Таблица2[Площадь, м2]
Name Площадь: Таблица2[Площадь, м2]
Name Площадь: Таблица2[Площадь, м2]
Name Площадь: Таблица2[Площадь, м2]
Name Площадь: Таблица2[Площадь, м2]
Name Площадь: Таблица2[Площадь, м2]
Name Площадь: Таблица2[Площадь, м2]
Name Площадь: Таблица2[Площадь, м2]
Name Площадь: Таблица2[Площадь, м2]

Sheet dict
A1: Характеристика | B1: Тип | C1: Значение | D1: Коэффициент | F1: доллар | G1: 87.45
A2: Высота | B2: гражд | C2: До 2,6 м. | D2: 0.6
A3: Высота | B3: гражд | C3: 2,6-3,2 м. | D3: 0.7
A4: Высота | B4: гражд | C4: 3,2-4 м. | D4: 0.8
A5: Высота | B5: гражд | C5: Более 4 м. (условно - 5 м в среднем) | D5: 1
A6: Архитектура | B6: гражд | C6: Устаревшая | D6: 0.8
A7: Архитектура | B7: гражд | C7: Устаревшая/ Современная | D7: 0.9
A8: Архитектура | B8: гражд | C8: Современная | D8: 1
A9: Конструкция | B9: гражд | C9: Некапитальная | D9: 0.8
A10: Конструкция | B10: гражд | C10: Смешанная | D10: 0.9
A11: Конструкция | B11: гражд | C11: Капитальная | D11: 1
A12: Планировка | B12: гражд | C12: Свободная | D12: 0.9
A13: Планировка | B13: гражд | C13: Смешанная | D13: 0.95
... A38: Инженерное оснащение | B38: произв | C38: Высокое (дополнителньые системы (вентиляция, противопожарная безопасность, бесключевой доступ), возможна подводка газа, | D38: 1

Sheet Таблица объектов
A1: Объект оценки/ аналог | B1: Площадь, м2 | C1: Объект | D1: Тип | E1: Высота | F1: Высота коэф. | G1: Наличие / Возможность кран-балки | H1: Наличие / Возможность кран-балки коэф. | I1: Конструкция | J1: Конструкция коэф. | K1: Полы | L1: Полы коэф. | M1: Инженерное оснащение | N1: Инженерное оснащение коэф. | O1: Архитектура | P1: Архитектура коэф. | Q1: Планировка | R1: Планировка коэф. | S1: Уровень отделки | T1: Уровень отделки коэф. | U1: Капитальность | V1: Класс | W1: Площадь, взвешенная по капитальности | X1: Состояние | Y1: состояние взвешенное | Z1: состояние взвешенное скорректир. На капитальность | AB1: из расчёта затратного
A2: Объект оценки 1 | B2: 1113.8 | C2: Нежилое помещение (Склады) | D2: произв | E2: 3-5 м. | F2: {=_xlfn.XLOOKUP(1,(Таблица2[[#This Row],[Тип]]=коэф_произв[Тип])*(Таблица2[[#This Row],[Высота]]=коэф_произв[Значение])*('Таблица объектов'!E$1=коэф_произв[Характеристика]),коэф_произв[Коэффициент],"",0)} -> 0.6 | G2: Не установлено (по умолчанию) | H2: {=_xlfn.XLOOKUP(1,(Таблица2[[#This Row],[Тип]]=коэф_произв[Тип])*(Таблица2[[#This Row],[Наличие / Возможность кран-балки]]=коэф_произв[Значение])*('Таблица объектов'!G$1=коэф_произв[Характеристика]),коэф_произв[Коэффициент],"",0)} -> 0.95 | I2: Блочные по железобетонному каркасу, без утепления | J2: {=_xlfn.XLOOKUP(1,(Таблица2[[#This Row],[Тип]]=коэф_произв[Тип])*(Таблица2[[#This Row],[Конструкция]]=коэф_произв[Значение])*('Таблица объектов'!I$1=коэф_произв[Характеристика]),коэф_произв[Коэффициент],"",0)} -> 0.7 | K2: Простые | L2: {=_xlfn.XLOOKUP(1,(Таблица2[[#This Row],[Тип]]=коэф_произв[Тип])*(Таблица2[[#This Row],[Полы]]=коэф_произв[Значение])*('Таблица объектов'!K$1=коэф_произв[Характеристика]),коэф_произв[Коэффициент],"",0)} -> 0.9 | M2: Отсутствует или минимальное (минимальная разводка освещения, водопровода) | N2: {=_xlfn.XLOOKUP(1,(Таблица2[[#This Row],[Тип]]=коэф_произв[Тип])*(Таблица2[[#This Row],[Инженерное оснащение]]=коэф_произв[Значение])*('Таблица объектов'!M$1=коэф_произв[Характеристика]),коэф_произв[Коэффициент],"",0)} -> 0.8 | P2: {=_xlfn.XLOOKUP(1,(Таблица2[[#This Row],[Тип]]=коэф_произв[Тип])*(Таблица2[[#This Row],[Архитектура]]=коэф_произв[Значение])*('Таблица объектов'!O$1=коэф_произв[Характеристика]),коэф_произв[Коэффициент],"",0)} | R2: {=_xlfn.XLOOKUP(1,(Таблица2[[#This Row],[Тип]]=коэф_произв[Тип])*(Таблица2[[#This Row],[Планировка]]=коэф_произв[Значение])*('Таблица объектов'!Q$1=коэф_произв[Характеристика]),коэф_произв[Коэффициент],"",0)} | T2: {=_xlfn.XLOOKUP(1,(Таблица2[[#This Row],[Тип]]=коэф_произв[Тип])*(Таблица2[[#This Row],[Уровень отделки]]=коэф_произв[Значение])*('Таблица объектов'!S$1=коэф_произв[Характеристика]),коэф_произв[Коэффициент],"",0)} | U2: =IF(Таблица2[[#This Row],[Тип]]="прочие",0.05,PRODUCT(Таблица2[[#This Row],[Уровень отделки коэф.]],Таблица2[[#This Row],[Планировка коэф.]],Таблица2[[#This Row],[Архитектура коэф.]],Таблица2[[#This Row],[Инженерное оснащение коэф.]],Таблица2[[#This Row],[Полы коэф.]],Таблица2[[#This Row],[Конструкция коэф.]],Таблица2[[#This Row],[Наличие / Возможность кран-балки коэф.]],Таблица2[[#This Row],[Высота коэф.]])) -> 0.28728 | V2: =IF(Таблица2[[#This Row],[Тип]]="произв",IF(Таблица2[[#This Row],[Капитальность]]<0.33,"произв класс 4",IF(Таблица2[[#This Row],[Капитальность]]<0.55,"произв класс 3",IF(Таблица2[[#This Row],[Капитальность]]<0.77,"произв класс 2","произв класс 1"))),IF(Таблица2[[#This Row],[Тип]]="гражд",IF(Таблица2[[#This Row],[Капитальность]]<0.33,"гражд класс 4",IF(Таблица2[[#This Row],[Капитальность]]<0.55,"гражд класс 3",IF(Таблица2[[#This Row],[Капитальность]]<0.77,"гражд класс 2","гражд класс 1"))),"прочие")) -> произв класс 4 | W2: =Таблица2[[#This Row],[Площадь, м2]]*Таблица2[[#This Row],[Капитальность]] -> 319.97246 | X2: =IF(AB2<4%,5,IF(AB2<9%,4.5,IF(AB2<14%,4,IF(AB2<24%,3.5,IF(AB2<40%,3,IF(AB2<60%,2.5,IF(AB2<80%,2,1))))))) -> 3 | Y2: =X2*Таблица2[[#This Row],[Площадь, м2]] -> 3341.4 | Z2: =Y2*Таблица2[[#This Row],[Капитальность]] -> 959.91739 | AB2: 0.364
A3: Объект оценки 1 | B3: 9482.1 | C3: Нежилое помещение с пристройкой (Склады) | D3: произв | E3: Более 8 м. (условно - 10 м в среднем) | F3: {=_xlfn.XLOOKUP(1,(Таблица2[[#This Row],[Тип]]=коэф_произв[Тип])*(Таблица2[[#This Row],[Высота]]=коэф_произв[Значение])*('Таблица объектов'!E$1=коэф_произв[Характеристика]),коэф_произв[Коэффициент],"",0)} -> 1 | G3: Да | H3: {=_xlfn.XLOOKUP(1,(Таблица2[[#This Row],[Тип]]=коэф_произв[Тип])*(Таблица2[[#This Row],[Наличие / Возможность кран-балки]]=коэф_произв[Значение])*('Таблица объектов'!G$1=коэф_произв[Характеристика]),коэф_произв[Коэффициент],"",0)} -> 1 | I3: Блочные бескаркасные или металлокаркасные холодные | J3: {=_xlfn.XLOOKUP(1,(Таблица2[[#This Row],[Тип]]=коэф_произв[Тип])*(Таблица2[[#This Row],[Конструкция]]=коэф_произв[Значение])*('Таблица объектов'!I$1=коэф_произв[Характеристика]),коэф_произв[Коэффициент],"",0)} -> 0.5 | K3: Усиленные для техники или специальные | L3: {=_xlfn.XLOOKUP(1,(Таблица2[[#This Row],[Тип]]=коэф_произв[Тип])*(Таблица2[[#This Row],[Полы]]=коэф_произв[Значение])*('Таблица объектов'!K$1=коэф_произв[Характеристика]),коэф_произв[Коэффициент],"",0)} -> 1 | M3: Отсутствует или минимальное (минимальная разводка освещения, водопровода) | N3: {=_xlfn.XLOOKUP(1,(Таблица2[[#This Row],[Тип]]=коэф_произв[Тип])*(Таблица2[[#This Row],[Инженерное оснащение]]=коэф_произв[Значение])*('Таблица объектов'!M$1=коэф_произв[Характеристика]),коэф_произв[Коэффициент],"",0)} -> 0.8 | P3: {=_xlfn.XLOOKUP(1,(Таблица2[[#This Row],[Тип]]=коэф_произв[Тип])*(Таблица2[[#This Row],[Архитектура]]=коэф_произв[Значение])*('Таблица объектов'!O$1=коэф_произв[Характеристика]),коэф_произв[Коэффициент],"",0)} | R3: {=_xlfn.XLOOKUP(1,(Таблица2[[#This Row],[Тип]]=коэф_произв[Тип])*(Таблица2[[#This Row],[Планировка]]=коэф_произв[Значение])*('Таблица объектов'!Q$1=коэф_произв[Характеристика]),коэф_произв[Коэффициент],"",0)} | T3: {=_xlfn.XLOOKUP(1,(Таблица2[[#This Row],[Тип]]=коэф_произв[Тип])*(Таблица2[[#This Row],[Уровень отделки]]=коэф_произв[Значение])*('Таблица объектов'!S$1=коэф_произв[Характеристика]),коэф_произв[Коэффициент],"",0)} | U3: =IF(Таблица2[[#This Row],[Тип]]="прочие",0.05,PRODUCT(Таблица2[[#This Row],[Уровень отделки коэф.]],Таблица2[[#This Row],[Планировка коэф.]],Таблица2[[#This Row],[Архитектура коэф.]],Таблица2[[#This Row],[Инженерное оснащение коэф.]],Таблица2[[#This Row],[Полы коэф.]],Таблица2[[#This Row],[Конструкция коэф.]],Таблица2[[#This Row],[Наличие / Возможность кран-балки коэф.]],Таблица2[[#This Row],[Высота коэф.]])) -> 0.4 | V3: =IF(Таблица2[[#This Row],[Тип]]="произв",IF(Таблица2[[#This Row],[Капитальность]]<0.33,"произв класс 4",IF(Таблица2[[#This Row],[Капитальность]]<0.55,"произв класс 3",IF(Таблица2[[#This Row],[Капитальность]]<0.77,"произв класс 2","произв класс 1"))),IF(Таблица2[[#This Row],[Тип]]="гражд",IF(Таблица2[[#This Row],[Капитальность]]<0.33,"гражд класс 4",IF(Таблица2[[#This Row],[Капитальность]]<0.55,"гражд класс 3",IF(Таблица2[[#This Row],[Капитальность]]<0.77,"гражд класс 2","гражд класс 1"))),"прочие")) -> произв класс 3 | W3: =Таблица2[[#This Row],[Площадь, м2]]*Таблица2[[#This Row],[Капитальность]] -> 3792.84 | X3: =IF(AB3<4%,5,IF(AB3<9%,4.5,IF(AB3<14%,4,IF(AB3<24%,3.5,IF(AB3<40%,3,IF(AB3<60%,2.5,IF(AB3<80%,2,1))))))) -> 5 | Y3: =X3*Таблица2[[#This Row],[Площадь, м2]] -> 47410.5 | Z3: =Y3*Таблица2[[#This Row],[Капитальность]] -> 18964.2 | AB3: 0.01
A4: Объект оценки 1 | B4: 10520 | C4: Нежилое помещение | D4: произв | E4: 5-8 м. | F4: {=_xlfn.XLOOKUP(1,(Таблица2[[#This Row],[Тип]]=коэф_произв[Тип])*(Таблица2[[#This Row],[Высота]]=коэф_произв[Значение])*('Таблица объектов'!E$1=коэф_произв[Характеристика]),коэф_произв[Коэффициент],"",0)} -> 0.8 | G4: Нет | H4: {=_xlfn.XLOOKUP(1,(Таблица2[[#This Row],[Тип]]=коэф_произв[Тип])*(Таблица2[[#This Row],[Наличие / Возможность кран-балки]]=коэф_произв[Значение])*('Таблица объектов'!G$1=коэф_произв[Характеристика]),коэф_произв[Коэффициент],"",0)} -> 0.9 | I4: Блочные бескаркасные или металлокаркасные холодные | J4: {=_xlfn.XLOOKUP(1,(Таблица2[[#This Row],[Тип]]=коэф_произв[Тип])*(Таблица2[[#This Row],[Конструкция]]=коэф_произв[Значение])*('Таблица объектов'!I$1=коэф_произв[Характеристика]),коэф_произв[Коэффициент],"",0)} -> 0.5 | K4: Усиленные для техники или специальные | L4: {=_xlfn.XLOOKUP(1,(Таблица2[[#This Row],[Тип]]=коэф_произв[Тип])*(Таблица2[[#This Row],[Полы]]=коэф_произв[Значение])*('Таблица объектов'!K$1=коэф_произв[Характеристика]),коэф_произв[Коэффициент],"",0)} -> 1 | M4: Отсутствует или минимальное (минимальная разводка освещения, водопровода) | N4: {=_xlfn.XLOOKUP(1,(Таблица2[[#This Row],[Тип]]=коэф_произв[Тип])*(Таблица2[[#This Row],[Инженерное оснащение]]=коэф_произв[Значение])*('Таблица объектов'!M$1=коэф_произв[Характеристика]),коэф_произв[Коэффициент],"",0)} -> 0.8 | P4: {=_xlfn.XLOOKUP(1,(Таблица2[[#This Row],[Тип]]=коэф_произв[Тип])*(Таблица2[[#This Row],[Архитектура]]=коэф_произв[Значение])*('Таблица объектов'!O$1=коэф_произв[Характеристика]),коэф_произв[Коэффициент],"",0)} | R4: {=_xlfn.XLOOKUP(1,(Таблица2[[#This Row],[Тип]]=коэф_произв[Тип])*(Таблица2[[#This Row],[Планировка]]=коэф_произв[Значение])*('Таблица объектов'!Q$1=коэф_произв[Характеристика]),коэф_произв[Коэффициент],"",0)} | T4: {=_xlfn.XLOOKUP(1,(Таблица2[[#This Row],[Тип]]=коэф_произв[Тип])*(Таблица2[[#This Row],[Уровень отделки]]=коэф_произв[Значение])*('Таблица объектов'!S$1=коэф_произв[Характеристика]),коэф_произв[Коэффициент],"",0)} | U4: =IF(Таблица2[[#This Row],[Тип]]="прочие",0.05,PRODUCT(Таблица2[[#This Row],[Уровень отделки коэф.]],Таблица2[[#This Row],[Планировка коэф.]],Таблица2[[#This Row],[Архитектура коэф.]],Таблица2[[#This Row],[Инженерное оснащение коэф.]],Таблица2[[#This Row],[Полы коэф.]],Таблица2[[#This Row],[Конструкция коэф.]],Таблица2[[#This Row],[Наличие / Возможность кран-балки коэф.]],Таблица2[[#This Row],[Высота коэф.]])) -> 0.288 | V4: =IF(Таблица2[[#This Row],[Тип]]="произв",IF(Таблица2[[#This Row],[Капитальность]]<0.33,"произв класс 4",IF(Таблица2[[#This Row],[Капитальность]]<0.55,"произв класс 3",IF(Таблица2[[#This Row],[Капитальность]]<0.77,"произв класс 2","произв класс 1"))),IF(Таблица2[[#This Row],[Тип]]="гражд",IF(Таблица2[[#This Row],[Капитальность]]<0.33,"гражд класс 4",IF(Таблица2[[#This Row],[Капитальность]]<0.55,"гражд класс 3",IF(Таблица2[[#This Row],[Капитальность]]<0.77,"гражд класс 2","гражд класс 1"))),"прочие")) -> произв класс 4 | W4: =Таблица2[[#This Row],[Площадь, м2]]*Таблица2[[#This Row],[Капитальность]] -> 3029.76 | X4: =IF(AB4<4%,5,IF(AB4<9%,4.5,IF(AB4<14%,4,IF(AB4<24%,3.5,IF(AB4<40%,3,IF(AB4<60%,2.5,IF(AB4<80%,2,1))))))) -> 5 | Y4: =X4*Таблица2[[#This Row],[Площадь, м2]] -> 52600 | Z4: =Y4*Таблица2[[#This Row],[Капитальность]] -> 15148.8 | AB4: 0.01
A5: Объект оценки 1 | B5: 155.9 | C5: Нежилое помещение | D5: гражд | E5: До 2,6 м. | F5: {=_xlfn.XLOOKUP(1,(Таблица2[[#This Row],[Тип]]=коэф_произв[Тип])*(Таблица2[[#This Row],[Высота]]=коэф_произв[Значение])*('Таблица объектов'!E$1=коэф_произв[Характеристика]),коэф_произв[Коэффициент],"",0)} -> 0.6 | H5: {=_xlfn.XLOOKUP(1,(Таблица2[[#This Row],[Тип]]=коэф_произв[Тип])*(Таблица2[[#This Row],[Наличие / Возможность кран-балки]]=коэф_произв[Значение])*('Таблица объектов'!G$1=коэф_произв[Характеристика]),коэф_произв[Коэффициент],"",0)} | I5: Капитальная | J5: {=_xlfn.XLOOKUP(1,(Таблица2[[#This Row],[Тип]]=коэф_произв[Тип])*(Таблица2[[#This Row],[Конструкция]]=коэф_произв[Значение])*('Таблица объектов'!I$1=коэф_произв[Характеристика]),коэф_произв[Коэффициент],"",0)} -> 1 | L5: {=_xlfn.XLOOKUP(1,(Таблица2[[#This Row],[Тип]]=коэф_произв[Тип])*(Таблица2[[#This Row],[Полы]]=коэф_произв[Значение])*('Таблица объектов'!K$1=коэф_произв[Характеристика]),коэф_произв[Коэффициент],"",0)} | M5: Стандартное (по всем помещениям разводка освещения, водопровод, канализация) | N5: {=_xlfn.XLOOKUP(1,(Таблица2[[#This Row],[Тип]]=коэф_произв[Тип])*(Таблица2[[#This Row],[Инженерное оснащение]]=коэф_произв[Значение])*('Таблица объектов'!M$1=коэф_произв[Характеристика]),коэф_произв[Коэффициент],"",0)} -> 0.9 | O5: Устаревшая/ Современная | P5: {=_xlfn.XLOOKUP(1,(Таблица2[[#This Row],[Тип]]=коэф_произв[Тип])*(Таблица2[[#This Row],[Архитектура]]=коэф_произв[Значение])*('Таблица объектов'!O$1=коэф_произв[Характеристика]),коэф_произв[Коэффициент],"",0)} -> 0.9 | Q5: Смешанная | R5: {=_xlfn.XLOOKUP(1,(Таблица2[[#This Row],[Тип]]=коэф_произв[Тип])*(Таблица2[[#This Row],[Планировка]]=коэф_произв[Значение])*('Таблица объектов'!Q$1=коэф_произв[Характеристика]),коэф_произв[Коэффициент],"",0)} -> 0.95 | S5: Простая (потолки и стены оштукатурены, окрашены или отделаны дешевыми материалами (МДФ), полы линолеумные | T5: {=_xlfn.XLOOKUP(1,(Таблица2[[#This Row],[Тип]]=коэф_произв[Тип])*(Таблица2[[#This Row],[Уровень отделки]]=коэф_произв[Значение])*('Таблица объектов'!S$1=коэф_произв[Характеристика]),коэф_произв[Коэффициент],"",0)} -> 0.7 | U5: =IF(Таблица2[[#This Row],[Тип]]="прочие",0.05,PRODUCT(Таблица2[[#This Row],[Уровень отделки коэф.]],Таблица2[[#This Row],[Планировка коэф.]],Таблица2[[#This Row],[Архитектура коэф.]],Таблица2[[#This Row],[Инженерное оснащение коэф.]],Таблица2[[#This Row],[Полы коэф.]],Таблица2[[#This Row],[Конструкция коэф.]],Таблица2[[#This Row],[Наличие / Возможность кран-балки коэф.]],Таблица2[[#This Row],[Высота коэф.]])) -> 0.32319 | V5: =IF(Таблица2[[#This Row],[Тип]]="произв",IF(Таблица2[[#This Row],[Капитальность]]<0.33,"произв класс 4",IF(Таблица2[[#This Row],[Капитальность]]<0.55,"произв класс 3",IF(Таблица2[[#This Row],[Капитальность]]<0.77,"произв класс 2","произв класс 1"))),IF(Таблица2[[#This Row],[Тип]]="гражд",IF(Таблица2[[#This Row],[Капитальность]]<0.33,"гражд класс 4",IF(Таблица2[[#This Row],[Капитальность]]<0.55,"гражд класс 3",IF(Таблица2[[#This Row],[Капитальность]]<0.77,"гражд класс 2","гражд класс 1"))),"прочие")) -> гражд класс 4 | W5: =Таблица2[[#This Row],[Площадь, м2]]*Таблица2[[#This Row],[Капитальность]] -> 50.385321 | X5: =IF(AB5<4%,5,IF(AB5<9%,4.5,IF(AB5<14%,4,IF(AB5<24%,3.5,IF(AB5<40%,3,IF(AB5<60%,2.5,IF(AB5<80%,2,1))))))) -> 3 | Y5: =X5*Таблица2[[#This Row],[Площадь, м2]] -> 467.7 | Z5: =Y5*Таблица2[[#This Row],[Капитальность]] -> 151.15596 | AB5: 0.399
A6: Объект оценки 1 | B6: 189.4 | C6: Нежилое помещение | D6: произв | E6: 3-5 м. | F6: {=_xlfn.XLOOKUP(1,(Таблица2[[#This Row],[Тип]]=коэф_произв[Тип])*(Таблица2[[#This Row],[Высота]]=коэф_произв[Значение])*('Таблица объектов'!E$1=коэф_произв[Характеристика]),коэф_произв[Коэффициент],"",0)} -> 0.6 | G6: Нет | H6: {=_xlfn.XLOOKUP(1,(Таблица2[[#This Row],[Тип]]=коэф_произв[Тип])*(Таблица2[[#This Row],[Наличие / Возможность кран-балки]]=коэф_произв[Значение])*('Таблица объектов'!G$1=коэф_произв[Характеристика]),коэф_произв[Коэффициент],"",0)} -> 0.9 | I6: Блочные по железобетонному каркасу, утепленные | J6: {=_xlfn.XLOOKUP(1,(Таблица2[[#This Row],[Тип]]=коэф_произв[Тип])*(Таблица2[[#This Row],[Конструкция]]=коэф_произв[Значение])*('Таблица объектов'!I$1=коэф_произв[Характеристика]),коэф_произв[Коэффициент],"",0)} -> 1 | K6: Простые | L6: {=_xlfn.XLOOKUP(1,(Таблица2[[#This Row],[Тип]]=коэф_произв[Тип])*(Таблица2[[#This Row],[Полы]]=коэф_произв[Значение])*('Таблица объектов'!K$1=коэф_произв[Характеристика]),коэф_произв[Коэффициент],"",0)} -> 0.9 | M6: Стандартное (по всем помещениям разводка освещения, водопровод, канализация) | N6: {=_xlfn.XLOOKUP(1,(Таблица2[[#This Row],[Тип]]=коэф_произв[Тип])*(Таблица2[[#This Row],[Инженерное оснащение]]=коэф_произв[Значение])*('Таблица объектов'!M$1=коэф_произв[Характеристика]),коэф_произв[Коэффициент],"",0)} -> 0.9 | P6: {=_xlfn.XLOOKUP(1,(Таблица2[[#This Row],[Тип]]=коэф_произв[Тип])*(Таблица2[[#This Row],[Архитектура]]=коэф_произв[Значение])*('Таблица объектов'!O$1=коэф_произв[Характеристика]),коэф_произв[Коэффициент],"",0)} | R6: {=_xlfn.XLOOKUP(1,(Таблица2[[#This Row],[Тип]]=коэф_произв[Тип])*(Таблица2[[#This Row],[Планировка]]=коэф_произв[Значение])*('Таблица объектов'!Q$1=коэф_произв[Характеристика]),коэф_произв[Коэффициент],"",0)} | T6: {=_xlfn.XLOOKUP(1,(Таблица2[[#This Row],[Тип]]=коэф_произв[Тип])*(Таблица2[[#This Row],[Уровень отделки]]=коэф_произв[Значение])*('Таблица объектов'!S$1=коэф_произв[Характеристика]),коэф_произв[Коэффициент],"",0)} | U6: =IF(Таблица2[[#This Row],[Тип]]="прочие",0.05,PRODUCT(Таблица2[[#This Row],[Уровень отделки коэф.]],Таблица2[[#This Row],[Планировка коэф.]],Таблица2[[#This Row],[Архитектура коэф.]],Таблица2[[#This Row],[Инженерное оснащение коэф.]],Таблица2[[#This Row],[Полы коэф.]],Таблица2[[#This Row],[Конструкция коэф.]],Таблица2[[#This Row],[Наличие / Возможность кран-балки коэф.]],Таблица2[[#This Row],[Высота коэф.]])) -> 0.4374 | V6: =IF(Таблица2[[#This Row],[Тип]]="произв",IF(Таблица2[[#This Row],[Капитальность]]<0.33,"произв класс 4",IF(Таблица2[[#This Row],[Капитальность]]<0.55,"произв класс 3",IF(Таблица2[[#This Row],[Капитальность]]<0.77,"произв класс 2","произв класс 1"))),IF(Таблица2[[#This Row],[Тип]]="гражд",IF(Таблица2[[#This Row],[Капитальность]]<0.33,"гражд класс 4",IF(Таблица2[[#This Row],[Капитальность]]<0.55,"гражд класс 3",IF(Таблица2[[#This Row],[Капитальность]]<0.77,"гражд класс 2","гражд класс 1"))),"прочие")) -> произв класс 3 | W6: =Таблица2[[#This Row],[Площадь, м2]]*Таблица2[[#This Row],[Капитальность]] -> 82.84356 | X6: =IF(AB6<4%,5,IF(AB6<9%,4.5,IF(AB6<14%,4,IF(AB6<24%,3.5,IF(AB6<40%,3,IF(AB6<60%,2.5,IF(AB6<80%,2,1))))))) -> 3 | Y6: =X6*Таблица2[[#This Row],[Площадь, м2]] -> 568.2 | Z6: =Y6*Таблица2[[#This Row],[Капитальность]] -> 248.53068 | AB6: 0.369
A7: Объект оценки 2 | B7: 4736.5 | C7: Нежилое помещение (склады) | D7: произв | E7: Более 8 м. (условно - 10 м в среднем) | F7: {=_xlfn.XLOOKUP(1,(Таблица2[[#This Row],[Тип]]=коэф_произв[Тип])*(Таблица2[[#This Row],[Высота]]=коэф_произв[Значение])*('Таблица объектов'!E$1=коэф_произв[Характеристика]),коэф_произв[Коэффициент],"",0)} -> 1 | G7: Да | H7: {=_xlfn.XLOOKUP(1,(Таблица2[[#This Row],[Тип]]=коэф_произв[Тип])*(Таблица2[[#This Row],[Наличие / Возможность кран-балки]]=коэф_произв[Значение])*('Таблица объектов'!G$1=коэф_произв[Характеристика]),коэф_произв[Коэффициент],"",0)} -> 1 | I7: Блочные бескаркасные или металлокаркасные холодные | J7: {=_xlfn.XLOOKUP(1,(Таблица2[[#This Row],[Тип]]=коэф_произв[Тип])*(Таблица2[[#This Row],[Конструкция]]=коэф_произв[Значение])*('Таблица объектов'!I$1=коэф_произв[Характеристика]),коэф_произв[Коэффициент],"",0)} -> 0.5 | K7: Усиленные для техники или специальные | L7: {=_xlfn.XLOOKUP(1,(Таблица2[[#This Row],[Тип]]=коэф_произв[Тип])*(Таблица2[[#This Row],[Полы]]=коэф_произв[Значение])*('Таблица объектов'!K$1=коэф_произв[Характеристика]),коэф_произв[Коэффициент],"",0)} -> 1 | M7: Отсутствует или минимальное (минимальная разводка освещения, водопровода) | N7: {=_xlfn.XLOOKUP(1,(Таблица2[[#This Row],[Тип]]=коэф_произв[Тип])*(Таблица2[[#This Row],[Инженерное оснащение]]=коэф_произв[Значение])*('Таблица объектов'!M$1=коэф_произв[Характеристика]),коэф_произв[Коэффициент],"",0)} -> 0.8 | P7: {=_xlfn.XLOOKUP(1,(Таблица2[[#This Row],[Тип]]=коэф_произв[Тип])*(Таблица2[[#This Row],[Архитектура]]=коэф_произв[Значение])*('Таблица объектов'!O$1=коэф_произв[Характеристика]),коэф_произв[Коэффициент],"",0)} | R7: {=_xlfn.XLOOKUP(1,(Таблица2[[#This Row],[Тип]]=коэф_произв[Тип])*(Таблица2[[#This Row],[Планировка]]=коэф_произв[Значение])*('Таблица объектов'!Q$1=коэф_произв[Характеристика]),коэф_произв[Коэффициент],"",0)} | T7: {=_xlfn.XLOOKUP(1,(Таблица2[[#This Row],[Тип]]=коэф_произв[Тип])*(Таблица2[[#This Row],[Уровень отделки]]=коэф_произв[Значение])*('Таблица объектов'!S$1=коэф_произв[Характеристика]),коэф_произв[Коэффициент],"",0)} | U7: =IF(Таблица2[[#This Row],[Тип]]="прочие",0.05,PRODUCT(Таблица2[[#This Row],[Уровень отделки коэф.]],Таблица2[[#This Row],[Планировка коэф.]],Таблица2[[#This Row],[Архитектура коэф.]],Таблица2[[#This Row],[Инженерное оснащение коэф.]],Таблица2[[#This Row],[Полы коэф.]],Таблица2[[#This Row],[Конструкция коэф.]],Таблица2[[#This Row],[Наличие / Возможность кран-балки коэф.]],Таблица2[[#This Row],[Высота коэф.]])) -> 0.4 | V7: =IF(Таблица2[[#This Row],[Тип]]="произв",IF(Таблица2[[#This Row],[Капитальность]]<0.33,"произв класс 4",IF(Таблица2[[#This Row],[Капитальность]]<0.55,"произв класс 3",IF(Таблица2[[#This Row],[Капитальность]]<0.77,"произв класс 2","произв класс 1"))),IF(Таблица2[[#This Row],[Тип]]="гражд",IF(Таблица2[[#This Row],[Капитальность]]<0.33,"гражд класс 4",IF(Таблица2[[#This Row],[Капитальность]]<0.55,"гражд класс 3",IF(Таблица2[[#This Row],[Капитальность]]<0.77,"гражд класс 2","гражд класс 1"))),"прочие")) -> произв класс 3 | W7: =Таблица2[[#This Row],[Площадь, м2]]*Таблица2[[#This Row],[Капитальность]] -> 1894.6 | X7: =IF(AB7<4%,5,IF(AB7<9%,4.5,IF(AB7<14%,4,IF(AB7<24%,3.5,IF(AB7<40%,3,IF(AB7<60%,2.5,IF(AB7<80%,2,1))))))) -> 5 | Y7: =X7*Таблица2[[#This Row],[Площадь, м2]] -> 23682.5 | Z7: =Y7*Таблица2[[#This Row],[Капитальность]] -> 9473 | AB7: 0.005
A8: Объект оценки 2 | B8: 14304 | C8: Нежилое помещение с пристройко (склады) | D8: произв | E8: Более 8 м. (условно - 10 м в среднем) | F8: {=_xlfn.XLOOKUP(1,(Таблица2[[#This Row],[Тип]]=коэф_произв[Тип])*(Таблица2[[#This Row],[Высота]]=коэф_произв[Значение])*('Таблица объектов'!E$1=коэф_произв[Характеристика]),коэф_произв[Коэффициент],"",0)} -> 1 | G8: Да | H8: {=_xlfn.XLOOKUP(1,(Таблица2[[#This Row],[Тип]]=коэф_произв[Тип])*(Таблица2[[#This Row],[Наличие / Возможность кран-балки]]=коэф_произв[Значение])*('Таблица объектов'!G$1=коэф_произв[Характеристика]),коэф_произв[Коэффициент],"",0)} -> 1 | I8: Блочные бескаркасные или металлокаркасные холодные | J8: {=_xlfn.XLOOKUP(1,(Таблица2[[#This Row],[Тип]]=коэф_произв[Тип])*(Таблица2[[#This Row],[Конструкция]]=коэф_произв[Значение])*('Таблица объектов'!I$1=коэф_произв[Характеристика]),коэф_произв[Коэффициент],"",0)} -> 0.5 | K8: Усиленные для техники или специальные | L8: {=_xlfn.XLOOKUP(1,(Таблица2[[#This Row],[Тип]]=коэф_произв[Тип])*(Таблица2[[#This Row],[Полы]]=коэф_произв[Значение])*('Таблица объектов'!K$1=коэф_произв[Характеристика]),коэф_произв[Коэффициент],"",0)} -> 1 | M8: Отсутствует или минимальное (минимальная разводка освещения, водопровода) | N8: {=_xlfn.XLOOKUP(1,(Таблица2[[#This Row],[Тип]]=коэф_произв[Тип])*(Таблица2[[#This Row],[Инженерное оснащение]]=коэф_произв[Значение])*('Таблица объектов'!M$1=коэф_произв[Характеристика]),коэф_произв[Коэффициент],"",0)} -> 0.8 | P8: {=_xlfn.XLOOKUP(1,(Таблица2[[#This Row],[Тип]]=коэф_произв[Тип])*(Таблица2[[#This Row],[Архитектура]]=коэф_произв[Значение])*('Таблица объектов'!O$1=коэф_произв[Характеристика]),коэф_произв[Коэффициент],"",0)} | R8: {=_xlfn.XLOOKUP(1,(Таблица2[[#This Row],[Тип]]=коэф_произв[Тип])*(Таблица2[[#This Row],[Планировка]]=коэф_произв[Значение])*('Таблица объектов'!Q$1=коэф_произв[Характеристика]),коэф_произв[Коэффициент],"",0)} | T8: {=_xlfn.XLOOKUP(1,(Таблица2[[#This Row],[Тип]]=коэф_произв[Тип])*(Таблица2[[#This Row],[Уровень отделки]]=коэф_произв[Значение])*('Таблица объектов'!S$1=коэф_произв[Характеристика]),коэф_произв[Коэффициент],"",0)} | U8: =IF(Таблица2[[#This Row],[Тип]]="прочие",0.05,PRODUCT(Таблица2[[#This Row],[Уровень отделки коэф.]],Таблица2[[#This Row],[Планировка коэф.]],Таблица2[[#This Row],[Архитектура коэф.]],Таблица2[[#This Row],[Инженерное оснащение коэф.]],Таблица2[[#This Row],[Полы коэф.]],Таблица2[[#This Row],[Конструкция коэф.]],Таблица2[[#This Row],[Наличие / Возможность кран-балки коэф.]],Таблица2[[#This Row],[Высота коэф.]])) -> 0.4 | V8: =IF(Таблица2[[#This Row],[Тип]]="произв",IF(Таблица2[[#This Row],[Капитальность]]<0.33,"произв класс 4",IF(Таблица2[[#This Row],[Капитальность]]<0.55,"произв класс 3",IF(Таблица2[[#This Row],[Капитальность]]<0.77,"произв класс 2","произв класс 1"))),IF(Таблица2[[#This Row],[Тип]]="гражд",IF(Таблица2[[#This Row],[Капитальность]]<0.33,"гражд класс 4",IF(Таблица2[[#This Row],[Капитальность]]<0.55,"гражд класс 3",IF(Таблица2[[#This Row],[Капитальность]]<0.77,"гражд класс 2","гражд класс 1"))),"прочие")) -> произв класс 3 | W8: =Таблица2[[#This Row],[Площадь, м2]]*Таблица2[[#This Row],[Капитальность]] -> 5721.6 | X8: =IF(AB8<4%,5,IF(AB8<9%,4.5,IF(AB8<14%,4,IF(AB8<24%,3.5,IF(AB8<40%,3,IF(AB8<60%,2.5,IF(AB8<80%,2,1))))))) -> 5 | Y8: =X8*Таблица2[[#This Row],[Площадь, м2]] -> 71520 | Z8: =Y8*Таблица2[[#This Row],[Капитальность]] -> 28608 | AB8: 0.003
A9: Объект оценки 2 | B9: 949.5 | C9: Нежилое помещение с пристройко (склады) | D9: гражд | E9: 2,6-3,2 м. | F9: {=_xlfn.XLOOKUP(1,(Таблица2[[#This Row],[Тип]]=коэф_произв[Тип])*(Таблица2[[#This Row],[Высота]]=коэф_произв[Значение])*('Таблица объектов'!E$1=коэф_произв[Характеристика]),коэф_произв[Коэффициент],"",0)} -> 0.7 | H9: {=_xlfn.XLOOKUP(1,(Таблица2[[#This Row],[Тип]]=коэф_произв[Тип])*(Таблица2[[#This Row],[Наличие / Возможность кран-балки]]=коэф_произв[Значение])*('Таблица объектов'!G$1=коэф_произв[Характеристика]),коэф_произв[Коэффициент],"",0)} | I9: Капитальная | J9: {=_xlfn.XLOOKUP(1,(Таблица2[[#This Row],[Тип]]=коэф_произв[Тип])*(Таблица2[[#This Row],[Конструкция]]=коэф_произв[Значение])*('Таблица объектов'!I$1=коэф_произв[Характеристика]),коэф_произв[Коэффициент],"",0)} -> 1 | L9: {=_xlfn.XLOOKUP(1,(Таблица2[[#This Row],[Тип]]=коэф_произв[Тип])*(Таблица2[[#This Row],[Полы]]=коэф_произв[Значение])*('Таблица объектов'!K$1=коэф_произв[Характеристика]),коэф_произв[Коэффициент],"",0)} | M9: Стандартное (по всем помещениям разводка освещения, водопровод, канализация) | N9: {=_xlfn.XLOOKUP(1,(Таблица2[[#This Row],[Тип]]=коэф_произв[Тип])*(Таблица2[[#This Row],[Инженерное оснащение]]=коэф_произв[Значение])*('Таблица объектов'!M$1=коэф_произв[Характеристика]),коэф_произв[Коэффициент],"",0)} -> 0.9 | O9: Современная | P9: {=_xlfn.XLOOKUP(1,(Таблица2[[#This Row],[Тип]]=коэф_произв[Тип])*(Таблица2[[#This Row],[Архитектура]]=коэф_произв[Значение])*('Таблица объектов'!O$1=коэф_произв[Характеристика]),коэф_произв[Коэффициент],"",0)} -> 1 | Q9: Смешанная | R9: {=_xlfn.XLOOKUP(1,(Таблица2[[#This Row],[Тип]]=коэф_произв[Тип])*(Таблица2[[#This Row],[Планировка]]=коэф_произв[Значение])*('Таблица объектов'!Q$1=коэф_произв[Характеристика]),коэф_произв[Коэффициент],"",0)} -> 0.95 | S9: Стандартная (современная отделка с применением актуальных материалов) | T9: {=_xlfn.XLOOKUP(1,(Таблица2[[#This Row],[Тип]]=коэф_произв[Тип])*(Таблица2[[#This Row],[Уровень отделки]]=коэф_произв[Значение])*('Таблица объектов'!S$1=коэф_произв[Характеристика]),коэф_произв[Коэффициент],"",0)} -> 0.8 | U9: =IF(Таблица2[[#This Row],[Тип]]="прочие",0.05,PRODUCT(Таблица2[[#This Row],[Уровень отделки коэф.]],Таблица2[[#This Row],[Планировка коэф.]],Таблица2[[#This Row],[Архитектура коэф.]],Таблица2[[#This Row],[Инженерное оснащение коэф.]],Таблица2[[#This Row],[Полы коэф.]],Таблица2[[#This Row],[Конструкция коэф.]],Таблица2[[#This Row],[Наличие / Возможность кран-балки коэф.]],Таблица2[[#This Row],[Высота коэф.]])) -> 0.4788 | V9: =IF(Таблица2[[#This Row],[Тип]]="произв",IF(Таблица2[[#This Row],[Капитальность]]<0.33,"произв класс 4",IF(Таблица2[[#This Row],[Капитальность]]<0.55,"произв класс 3",IF(Таблица2[[#This Row],[Капитальность]]<0.77,"произв класс 2","произв класс 1"))),IF(Таблица2[[#This Row],[Тип]]="гражд",IF(Таблица2[[#This Row],[Капитальность]]<0.33,"гражд класс 4",IF(Таблица2[[#This Row],[Капитальность]]<0.55,"гражд класс 3",IF(Таблица2[[#This Row],[Капитальность]]<0.77,"гражд класс 2","гражд класс 1"))),"прочие")) -> гражд класс 3 | W9: =Таблица2[[#This Row],[Площадь, м2]]*Таблица2[[#This Row],[Капитальность]] -> 454.6206 | X9: =IF(AB9<4%,5,IF(AB9<9%,4.5,IF(AB9<14%,4,IF(AB9<24%,3.5,IF(AB9<40%,3,IF(AB9<60%,2.5,IF(AB9<80%,2,1))))))) -> 5 | Y9: =X9*Таблица2[[#This Row],[Площадь, м2]] -> 4747.5 | Z9: =Y9*Таблица2[[#This Row],[Капитальность]] -> 2273.103 | AB9: 0.001
A10: Объект оценки 3 | B10: 4393.4 | C10: Нежилое помещение швейный цех | D10: гражд | E10: 2,6-3,2 м. | F10: {=_xlfn.XLOOKUP(1,(Таблица2[[#This Row],[Тип]]=коэф_произв[Тип])*(Таблица2[[#This Row],[Высота]]=коэф_произв[Значение])*('Таблица объектов'!E$1=коэф_произв[Характеристика]),коэф_произв[Коэффициент],"",0)} -> 0.7 | H10: {=_xlfn.XLOOKUP(1,(Таблица2[[#This Row],[Тип]]=коэф_произв[Тип])*(Таблица2[[#This Row],[Наличие / Возможность кран-балки]]=коэф_произв[Значение])*('Таблица объектов'!G$1=коэф_произв[Характеристика]),коэф_произв[Коэффициент],"",0)} | I10: Капитальная | J10: {=_xlfn.XLOOKUP(1,(Таблица2[[#This Row],[Тип]]=коэф_произв[Тип])*(Таблица2[[#This Row],[Конструкция]]=коэф_произв[Значение])*('Таблица объектов'!I$1=коэф_произв[Характеристика]),коэф_произв[Коэффициент],"",0)} -> 1 | L10: {=_xlfn.XLOOKUP(1,(Таблица2[[#This Row],[Тип]]=коэф_произв[Тип])*(Таблица2[[#This Row],[Полы]]=коэф_произв[Значение])*('Таблица объектов'!K$1=коэф_произв[Характеристика]),коэф_произв[Коэффициент],"",0)} | M10: Стандартное (по всем помещениям разводка освещения, водопровод, канализация) | N10: {=_xlfn.XLOOKUP(1,(Таблица2[[#This Row],[Тип]]=коэф_произв[Тип])*(Таблица2[[#This Row],[Инженерное оснащение]]=коэф_произв[Значение])*('Таблица объектов'!M$1=коэф_произв[Характеристика]),коэф_произв[Коэффициент],"",0)} -> 0.9 | O10: Устаревшая | P10: {=_xlfn.XLOOKUP(1,(Таблица2[[#This Row],[Тип]]=коэф_произв[Тип])*(Таблица2[[#This Row],[Архитектура]]=коэф_произв[Значение])*('Таблица объектов'!O$1=коэф_произв[Характеристика]),коэф_произв[Коэффициент],"",0)} -> 0.8 | Q10: Смешанная | R10: {=_xlfn.XLOOKUP(1,(Таблица2[[#This Row],[Тип]]=коэф_произв[Тип])*(Таблица2[[#This Row],[Планировка]]=коэф_произв[Значение])*('Таблица объектов'!Q$1=коэф_произв[Характеристика]),коэф_произв[Коэффициент],"",0)} -> 0.95 | S10: Простая (потолки и стены оштукатурены, окрашены или отделаны дешевыми материалами (МДФ), полы линолеумные | T10: {=_xlfn.XLOOKUP(1,(Таблица2[[#This Row],[Тип]]=коэф_произв[Тип])*(Таблица2[[#This Row],[Уровень отделки]]=коэф_произв[Значение])*('Таблица объектов'!S$1=коэф_произв[Характеристика]),коэф_произв[Коэффициент],"",0)} -> 0.7 | U10: =IF(Таблица2[[#This Row],[Тип]]="прочие",0.05,PRODUCT(Таблица2[[#This Row],[Уровень отделки коэф.]],Таблица2[[#This Row],[Планировка коэф.]],Таблица2[[#This Row],[Архитектура коэф.]],Таблица2[[#This Row],[Инженерное оснащение коэф.]],Таблица2[[#This Row],[Полы коэф.]],Таблица2[[#This Row],[Конструкция коэф.]],Таблица2[[#This Row],[Наличие / Возможность кран-балки коэф.]],Таблица2[[#This Row],[Высота коэф.]])) -> 0.33516 | V10: =IF(Таблица2[[#This Row],[Тип]]="произв",IF(Таблица2[[#This Row],[Капитальность]]<0.33,"произв класс 4",IF(Таблица2[[#This Row],[Капитальность]]<0.55,"произв класс 3",IF(Таблица2[[#This Row],[Капитальность]]<0.77,"произв класс 2","произв класс 1"))),IF(Таблица2[[#This Row],[Тип]]="гражд",IF(Таблица2[[#This Row],[Капитальность]]<0.33,"гражд класс 4",IF(Таблица2[[#This Row],[Капитальность]]<0.55,"гражд класс 3",IF(Таблица2[[#This Row],[Капитальность]]<0.77,"гражд класс 2","гражд класс 1"))),"прочие")) -> гражд класс 3 | W10: =Таблица2[[#This Row],[Площадь, м2]]*Таблица2[[#This Row],[Капитальность]] -> 1472.4919 | X10: =IF(AB10<4%,5,IF(AB10<9%,4.5,IF(AB10<14%,4,IF(AB10<24%,3.5,IF(AB10<40%,3,IF(AB10<60%,2.5,IF(AB10<80%,2,1))))))) -> 2.5 | Y10: =X10*Таблица2[[#This Row],[Площадь, м2]] -> 10983.5 | Z10: =Y10*Таблица2[[#This Row],[Капитальность]] -> 3681.2299 | AB10: 0.462
A11: Объект оценки 3 | B11: 11110.7 | C11: Нежилое помещение склад | D11: произв | E11: 5-8 м. | F11: {=_xlfn.XLOOKUP(1,(Таблица2[[#This Row],[Тип]]=коэф_произв[Тип])*(Таблица2[[#This Row],[Высота]]=коэф_произв[Значение])*('Таблица объектов'!E$1=коэф_произв[Характеристика]),коэф_произв[Коэффициент],"",0)} -> 0.8 | G11: Не установлено (по умолчанию) | H11: {=_xlfn.XLOOKUP(1,(Таблица2[[#This Row],[Тип]]=коэф_произв[Тип])*(Таблица2[[#This Row],[Наличие / Возможность кран-балки]]=коэф_произв[Значение])*('Таблица объектов'!G$1=коэф_произв[Характеристика]),коэф_произв[Коэффициент],"",0)} -> 0.95 | I11: Блочные по железобетонному каркасу, без утепления | J11: {=_xlfn.XLOOKUP(1,(Таблица2[[#This Row],[Тип]]=коэф_произв[Тип])*(Таблица2[[#This Row],[Конструкция]]=коэф_произв[Значение])*('Таблица объектов'!I$1=коэф_произв[Характеристика]),коэф_произв[Коэффициент],"",0)} -> 0.7 | K11: Простые | L11: {=_xlfn.XLOOKUP(1,(Таблица2[[#This Row],[Тип]]=коэф_произв[Тип])*(Таблица2[[#This Row],[Полы]]=коэф_произв[Значение])*('Таблица объектов'!K$1=коэф_произв[Характеристика]),коэф_произв[Коэффициент],"",0)} -> 0.9 | M11: Стандартное (по всем помещениям разводка освещения, водопровод, канализация) | N11: {=_xlfn.XLOOKUP(1,(Таблица2[[#This Row],[Тип]]=коэф_произв[Тип])*(Таблица2[[#This Row],[Инженерное оснащение]]=коэф_произв[Значение])*('Таблица объектов'!M$1=коэф_произв[Характеристика]),коэф_произв[Коэффициент],"",0)} -> 0.9 | P11: {=_xlfn.XLOOKUP(1,(Таблица2[[#This Row],[Тип]]=коэф_произв[Тип])*(Таблица2[[#This Row],[Архитектура]]=коэф_произв[Значение])*('Таблица объектов'!O$1=коэф_произв[Характеристика]),коэф_произв[Коэффициент],"",0)} | R11: {=_xlfn.XLOOKUP(1,(Таблица2[[#This Row],[Тип]]=коэф_произв[Тип])*(Таблица2[[#This Row],[Планировка]]=коэф_произв[Значение])*('Таблица объектов'!Q$1=коэф_произв[Характеристика]),коэф_произв[Коэффициент],"",0)} | T11: {=_xlfn.XLOOKUP(1,(Таблица2[[#This Row],[Тип]]=коэф_произв[Тип])*(Таблица2[[#This Row],[Уровень отделки]]=коэф_произв[Значение])*('Таблица объектов'!S$1=коэф_произв[Характеристика]),коэф_произв[Коэффициент],"",0)} | U11: =IF(Таблица2[[#This Row],[Тип]]="прочие",0.05,PRODUCT(Таблица2[[#This Row],[Уровень отделки коэф.]],Таблица2[[#This Row],[Планировка коэф.]],Таблица2[[#This Row],[Архитектура коэф.]],Таблица2[[#This Row],[Инженерное оснащение коэф.]],Таблица2[[#This Row],[Полы коэф.]],Таблица2[[#This Row],[Конструкция коэф.]],Таблица2[[#This Row],[Наличие / Возможность кран-балки коэф.]],Таблица2[[#This Row],[Высота коэф.]])) -> 0.43092 | V11: =IF(Таблица2[[#This Row],[Тип]]="произв",IF(Таблица2[[#This Row],[Капитальность]]<0.33,"произв класс 4",IF(Таблица2[[#This Row],[Капитальность]]<0.55,"произв класс 3",IF(Таблица2[[#This Row],[Капитальность]]<0.77,"произв класс 2","произв класс 1"))),IF(Таблица2[[#This Row],[Тип]]="гражд",IF(Таблица2[[#This Row],[Капитальность]]<0.33,"гражд класс 4",IF(Таблица2[[#This Row],[Капитальность]]<0.55,"гражд класс 3",IF(Таблица2[[#This Row],[Капитальность]]<0.77,"гражд класс 2","гражд класс 1"))),"прочие")) -> произв класс 3 | W11: =Таблица2[[#This Row],[Площадь, м2]]*Таблица2[[#This Row],[Капитальность]] -> 4787.8228 | X11: =IF(AB11<4%,5,IF(AB11<9%,4.5,IF(AB11<14%,4,IF(AB11<24%,3.5,IF(AB11<40%,3,IF(AB11<60%,2.5,IF(AB11<80%,2,1))))))) -> 2.5 | Y11: =X11*Таблица2[[#This Row],[Площадь, м2]] -> 27776.75 | Z11: =Y11*Таблица2[[#This Row],[Капитальность]] -> 11969.557 | AB11: 0.492
A12: Объект оценки 3 | B12: 41.6 | C12: Нежилое помещение (гараж) | D12: гражд | E12: До 2,6 м. | F12: {=_xlfn.XLOOKUP(1,(Таблица2[[#This Row],[Тип]]=коэф_произв[Тип])*(Таблица2[[#This Row],[Высота]]=коэф_произв[Значение])*('Таблица объектов'!E$1=коэф_произв[Характеристика]),коэф_произв[Коэффициент],"",0)} -> 0.6 | H12: {=_xlfn.XLOOKUP(1,(Таблица2[[#This Row],[Тип]]=коэф_произв[Тип])*(Таблица2[[#This Row],[Наличие / Возможность кран-балки]]=коэф_произв[Значение])*('Таблица объектов'!G$1=коэф_произв[Характеристика]),коэф_произв[Коэффициент],"",0)} | I12: Капитальная | J12: {=_xlfn.XLOOKUP(1,(Таблица2[[#This Row],[Тип]]=коэф_произв[Тип])*(Таблица2[[#This Row],[Конструкция]]=коэф_произв[Значение])*('Таблица объектов'!I$1=коэф_произв[Характеристика]),коэф_произв[Коэффициент],"",0)} -> 1 | L12: {=_xlfn.XLOOKUP(1,(Таблица2[[#This Row],[Тип]]=коэф_произв[Тип])*(Таблица2[[#This Row],[Полы]]=коэф_произв[Значение])*('Таблица объектов'!K$1=коэф_произв[Характеристика]),коэф_произв[Коэффициент],"",0)} | M12: Отсутствует или минимальное (минимальная разводка освещения, водопровода) | N12: {=_xlfn.XLOOKUP(1,(Таблица2[[#This Row],[Тип]]=коэф_произв[Тип])*(Таблица2[[#This Row],[Инженерное оснащение]]=коэф_произв[Значение])*('Таблица объектов'!M$1=коэф_произв[Характеристика]),коэф_произв[Коэффициент],"",0)} -> 0.8 | O12: Устаревшая | P12: {=_xlfn.XLOOKUP(1,(Таблица2[[#This Row],[Тип]]=коэф_произв[Тип])*(Таблица2[[#This Row],[Архитектура]]=коэф_произв[Значение])*('Таблица объектов'!O$1=коэф_произв[Характеристика]),коэф_произв[Коэффициент],"",0)} -> 0.8 | Q12: Свободная | R12: {=_xlfn.XLOOKUP(1,(Таблица2[[#This Row],[Тип]]=коэф_произв[Тип])*(Таблица2[[#This Row],[Планировка]]=коэф_произв[Значение])*('Таблица объектов'!Q$1=коэф_произв[Характеристика]),коэф_произв[Коэффициент],"",0)} -> 0.9 | S12: Без отделки (потолки не подшиты или не отделаны, стены неоштукатурены или неокрашены, полы без покрытий со стяжкой или без) | T12: {=_xlfn.XLOOKUP(1,(Таблица2[[#This Row],[Тип]]=коэф_произв[Тип])*(Таблица2[[#This Row],[Уровень отделки]]=коэф_произв[Значение])*('Таблица объектов'!S$1=коэф_произв[Характеристика]),коэф_произв[Коэффициент],"",0)} -> 0.5 | U12: =IF(Таблица2[[#This Row],[Тип]]="прочие",0.05,PRODUCT(Таблица2[[#This Row],[Уровень отделки коэф.]],Таблица2[[#This Row],[Планировка коэф.]],Таблица2[[#This Row],[Архитектура коэф.]],Таблица2[[#This Row],[Инженерное оснащение коэф.]],Таблица2[[#This Row],[Полы коэф.]],Таблица2[[#This Row],[Конструкция коэф.]],Таблица2[[#This Row],[Наличие / Возможность кран-балки коэф.]],Таблица2[[#This Row],[Высота коэф.]])) -> 0.1728 | V12: =IF(Таблица2[[#This Row],[Тип]]="произв",IF(Таблица2[[#This Row],[Капитальность]]<0.33,"произв класс 4",IF(Таблица2[[#This Row],[Капитальность]]<0.55,"произв класс 3",IF(Таблица2[[#This Row],[Капитальность]]<0.77,"произв класс 2","произв класс 1"))),IF(Таблица2[[#This Row],[Тип]]="гражд",IF(Таблица2[[#This Row],[Капитальность]]<0.33,"гражд класс 4",IF(Таблица2[[#This Row],[Капитальность]]<0.55,"гражд класс 3",IF(Таблица2[[#This Row],[Капитальность]]<0.77,"гражд класс 2","гражд класс 1"))),"прочие")) -> гражд класс 4 | W12: =Таблица2[[#This Row],[Площадь, м2]]*Таблица2[[#This Row],[Капитальность]] -> 7.18848 | X12: =IF(AB12<4%,5,IF(AB12<9%,4.5,IF(AB12<14%,4,IF(AB12<24%,3.5,IF(AB12<40%,3,IF(AB12<60%,2.5,IF(AB12<80%,2,1))))))) -> 2.5 | Y12: =X12*Таблица2[[#This Row],[Площадь, м2]] -> 104 | Z12: =Y12*Таблица2[[#This Row],[Капитальность]] -> 17.9712 | AB12: 0.555
A13: Объект оценки 3 | B13: 58.5 | C13: Нежилое помещение | D13: произв | E13: 3-5 м. | F13: {=_xlfn.XLOOKUP(1,(Таблица2[[#This Row],[Тип]]=коэф_произв[Тип])*(Таблица2[[#This Row],[Высота]]=коэф_произв[Значение])*('Таблица объектов'!E$1=коэф_произв[Характеристика]),коэф_произв[Коэффициент],"",0)} -> 0.6 | G13: Нет | H13: {=_xlfn.XLOOKUP(1,(Таблица2[[#This Row],[Тип]]=коэф_произв[Тип])*(Таблица2[[#This Row],[Наличие / Возможность кран-балки]]=коэф_произв[Значение])*('Таблица объектов'!G$1=коэф_произв[Характеристика]),коэф_произв[Коэффициент],"",0)} -> 0.9 | I13: Блочные по железобетонному каркасу, без утепления | J13: {=_xlfn.XLOOKUP(1,(Таблица2[[#This Row],[Тип]]=коэф_произв[Тип])*(Таблица2[[#This Row],[Конструкция]]=коэф_произв[Значение])*('Таблица объектов'!I$1=коэф_произв[Характеристика]),коэф_произв[Коэффициент],"",0)} -> 0.7 | K13: Простые | L13: {=_xlfn.XLOOKUP(1,(Таблица2[[#This Row],[Тип]]=коэф_произв[Тип])*(Таблица2[[#This Row],[Полы]]=коэф_произв[Значение])*('Таблица объектов'!K$1=коэф_произв[Характеристика]),коэф_произв[Коэффициент],"",0)} -> 0.9 | M13: Отсутствует или минимальное (минимальная разводка освещения, водопровода) | N13: {=_xlfn.XLOOKUP(1,(Таблица2[[#This Row],[Тип]]=коэф_произв[Тип])*(Таблица2[[#This Row],[Инженерное оснащение]]=коэф_произв[Значение])*('Таблица объектов'!M$1=коэф_произв[Характеристика]),коэф_произв[Коэффициент],"",0)} -> 0.8 | P13: {=_xlfn.XLOOKUP(1,(Таблица2[[#This Row],[Тип]]=коэф_произв[Тип])*(Таблица2[[#This Row],[Архитектура]]=коэф_произв[Значение])*('Таблица объектов'!O$1=коэф_произв[Характеристика]),коэф_произв[Коэффициент],"",0)} | R13: {=_xlfn.XLOOKUP(1,(Таблица2[[#This Row],[Тип]]=коэф_произв[Тип])*(Таблица2[[#This Row],[Планировка]]=коэф_произв[Значение])*('Таблица объектов'!Q$1=коэф_произв[Характеристика]),коэф_произв[Коэффициент],"",0)} | T13: {=_xlfn.XLOOKUP(1,(Таблица2[[#This Row],[Тип]]=коэф_произв[Тип])*(Таблица2[[#This Row],[Уровень отделки]]=коэф_произв[Значение])*('Таблица объектов'!S$1=коэф_произв[Характеристика]),коэф_произв[Коэффициент],"",0)} | U13: =IF(Таблица2[[#This Row],[Тип]]="прочие",0.05,PRODUCT(Таблица2[[#This Row],[Уровень отделки коэф.]],Таблица2[[#This Row],[Планировка коэф.]],Таблица2[[#This Row],[Архитектура коэф.]],Таблица2[[#This Row],[Инженерное оснащение коэф.]],Таблица2[[#This Row],[Полы коэф.]],Таблица2[[#This Row],[Конструкция коэф.]],Таблица2[[#This Row],[Наличие / Возможность кран-балки коэф.]],Таблица2[[#This Row],[Высота коэф.]])) -> 0.27216 | V13: =IF(Таблица2[[#This Row],[Тип]]="произв",IF(Таблица2[[#This Row],[Капитальность]]<0.33,"произв класс 4",IF(Таблица2[[#This Row],[Капитальность]]<0.55,"произв класс 3",IF(Таблица2[[#This Row],[Капитальность]]<0.77,"произв класс 2","произв класс 1"))),IF(Таблица2[[#This Row],[Тип]]="гражд",IF(Таблица2[[#This Row],[Капитальность]]<0.33,"гражд класс 4",IF(Таблица2[[#This Row],[Капитальность]]<0.55,"гражд класс 3",IF(Таблица2[[#This Row],[Капитальность]]<0.77,"гражд класс 2","гражд класс 1"))),"прочие")) -> произв класс 4 | W13: =Таблица2[[#This Row],[Площадь, м2]]*Таблица2[[#This Row],[Капитальность]] -> 15.92136 | X13: =IF(AB13<4%,5,IF(AB13<9%,4.5,IF(AB13<14%,4,IF(AB13<24%,3.5,IF(AB13<40%,3,IF(AB13<60%,2.5,IF(AB13<80%,2,1))))))) -> 2.5 | Y13: =X13*Таблица2[[#This Row],[Площадь, м2]] -> 146.25 | Z13: =Y13*Таблица2[[#This Row],[Капитальность]] -> 39.8034 | AB13: 0.5
A14: Объект оценки 3 | B14: 130.9 | C14: Нежилое помещение | D14: гражд | E14: 2,6-3,2 м. | F14: {=_xlfn.XLOOKUP(1,(Таблица2[[#This Row],[Тип]]=коэф_произв[Тип])*(Таблица2[[#This Row],[Высота]]=коэф_произв[Значение])*('Таблица объектов'!E$1=коэф_произв[Характеристика]),коэф_произв[Коэффициент],"",0)} -> 0.7 | H14: {=_xlfn.XLOOKUP(1,(Таблица2[[#This Row],[Тип]]=коэф_произв[Тип])*(Таблица2[[#This Row],[Наличие / Возможность кран-балки]]=коэф_произв[Значение])*('Таблица объектов'!G$1=коэф_произв[Характеристика]),коэф_произв[Коэффициент],"",0)} | I14: Капитальная | J14: {=_xlfn.XLOOKUP(1,(Таблица2[[#This Row],[Тип]]=коэф_произв[Тип])*(Таблица2[[#This Row],[Конструкция]]=коэф_произв[Значение])*('Таблица объектов'!I$1=коэф_произв[Характеристика]),коэф_произв[Коэффициент],"",0)} -> 1 | L14: {=_xlfn.XLOOKUP(1,(Таблица2[[#This Row],[Тип]]=коэф_произв[Тип])*(Таблица2[[#This Row],[Полы]]=коэф_произв[Значение])*('Таблица объектов'!K$1=коэф_произв[Характеристика]),коэф_произв[Коэффициент],"",0)} | M14: Стандартное (по всем помещениям разводка освещения, водопровод, канализация) | N14: {=_xlfn.XLOOKUP(1,(Таблица2[[#This Row],[Тип]]=коэф_произв[Тип])*(Таблица2[[#This Row],[Инженерное оснащение]]=коэф_произв[Значение])*('Таблица объектов'!M$1=коэф_произв[Характеристика]),коэф_произв[Коэффициент],"",0)} -> 0.9 | O14: Устаревшая | P14: {=_xlfn.XLOOKUP(1,(Таблица2[[#This Row],[Тип]]=коэф_произв[Тип])*(Таблица2[[#This Row],[Архитектура]]=коэф_произв[Значение])*('Таблица объектов'!O$1=коэф_произв[Характеристика]),коэф_произв[Коэффициент],"",0)} -> 0.8 | Q14: Смешанная | R14: {=_xlfn.XLOOKUP(1,(Таблица2[[#This Row],[Тип]]=коэф_произв[Тип])*(Таблица2[[#This Row],[Планировка]]=коэф_произв[Значение])*('Таблица объектов'!Q$1=коэф_произв[Характеристика]),коэф_произв[Коэффициент],"",0)} -> 0.95 | S14: Простая (потолки и стены оштукатурены, окрашены или отделаны дешевыми материалами (МДФ), полы линолеумные | T14: {=_xlfn.XLOOKUP(1,(Таблица2[[#This Row],[Тип]]=коэф_произв[Тип])*(Таблица2[[#This Row],[Уровень отделки]]=коэф_произв[Значение])*('Таблица объектов'!S$1=коэф_произв[Характеристика]),коэф_произв[Коэффициент],"",0)} -> 0.7 | U14: =IF(Таблица2[[#This Row],[Тип]]="прочие",0.05,PRODUCT(Таблица2[[#This Row],[Уровень отделки коэф.]],Таблица2[[#This Row],[Планировка коэф.]],Таблица2[[#This Row],[Архитектура коэф.]],Таблица2[[#This Row],[Инженерное оснащение коэф.]],Таблица2[[#This Row],[Полы коэф.]],Таблица2[[#This Row],[Конструкция коэф.]],Таблица2[[#This Row],[Наличие / Возможность кран-балки коэф.]],Таблица2[[#This Row],[Высота коэф.]])) -> 0.33516 | V14: =IF(Таблица2[[#This Row],[Тип]]="произв",IF(Таблица2[[#This Row],[Капитальность]]<0.33,"произв класс 4",IF(Таблица2[[#This Row],[Капитальность]]<0.55,"произв класс 3",IF(Таблица2[[#This Row],[Капитальность]]<0.77,"произв класс 2","произв класс 1"))),IF(Таблица2[[#This Row],[Тип]]="гражд",IF(Таблица2[[#This Row],[Капитальность]]<0.33,"гражд класс 4",IF(Таблица2[[#This Row],[Капитальность]]<0.55,"гражд класс 3",IF(Таблица2[[#This Row],[Капитальность]]<0.77,"гражд класс 2","гражд класс 1"))),"прочие")) -> гражд класс 3 | W14: =Таблица2[[#This Row],[Площадь, м2]]*Таблица2[[#This Row],[Капитальность]] -> 43.872444 | X14: =IF(AB14<4%,5,IF(AB14<9%,4.5,IF(AB14<14%,4,IF(AB14<24%,3.5,IF(AB14<40%,3,IF(AB14<60%,2.5,IF(AB14<80%,2,1))))))) -> 2.5 | Y14: =X14*Таблица2[[#This Row],[Площадь, м2]] -> 327.25 | Z14: =Y14*Таблица2[[#This Row],[Капитальность]] -> 109.68111 | AB14: 0.427
A15: Объект оценки 3 | B15: 18.19 | C15: Дополнительная пристройка | D15: гражд | E15: 2,6-3,2 м. | F15: {=_xlfn.XLOOKUP(1,(Таблица2[[#This Row],[Тип]]=коэф_произв[Тип])*(Таблица2[[#This Row],[Высота]]=коэф_произв[Значение])*('Таблица объектов'!E$1=коэф_произв[Характеристика]),коэф_произв[Коэффициент],"",0)} -> 0.7 | H15: {=_xlfn.XLOOKUP(1,(Таблица2[[#This Row],[Тип]]=коэф_произв[Тип])*(Таблица2[[#This Row],[Наличие / Возможность кран-балки]]=коэф_произв[Значение])*('Таблица объектов'!G$1=коэф_произв[Характеристика]),коэф_произв[Коэффициент],"",0)} | I15: Смешанная | J15: {=_xlfn.XLOOKUP(1,(Таблица2[[#This Row],[Тип]]=коэф_произв[Тип])*(Таблица2[[#This Row],[Конструкция]]=коэф_произв[Значение])*('Таблица объектов'!I$1=коэф_произв[Характеристика]),коэф_произв[Коэффициент],"",0)} -> 0.9 | L15: {=_xlfn.XLOOKUP(1,(Таблица2[[#This Row],[Тип]]=коэф_произв[Тип])*(Таблица2[[#This Row],[Полы]]=коэф_произв[Значение])*('Таблица объектов'!K$1=коэф_произв[Характеристика]),коэф_произв[Коэффициент],"",0)} | M15: Отсутствует или минимальное (минимальная разводка освещения, водопровода) | N15: {=_xlfn.XLOOKUP(1,(Таблица2[[#This Row],[Тип]]=коэф_произв[Тип])*(Таблица2[[#This Row],[Инженерное оснащение]]=коэф_произв[Значение])*('Таблица объектов'!M$1=коэф_произв[Характеристика]),коэф_произв[Коэффициент],"",0)} -> 0.8 | O15: Устаревшая | P15: {=_xlfn.XLOOKUP(1,(Таблица2[[#This Row],[Тип]]=коэф_произв[Тип])*(Таблица2[[#This Row],[Архитектура]]=коэф_произв[Значение])*('Таблица объектов'!O$1=коэф_произв[Характеристика]),коэф_произв[Коэффициент],"",0)} -> 0.8 | Q15: Смешанная | R15: {=_xlfn.XLOOKUP(1,(Таблица2[[#This Row],[Тип]]=коэф_произв[Тип])*(Таблица2[[#This Row],[Планировка]]=коэф_произв[Значение])*('Таблица объектов'!Q$1=коэф_произв[Характеристика]),коэф_произв[Коэффициент],"",0)} -> 0.95 | S15: Без отделки (потолки не подшиты или не отделаны, стены неоштукатурены или неокрашены, полы без покрытий со стяжкой или без) | T15: {=_xlfn.XLOOKUP(1,(Таблица2[[#This Row],[Тип]]=коэф_произв[Тип])*(Таблица2[[#This Row],[Уровень отделки]]=коэф_произв[Значение])*('Таблица объектов'!S$1=коэф_произв[Характеристика]),коэф_произв[Коэффициент],"",0)} -> 0.5 | U15: =IF(Таблица2[[#This Row],[Тип]]="прочие",0.05,PRODUCT(Таблица2[[#This Row],[Уровень отделки коэф.]],Таблица2[[#This Row],[Планировка коэф.]],Таблица2[[#This Row],[Архитектура коэф.]],Таблица2[[#This Row],[Инженерное оснащение коэф.]],Таблица2[[#This Row],[Полы коэф.]],Таблица2[[#This Row],[Конструкция коэф.]],Таблица2[[#This Row],[Наличие / Возможность кран-балки коэф.]],Таблица2[[#This Row],[Высота коэф.]])) -> 0.19152 | V15: =IF(Таблица2[[#This Row],[Тип]]="произв",IF(Таблица2[[#This Row],[Капитальность]]<0.33,"произв класс 4",IF(Таблица2[[#This Row],[Капитальность]]<0.55,"произв класс 3",IF(Таблица2[[#This Row],[Капитальность]]<0.77,"произв класс 2","произв класс 1"))),IF(Таблица2[[#This Row],[Тип]]="гражд",IF(Таблица2[[#This Row],[Капитальность]]<0.33,"гражд класс 4",IF(Таблица2[[#This Row],[Капитальность]]<0.55,"гражд класс 3",IF(Таблица2[[#This Row],[Капитальность]]<0.77,"гражд класс 2","гражд класс 1"))),"прочие")) -> гражд класс 4 | W15: =Таблица2[[#This Row],[Площадь, м2]]*Таблица2[[#This Row],[Капитальность]] -> 3.4837488 | X15: =IF(AB15<4%,5,IF(AB15<9%,4.5,IF(AB15<14%,4,IF(AB15<24%,3.5,IF(AB15<40%,3,IF(AB15<60%,2.5,IF(AB15<80%,2,1))))))) -> 2.5 | Y15: =X15*Таблица2[[#This Row],[Площадь, м2]] -> 45.475 | Z15: =Y15*Таблица2[[#This Row],[Капитальность]] -> 8.709372 | AB15: 0.427
A16: Объект оценки 3 | B16: 289.3 | C16: Нежилое помещение | D16: произв | E16: 5-8 м. | F16: {=_xlfn.XLOOKUP(1,(Таблица2[[#This Row],[Тип]]=коэф_произв[Тип])*(Таблица2[[#This Row],[Высота]]=коэф_произв[Значение])*('Таблица объектов'!E$1=коэф_произв[Характеристика]),коэф_произв[Коэффициент],"",0)} -> 0.8 | G16: Не установлено (по умолчанию) | H16: {=_xlfn.XLOOKUP(1,(Таблица2[[#This Row],[Тип]]=коэф_произв[Тип])*(Таблица2[[#This Row],[Наличие / Возможность кран-балки]]=коэф_произв[Значение])*('Таблица объектов'!G$1=коэф_произв[Характеристика]),коэф_произв[Коэффициент],"",0)} -> 0.95 | I16: Блочные по железобетонному каркасу, без утепления | J16: {=_xlfn.XLOOKUP(1,(Таблица2[[#This Row],[Тип]]=коэф_произв[Тип])*(Таблица2[[#This Row],[Конструкция]]=коэф_произв[Значение])*('Таблица объектов'!I$1=коэф_произв[Характеристика]),коэф_произв[Коэффициент],"",0)} -> 0.7 | K16: Простые | L16: {=_xlfn.XLOOKUP(1,(Таблица2[[#This Row],[Тип]]=коэф_произв[Тип])*(Таблица2[[#This Row],[Полы]]=коэф_произв[Значение])*('Таблица объектов'!K$1=коэф_произв[Характеристика]),коэф_произв[Коэффициент],"",0)} -> 0.9 | M16: Отсутствует или минимальное (минимальная разводка освещения, водопровода) | N16: {=_xlfn.XLOOKUP(1,(Таблица2[[#This Row],[Тип]]=коэф_произв[Тип])*(Таблица2[[#This Row],[Инженерное оснащение]]=коэф_произв[Значение])*('Таблица объектов'!M$1=коэф_произв[Характеристика]),коэф_произв[Коэффициент],"",0)} -> 0.8 | P16: {=_xlfn.XLOOKUP(1,(Таблица2[[#This Row],[Тип]]=коэф_произв[Тип])*(Таблица2[[#This Row],[Архитектура]]=коэф_произв[Значение])*('Таблица объектов'!O$1=коэф_произв[Характеристика]),коэф_произв[Коэффициент],"",0)} | R16: {=_xlfn.XLOOKUP(1,(Таблица2[[#This Row],[Тип]]=коэф_произв[Тип])*(Таблица2[[#This Row],[Планировка]]=коэф_произв[Значение])*('Таблица объектов'!Q$1=коэф_произв[Характеристика]),коэф_произв[Коэффициент],"",0)} | T16: {=_xlfn.XLOOKUP(1,(Таблица2[[#This Row],[Тип]]=коэф_произв[Тип])*(Таблица2[[#This Row],[Уровень отделки]]=коэф_произв[Значение])*('Таблица объектов'!S$1=коэф_произв[Характеристика]),коэф_произв[Коэффициент],"",0)} | U16: =IF(Таблица2[[#This Row],[Тип]]="прочие",0.05,PRODUCT(Таблица2[[#This Row],[Уровень отделки коэф.]],Таблица2[[#This Row],[Планировка коэф.]],Таблица2[[#This Row],[Архитектура коэф.]],Таблица2[[#This Row],[Инженерное оснащение коэф.]],Таблица2[[#This Row],[Полы коэф.]],Таблица2[[#This Row],[Конструкция коэф.]],Таблица2[[#This Row],[Наличие / Возможность кран-балки коэф.]],Таблица2[[#This Row],[Высота коэф.]])) -> 0.38304 | V16: =IF(Таблица2[[#This Row],[Тип]]="произв",IF(Таблица2[[#This Row],[Капитальность]]<0.33,"произв класс 4",IF(Таблица2[[#This Row],[Капитальность]]<0.55,"произв класс 3",IF(Таблица2[[#This Row],[Капитальность]]<0.77,"произв класс 2","произв класс 1"))),IF(Таблица2[[#This Row],[Тип]]="гражд",IF(Таблица2[[#This Row],[Капитальность]]<0.33,"гражд класс 4",IF(Таблица2[[#This Row],[Капитальность]]<0.55,"гражд класс 3",IF(Таблица2[[#This Row],[Капитальность]]<0.77,"гражд класс 2","гражд класс 1"))),"прочие")) -> произв класс 3 | W16: =Таблица2[[#This Row],[Площадь, м2]]*Таблица2[[#This Row],[Капитальность]] -> 110.81347 | X16: =IF(AB16<4%,5,IF(AB16<9%,4.5,IF(AB16<14%,4,IF(AB16<24%,3.5,IF(AB16<40%,3,IF(AB16<60%,2.5,IF(AB16<80%,2,1))))))) -> 2.5 | Y16: =X16*Таблица2[[#This Row],[Площадь, м2]] -> 723.25 | Z16: =Y16*Таблица2[[#This Row],[Капитальность]] -> 277.03368 | AB16: 0.465
A17: Объект оценки 3 | B17: 13.775 | C17: Навес | D17: прочие | F17: {=_xlfn.XLOOKUP(1,(Таблица2[[#This Row],[Тип]]=коэф_произв[Тип])*(Таблица2[[#This Row],[Высота]]=коэф_произв[Значение])*('Таблица объектов'!E$1=коэф_произв[Характеристика]),коэф_произв[Коэффициент],"",0)} | H17: {=_xlfn.XLOOKUP(1,(Таблица2[[#This Row],[Тип]]=коэф_произв[Тип])*(Таблица2[[#This Row],[Наличие / Возможность кран-балки]]=коэф_произв[Значение])*('Таблица объектов'!G$1=коэф_произв[Характеристика]),коэф_произв[Коэффициент],"",0)} | J17: {=_xlfn.XLOOKUP(1,(Таблица2[[#This Row],[Тип]]=коэф_произв[Тип])*(Таблица2[[#This Row],[Конструкция]]=коэф_произв[Значение])*('Таблица объектов'!I$1=коэф_произв[Характеристика]),коэф_произв[Коэффициент],"",0)} | L17: {=_xlfn.XLOOKUP(1,(Таблица2[[#This Row],[Тип]]=коэф_произв[Тип])*(Таблица2[[#This Row],[Полы]]=коэф_произв[Значение])*('Таблица объектов'!K$1=коэф_произв[Характеристика]),коэф_произв[Коэффициент],"",0)} | N17: {=_xlfn.XLOOKUP(1,(Таблица2[[#This Row],[Тип]]=коэф_произв[Тип])*(Таблица2[[#This Row],[Инженерное оснащение]]=коэф_произв[Значение])*('Таблица объектов'!M$1=коэф_произв[Характеристика]),коэф_произв[Коэффициент],"",0)} | P17: {=_xlfn.XLOOKUP(1,(Таблица2[[#This Row],[Тип]]=коэф_произв[Тип])*(Таблица2[[#This Row],[Архитектура]]=коэф_произв[Значение])*('Таблица объектов'!O$1=коэф_произв[Характеристика]),коэф_произв[Коэффициент],"",0)} | R17: {=_xlfn.XLOOKUP(1,(Таблица2[[#This Row],[Тип]]=коэф_произв[Тип])*(Таблица2[[#This Row],[Планировка]]=коэф_произв[Значение])*('Таблица объектов'!Q$1=коэф_произв[Характеристика]),коэф_произв[Коэффициент],"",0)} | T17: {=_xlfn.XLOOKUP(1,(Таблица2[[#This Row],[Тип]]=коэф_произв[Тип])*(Таблица2[[#This Row],[Уровень отделки]]=коэф_произв[Значение])*('Таблица объектов'!S$1=коэф_произв[Характеристика]),коэф_произв[Коэффициент],"",0)} | U17: =IF(Таблица2[[#This Row],[Тип]]="прочие",0.05,PRODUCT(Таблица2[[#This Row],[Уровень отделки коэф.]],Таблица2[[#This Row],[Планировка коэф.]],Таблица2[[#This Row],[Архитектура коэф.]],Таблица2[[#This Row],[Инженерное оснащение коэф.]],Таблица2[[#This Row],[Полы коэф.]],Таблица2[[#This Row],[Конструкция коэф.]],Таблица2[[#This Row],[Наличие / Возможность кран-балки коэф.]],Таблица2[[#This Row],[Высота коэф.]])) -> 0.05 | V17: =IF(Таблица2[[#This Row],[Тип]]="произв",IF(Таблица2[[#This Row],[Капитальность]]<0.33,"произв класс 4",IF(Таблица2[[#This Row],[Капитальность]]<0.55,"произв класс 3",IF(Таблица2[[#This Row],[Капитальность]]<0.77,"произв класс 2","произв класс 1"))),IF(Таблица2[[#This Row],[Тип]]="гражд",IF(Таблица2[[#This Row],[Капитальность]]<0.33,"гражд класс 4",IF(Таблица2[[#This Row],[Капитальность]]<0.55,"гражд класс 3",IF(Таблица2[[#This Row],[Капитальность]]<0.77,"гражд класс 2","гражд класс 1"))),"прочие")) -> прочие | W17: =Таблица2[[#This Row],[Площадь, м2]]*Таблица2[[#This Row],[Капитальность]] -> 0.68875 | X17: =IF(AB17<4%,5,IF(AB17<9%,4.5,IF(AB17<14%,4,IF(AB17<24%,3.5,IF(AB17<40%,3,IF(AB17<60%,2.5,IF(AB17<80%,2,1))))))) -> 2.5 | Y17: =X17*Таблица2[[#This Row],[Площадь, м2]] -> 34.4375 | Z17: =Y17*Таблица2[[#This Row],[Капитальность]] -> 1.721875 | AB17: 0.5
A18: Объект оценки 3 | B18: 289.7 | C18: Нежилое помещение | D18: произв | E18: 5-8 м. | F18: {=_xlfn.XLOOKUP(1,(Таблица2[[#This Row],[Тип]]=коэф_произв[Тип])*(Таблица2[[#This Row],[Высота]]=коэф_произв[Значение])*('Таблица объектов'!E$1=коэф_произв[Характеристика]),коэф_произв[Коэффициент],"",0)} -> 0.8 | G18: Не установлено (по умолчанию) | H18: {=_xlfn.XLOOKUP(1,(Таблица2[[#This Row],[Тип]]=коэф_произв[Тип])*(Таблица2[[#This Row],[Наличие / Возможность кран-балки]]=коэф_произв[Значение])*('Таблица объектов'!G$1=коэф_произв[Характеристика]),коэф_произв[Коэффициент],"",0)} -> 0.95 | I18: Блочные по железобетонному каркасу, без утепления | J18: {=_xlfn.XLOOKUP(1,(Таблица2[[#This Row],[Тип]]=коэф_произв[Тип])*(Таблица2[[#This Row],[Конструкция]]=коэф_произв[Значение])*('Таблица объектов'!I$1=коэф_произв[Характеристика]),коэф_произв[Коэффициент],"",0)} -> 0.7 | K18: Простые | L18: {=_xlfn.XLOOKUP(1,(Таблица2[[#This Row],[Тип]]=коэф_произв[Тип])*(Таблица2[[#This Row],[Полы]]=коэф_произв[Значение])*('Таблица объектов'!K$1=коэф_произв[Характеристика]),коэф_произв[Коэффициент],"",0)} -> 0.9 | M18: Отсутствует или минимальное (минимальная разводка освещения, водопровода) | N18: {=_xlfn.XLOOKUP(1,(Таблица2[[#This Row],[Тип]]=коэф_произв[Тип])*(Таблица2[[#This Row],[Инженерное оснащение]]=коэф_произв[Значение])*('Таблица объектов'!M$1=коэф_произв[Характеристика]),коэф_произв[Коэффициент],"",0)} -> 0.8 | P18: {=_xlfn.XLOOKUP(1,(Таблица2[[#This Row],[Тип]]=коэф_произв[Тип])*(Таблица2[[#This Row],[Архитектура]]=коэф_произв[Значение])*('Таблица объектов'!O$1=коэф_произв[Характеристика]),коэф_произв[Коэффициент],"",0)} | R18: {=_xlfn.XLOOKUP(1,(Таблица2[[#This Row],[Тип]]=коэф_произв[Тип])*(Таблица2[[#This Row],[Планировка]]=коэф_произв[Значение])*('Таблица объектов'!Q$1=коэф_произв[Характеристика]),коэф_произв[Коэффициент],"",0)} | T18: {=_xlfn.XLOOKUP(1,(Таблица2[[#This Row],[Тип]]=коэф_произв[Тип])*(Таблица2[[#This Row],[Уровень отделки]]=коэф_произв[Значение])*('Таблица объектов'!S$1=коэф_произв[Характеристика]),коэф_произв[Коэффициент],"",0)} | U18: =IF(Таблица2[[#This Row],[Тип]]="прочие",0.05,PRODUCT(Таблица2[[#This Row],[Уровень отделки коэф.]],Таблица2[[#This Row],[Планировка коэф.]],Таблица2[[#This Row],[Архитектура коэф.]],Таблица2[[#This Row],[Инженерное оснащение коэф.]],Таблица2[[#This Row],[Полы коэф.]],Таблица2[[#This Row],[Конструкция коэф.]],Таблица2[[#This Row],[Наличие / Возможность кран-балки коэф.]],Таблица2[[#This Row],[Высота коэф.]])) -> 0.38304 | V18: =IF(Таблица2[[#This Row],[Тип]]="произв",IF(Таблица2[[#This Row],[Капитальность]]<0.33,"произв класс 4",IF(Таблица2[[#This Row],[Капитальность]]<0.55,"произв класс 3",IF(Таблица2[[#This Row],[Капитальность]]<0.77,"произв класс 2","произв класс 1"))),IF(Таблица2[[#This Row],[Тип]]="гражд",IF(Таблица2[[#This Row],[Капитальность]]<0.33,"гражд класс 4",IF(Таблица2[[#This Row],[Капитальность]]<0.55,"гражд класс 3",IF(Таблица2[[#This Row],[Капитальность]]<0.77,"гражд класс 2","гражд класс 1"))),"прочие")) -> произв класс 3 | W18: =Таблица2[[#This Row],[Площадь, м2]]*Таблица2[[#This Row],[Капитальность]] -> 110.96669 | X18: =IF(AB18<4%,5,IF(AB18<9%,4.5,IF(AB18<14%,4,IF(AB18<24%,3.5,IF(AB18<40%,3,IF(AB18<60%,2.5,IF(AB18<80%,2,1))))))) -> 2.5 | Y18: =X18*Таблица2[[#This Row],[Площадь, м2]] -> 724.25 | Z18: =Y18*Таблица2[[#This Row],[Капитальность]] -> 277.41672 | AB18: 0.506
A19: Объект оценки 3 | B19: 17.85 | C19: Пожарное депо | D19: прочие | F19: {=_xlfn.XLOOKUP(1,(Таблица2[[#This Row],[Тип]]=коэф_произв[Тип])*(Таблица2[[#This Row],[Высота]]=коэф_произв[Значение])*('Таблица объектов'!E$1=коэф_произв[Характеристика]),коэф_произв[Коэффициент],"",0)} | H19: {=_xlfn.XLOOKUP(1,(Таблица2[[#This Row],[Тип]]=коэф_произв[Тип])*(Таблица2[[#This Row],[Наличие / Возможность кран-балки]]=коэф_произв[Значение])*('Таблица объектов'!G$1=коэф_произв[Характеристика]),коэф_произв[Коэффициент],"",0)} | J19: {=_xlfn.XLOOKUP(1,(Таблица2[[#This Row],[Тип]]=коэф_произв[Тип])*(Таблица2[[#This Row],[Конструкция]]=коэф_произв[Значение])*('Таблица объектов'!I$1=коэф_произв[Характеристика]),коэф_произв[Коэффициент],"",0)} | L19: {=_xlfn.XLOOKUP(1,(Таблица2[[#This Row],[Тип]]=коэф_произв[Тип])*(Таблица2[[#This Row],[Полы]]=коэф_произв[Значение])*('Таблица объектов'!K$1=коэф_произв[Характеристика]),коэф_произв[Коэффициент],"",0)} | N19: {=_xlfn.XLOOKUP(1,(Таблица2[[#This Row],[Тип]]=коэф_произв[Тип])*(Таблица2[[#This Row],[Инженерное оснащение]]=коэф_произв[Значение])*('Таблица объектов'!M$1=коэф_произв[Характеристика]),коэф_произв[Коэффициент],"",0)} | P19: {=_xlfn.XLOOKUP(1,(Таблица2[[#This Row],[Тип]]=коэф_произв[Тип])*(Таблица2[[#This Row],[Архитектура]]=коэф_произв[Значение])*('Таблица объектов'!O$1=коэф_произв[Характеристика]),коэф_произв[Коэффициент],"",0)} | R19: {=_xlfn.XLOOKUP(1,(Таблица2[[#This Row],[Тип]]=коэф_произв[Тип])*(Таблица2[[#This Row],[Планировка]]=коэф_произв[Значение])*('Таблица объектов'!Q$1=коэф_произв[Характеристика]),коэф_произв[Коэффициент],"",0)} | T19: {=_xlfn.XLOOKUP(1,(Таблица2[[#This Row],[Тип]]=коэф_произв[Тип])*(Таблица2[[#This Row],[Уровень отделки]]=коэф_произв[Значение])*('Таблица объектов'!S$1=коэф_произв[Характеристика]),коэф_произв[Коэффициент],"",0)} | U19: =IF(Таблица2[[#This Row],[Тип]]="прочие",0.05,PRODUCT(Таблица2[[#This Row],[Уровень отделки коэф.]],Таблица2[[#This Row],[Планировка коэф.]],Таблица2[[#This Row],[Архитектура коэф.]],Таблица2[[#This Row],[Инженерное оснащение коэф.]],Таблица2[[#This Row],[Полы коэф.]],Таблица2[[#This Row],[Конструкция коэф.]],Таблица2[[#This Row],[Наличие / Возможность кран-балки коэф.]],Таблица2[[#This Row],[Высота коэф.]])) -> 0.05 | V19: =IF(Таблица2[[#This Row],[Тип]]="произв",IF(Таблица2[[#This Row],[Капитальность]]<0.33,"произв класс 4",IF(Таблица2[[#This Row],[Капитальность]]<0.55,"произв класс 3",IF(Таблица2[[#This Row],[Капитальность]]<0.77,"произв класс 2","произв класс 1"))),IF(Таблица2[[#This Row],[Тип]]="гражд",IF(Таблица2[[#This Row],[Капитальность]]<0.33,"гражд класс 4",IF(Таблица2[[#This Row],[Капитальность]]<0.55,"гражд класс 3",IF(Таблица2[[#This Row],[Капитальность]]<0.77,"гражд класс 2","гражд класс 1"))),"прочие")) -> прочие | W19: =Таблица2[[#This Row],[Площадь, м2]]*Таблица2[[#This Row],[Капитальность]] -> 0.8925 | X19: =IF(AB19<4%,5,IF(AB19<9%,4.5,IF(AB19<14%,4,IF(AB19<24%,3.5,IF(AB19<40%,3,IF(AB19<60%,2.5,IF(AB19<80%,2,1))))))) -> 2.5 | Y19: =X19*Таблица2[[#This Row],[Площадь, м2]] -> 44.625 | Z19: =Y19*Таблица2[[#This Row],[Капитальность]] -> 2.23125 | AB19: 0.479
A20: Объект оценки 3 | B20: 18.53 | C20: Комната охраны | D20: прочие | F20: {=_xlfn.XLOOKUP(1,(Таблица2[[#This Row],[Тип]]=коэф_произв[Тип])*(Таблица2[[#This Row],[Высота]]=коэф_произв[Значение])*('Таблица объектов'!E$1=коэф_произв[Характеристика]),коэф_произв[Коэффициент],"",0)} | H20: {=_xlfn.XLOOKUP(1,(Таблица2[[#This Row],[Тип]]=коэф_произв[Тип])*(Таблица2[[#This Row],[Наличие / Возможность кран-балки]]=коэф_произв[Значение])*('Таблица объектов'!G$1=коэф_произв[Характеристика]),коэф_произв[Коэффициент],"",0)} | J20: {=_xlfn.XLOOKUP(1,(Таблица2[[#This Row],[Тип]]=коэф_произв[Тип])*(Таблица2[[#This Row],[Конструкция]]=коэф_произв[Значение])*('Таблица объектов'!I$1=коэф_произв[Характеристика]),коэф_произв[Коэффициент],"",0)} | L20: {=_xlfn.XLOOKUP(1,(Таблица2[[#This Row],[Тип]]=коэф_произв[Тип])*(Таблица2[[#This Row],[Полы]]=коэф_произв[Значение])*('Таблица объектов'!K$1=коэф_произв[Характеристика]),коэф_произв[Коэффициент],"",0)} | N20: {=_xlfn.XLOOKUP(1,(Таблица2[[#This Row],[Тип]]=коэф_произв[Тип])*(Таблица2[[#This Row],[Инженерное оснащение]]=коэф_произв[Значение])*('Таблица объектов'!M$1=коэф_произв[Характеристика]),коэф_произв[Коэффициент],"",0)} | P20: {=_xlfn.XLOOKUP(1,(Таблица2[[#This Row],[Тип]]=коэф_произв[Тип])*(Таблица2[[#This Row],[Архитектура]]=коэф_произв[Значение])*('Таблица объектов'!O$1=коэф_произв[Характеристика]),коэф_произв[Коэффициент],"",0)} | R20: {=_xlfn.XLOOKUP(1,(Таблица2[[#This Row],[Тип]]=коэф_произв[Тип])*(Таблица2[[#This Row],[Планировка]]=коэф_произв[Значение])*('Таблица объектов'!Q$1=коэф_произв[Характеристика]),коэф_произв[Коэффициент],"",0)} | T20: {=_xlfn.XLOOKUP(1,(Таблица2[[#This Row],[Тип]]=коэф_произв[Тип])*(Таблица2[[#This Row],[Уровень отделки]]=коэф_произв[Значение])*('Таблица объектов'!S$1=коэф_произв[Характеристика]),коэф_произв[Коэффициент],"",0)} | U20: =IF(Таблица2[[#This Row],[Тип]]="прочие",0.05,PRODUCT(Таблица2[[#This Row],[Уровень отделки коэф.]],Таблица2[[#This Row],[Планировка коэф.]],Таблица2[[#This Row],[Архитектура коэф.]],Таблица2[[#This Row],[Инженерное оснащение коэф.]],Таблица2[[#This Row],[Полы коэф.]],Таблица2[[#This Row],[Конструкция коэф.]],Таблица2[[#This Row],[Наличие / Возможность кран-балки коэф.]],Таблица2[[#This Row],[Высота коэф.]])) -> 0.05 | V20: =IF(Таблица2[[#This Row],[Тип]]="произв",IF(Таблица2[[#This Row],[Капитальность]]<0.33,"произв класс 4",IF(Таблица2[[#This Row],[Капитальность]]<0.55,"произв класс 3",IF(Таблица2[[#This Row],[Капитальность]]<0.77,"произв класс 2","произв класс 1"))),IF(Таблица2[[#This Row],[Тип]]="гражд",IF(Таблица2[[#This Row],[Капитальность]]<0.33,"гражд класс 4",IF(Таблица2[[#This Row],[Капитальность]]<0.55,"гражд класс 3",IF(Таблица2[[#This Row],[Капитальность]]<0.77,"гражд класс 2","гражд класс 1"))),"прочие")) -> прочие | W20: =Таблица2[[#This Row],[Площадь, м2]]*Таблица2[[#This Row],[Капитальность]] -> 0.9265 | X20: =IF(AB20<4%,5,IF(AB20<9%,4.5,IF(AB20<14%,4,IF(AB20<24%,3.5,IF(AB20<40%,3,IF(AB20<60%,2.5,IF(AB20<80%,2,1))))))) -> 2.5 | Y20: =X20*Таблица2[[#This Row],[Площадь, м2]] -> 46.325 | Z20: =Y20*Таблица2[[#This Row],[Капитальность]] -> 2.31625 | AB20: 0.502
A21: Объект оценки 3 | B21: 27.37 | C21: ТП | D21: прочие | F21: {=_xlfn.XLOOKUP(1,(Таблица2[[#This Row],[Тип]]=коэф_произв[Тип])*(Таблица2[[#This Row],[Высота]]=коэф_произв[Значение])*('Таблица объектов'!E$1=коэф_произв[Характеристика]),коэф_произв[Коэффициент],"",0)} | H21: {=_xlfn.XLOOKUP(1,(Таблица2[[#This Row],[Тип]]=коэф_произв[Тип])*(Таблица2[[#This Row],[Наличие / Возможность кран-балки]]=коэф_произв[Значение])*('Таблица объектов'!G$1=коэф_произв[Характеристика]),коэф_произв[Коэффициент],"",0)} | J21: {=_xlfn.XLOOKUP(1,(Таблица2[[#This Row],[Тип]]=коэф_произв[Тип])*(Таблица2[[#This Row],[Конструкция]]=коэф_произв[Значение])*('Таблица объектов'!I$1=коэф_произв[Характеристика]),коэф_произв[Коэффициент],"",0)} | L21: {=_xlfn.XLOOKUP(1,(Таблица2[[#This Row],[Тип]]=коэф_произв[Тип])*(Таблица2[[#This Row],[Полы]]=коэф_произв[Значение])*('Таблица объектов'!K$1=коэф_произв[Характеристика]),коэф_произв[Коэффициент],"",0)} | N21: {=_xlfn.XLOOKUP(1,(Таблица2[[#This Row],[Тип]]=коэф_произв[Тип])*(Таблица2[[#This Row],[Инженерное оснащение]]=коэф_произв[Значение])*('Таблица объектов'!M$1=коэф_произв[Характеристика]),коэф_произв[Коэффициент],"",0)} | P21: {=_xlfn.XLOOKUP(1,(Таблица2[[#This Row],[Тип]]=коэф_произв[Тип])*(Таблица2[[#This Row],[Архитектура]]=коэф_произв[Значение])*('Таблица объектов'!O$1=коэф_произв[Характеристика]),коэф_произв[Коэффициент],"",0)} | R21: {=_xlfn.XLOOKUP(1,(Таблица2[[#This Row],[Тип]]=коэф_произв[Тип])*(Таблица2[[#This Row],[Планировка]]=коэф_произв[Значение])*('Таблица объектов'!Q$1=коэф_произв[Характеристика]),коэф_произв[Коэффициент],"",0)} | T21: {=_xlfn.XLOOKUP(1,(Таблица2[[#This Row],[Тип]]=коэф_произв[Тип])*(Таблица2[[#This Row],[Уровень отделки]]=коэф_произв[Значение])*('Таблица объектов'!S$1=коэф_произв[Характеристика]),коэф_произв[Коэффициент],"",0)} | U21: =IF(Таблица2[[#This Row],[Тип]]="прочие",0.05,PRODUCT(Таблица2[[#This Row],[Уровень отделки коэф.]],Таблица2[[#This Row],[Планировка коэф.]],Таблица2[[#This Row],[Архитектура коэф.]],Таблица2[[#This Row],[Инженерное оснащение коэф.]],Таблица2[[#This Row],[Полы коэф.]],Таблица2[[#This Row],[Конструкция коэф.]],Таблица2[[#This Row],[Наличие / Возможность кран-балки коэф.]],Таблица2[[#This Row],[Высота коэф.]])) -> 0.05 | V21: =IF(Таблица2[[#This Row],[Тип]]="произв",IF(Таблица2[[#This Row],[Капитальность]]<0.33,"произв класс 4",IF(Таблица2[[#This Row],[Капитальность]]<0.55,"произв класс 3",IF(Таблица2[[#This Row],[Капитальность]]<0.77,"произв класс 2","произв класс 1"))),IF(Таблица2[[#This Row],[Тип]]="гражд",IF(Таблица2[[#This Row],[Капитальность]]<0.33,"гражд класс 4",IF(Таблица2[[#This Row],[Капитальность]]<0.55,"гражд класс 3",IF(Таблица2[[#This Row],[Капитальность]]<0.77,"гражд класс 2","гражд класс 1"))),"прочие")) -> прочие | W21: =Таблица2[[#This Row],[Площадь, м2]]*Таблица2[[#This Row],[Капитальность]] -> 1.3685 | X21: =IF(AB21<4%,5,IF(AB21<9%,4.5,IF(AB21<14%,4,IF(AB21<24%,3.5,IF(AB21<40%,3,IF(AB21<60%,2.5,IF(AB21<80%,2,1))))))) -> 2 | Y21: =X21*Таблица2[[#This Row],[Площадь, м2]] -> 54.74 | Z21: =Y21*Таблица2[[#This Row],[Капитальность]] -> 2.737 | AB21: 0.626
A22: Объект оценки 3 | B22: 81 | C22: Навес | D22: прочие | F22: {=_xlfn.XLOOKUP(1,(Таблица2[[#This Row],[Тип]]=коэф_произв[Тип])*(Таблица2[[#This Row],[Высота]]=коэф_произв[Значение])*('Таблица объектов'!E$1=коэф_произв[Характеристика]),коэф_произв[Коэффициент],"",0)} | H22: {=_xlfn.XLOOKUP(1,(Таблица2[[#This Row],[Тип]]=коэф_произв[Тип])*(Таблица2[[#This Row],[Наличие / Возможность кран-балки]]=коэф_произв[Значение])*('Таблица объектов'!G$1=коэф_произв[Характеристика]),коэф_произв[Коэффициент],"",0)} | J22: {=_xlfn.XLOOKUP(1,(Таблица2[[#This Row],[Тип]]=коэф_произв[Тип])*(Таблица2[[#This Row],[Конструкция]]=коэф_произв[Значение])*('Таблица объектов'!I$1=коэф_произв[Характеристика]),коэф_произв[Коэффициент],"",0)} | L22: {=_xlfn.XLOOKUP(1,(Таблица2[[#This Row],[Тип]]=коэф_произв[Тип])*(Таблица2[[#This Row],[Полы]]=коэф_произв[Значение])*('Таблица объектов'!K$1=коэф_произв[Характеристика]),коэф_произв[Коэффициент],"",0)} | N22: {=_xlfn.XLOOKUP(1,(Таблица2[[#This Row],[Тип]]=коэф_произв[Тип])*(Таблица2[[#This Row],[Инженерное оснащение]]=коэф_произв[Значение])*('Таблица объектов'!M$1=коэф_произв[Характеристика]),коэф_произв[Коэффициент],"",0)} | P22: {=_xlfn.XLOOKUP(1,(Таблица2[[#This Row],[Тип]]=коэф_произв[Тип])*(Таблица2[[#This Row],[Архитектура]]=коэф_произв[Значение])*('Таблица объектов'!O$1=коэф_произв[Характеристика]),коэф_произв[Коэффициент],"",0)} | R22: {=_xlfn.XLOOKUP(1,(Таблица2[[#This Row],[Тип]]=коэф_произв[Тип])*(Таблица2[[#This Row],[Планировка]]=коэф_произв[Значение])*('Таблица объектов'!Q$1=коэф_произв[Характеристика]),коэф_произв[Коэффициент],"",0)} | T22: {=_xlfn.XLOOKUP(1,(Таблица2[[#This Row],[Тип]]=коэф_произв[Тип])*(Таблица2[[#This Row],[Уровень отделки]]=коэф_произв[Значение])*('Таблица объектов'!S$1=коэф_произв[Характеристика]),коэф_произв[Коэффициент],"",0)} | U22: =IF(Таблица2[[#This Row],[Тип]]="прочие",0.05,PRODUCT(Таблица2[[#This Row],[Уровень отделки коэф.]],Таблица2[[#This Row],[Планировка коэф.]],Таблица2[[#This Row],[Архитектура коэф.]],Таблица2[[#This Row],[Инженерное оснащение коэф.]],Таблица2[[#This Row],[Полы коэф.]],Таблица2[[#This Row],[Конструкция коэф.]],Таблица2[[#This Row],[Наличие / Возможность кран-балки коэф.]],Таблица2[[#This Row],[Высота коэф.]])) -> 0.05 | V22: =IF(Таблица2[[#This Row],[Тип]]="произв",IF(Таблица2[[#This Row],[Капитальность]]<0.33,"произв класс 4",IF(Таблица2[[#This Row],[Капитальность]]<0.55,"произв класс 3",IF(Таблица2[[#This Row],[Капитальность]]<0.77,"произв класс 2","произв класс 1"))),IF(Таблица2[[#This Row],[Тип]]="гражд",IF(Таблица2[[#This Row],[Капитальность]]<0.33,"гражд класс 4",IF(Таблица2[[#This Row],[Капитальность]]<0.55,"гражд класс 3",IF(Таблица2[[#This Row],[Капитальность]]<0.77,"гражд класс 2","гражд класс 1"))),"прочие")) -> прочие | W22: =Таблица2[[#This Row],[Площадь, м2]]*Таблица2[[#This Row],[Капитальность]] -> 4.05 | X22: =IF(AB22<4%,5,IF(AB22<9%,4.5,IF(AB22<14%,4,IF(AB22<24%,3.5,IF(AB22<40%,3,IF(AB22<60%,2.5,IF(AB22<80%,2,1))))))) -> 4 | Y22: =X22*Таблица2[[#This Row],[Площадь, м2]] -> 324 | Z22: =Y22*Таблица2[[#This Row],[Капитальность]] -> 16.2 | AB22: 0.1
A23: Объект оценки 3 | B23: 50.4 | C23: Навес | D23: прочие | F23: {=_xlfn.XLOOKUP(1,(Таблица2[[#This Row],[Тип]]=коэф_произв[Тип])*(Таблица2[[#This Row],[Высота]]=коэф_произв[Значение])*('Таблица объектов'!E$1=коэф_произв[Характеристика]),коэф_произв[Коэффициент],"",0)} | H23: {=_xlfn.XLOOKUP(1,(Таблица2[[#This Row],[Тип]]=коэф_произв[Тип])*(Таблица2[[#This Row],[Наличие / Возможность кран-балки]]=коэф_произв[Значение])*('Таблица объектов'!G$1=коэф_произв[Характеристика]),коэф_произв[Коэффициент],"",0)} | J23: {=_xlfn.XLOOKUP(1,(Таблица2[[#This Row],[Тип]]=коэф_произв[Тип])*(Таблица2[[#This Row],[Конструкция]]=коэф_произв[Значение])*('Таблица объектов'!I$1=коэф_произв[Характеристика]),коэф_произв[Коэффициент],"",0)} | L23: {=_xlfn.XLOOKUP(1,(Таблица2[[#This Row],[Тип]]=коэф_произв[Тип])*(Таблица2[[#This Row],[Полы]]=коэф_произв[Значение])*('Таблица объектов'!K$1=коэф_произв[Характеристика]),коэф_произв[Коэффициент],"",0)} | N23: {=_xlfn.XLOOKUP(1,(Таблица2[[#This Row],[Тип]]=коэф_произв[Тип])*(Таблица2[[#This Row],[Инженерное оснащение]]=коэф_произв[Значение])*('Таблица объектов'!M$1=коэф_произв[Характеристика]),коэф_произв[Коэффициент],"",0)} | P23: {=_xlfn.XLOOKUP(1,(Таблица2[[#This Row],[Тип]]=коэф_произв[Тип])*(Таблица2[[#This Row],[Архитектура]]=коэф_произв[Значение])*('Таблица объектов'!O$1=коэф_произв[Характеристика]),коэф_произв[Коэффициент],"",0)} | R23: {=_xlfn.XLOOKUP(1,(Таблица2[[#This Row],[Тип]]=коэф_произв[Тип])*(Таблица2[[#This Row],[Планировка]]=коэф_произв[Значение])*('Таблица объектов'!Q$1=коэф_произв[Характеристика]),коэф_произв[Коэффициент],"",0)} | T23: {=_xlfn.XLOOKUP(1,(Таблица2[[#This Row],[Тип]]=коэф_произв[Тип])*(Таблица2[[#This Row],[Уровень отделки]]=коэф_произв[Значение])*('Таблица объектов'!S$1=коэф_произв[Характеристика]),коэф_произв[Коэффициент],"",0)} | U23: =IF(Таблица2[[#This Row],[Тип]]="прочие",0.05,PRODUCT(Таблица2[[#This Row],[Уровень отделки коэф.]],Таблица2[[#This Row],[Планировка коэф.]],Таблица2[[#This Row],[Архитектура коэф.]],Таблица2[[#This Row],[Инженерное оснащение коэф.]],Таблица2[[#This Row],[Полы коэф.]],Таблица2[[#This Row],[Конструкция коэф.]],Таблица2[[#This Row],[Наличие / Возможность кран-балки коэф.]],Таблица2[[#This Row],[Высота коэф.]])) -> 0.05 | V23: =IF(Таблица2[[#This Row],[Тип]]="произв",IF(Таблица2[[#This Row],[Капитальность]]<0.33,"произв класс 4",IF(Таблица2[[#This Row],[Капитальность]]<0.55,"произв класс 3",IF(Таблица2[[#This Row],[Капитальность]]<0.77,"произв класс 2","произв класс 1"))),IF(Таблица2[[#This Row],[Тип]]="гражд",IF(Таблица2[[#This Row],[Капитальность]]<0.33,"гражд класс 4",IF(Таблица2[[#This Row],[Капитальность]]<0.55,"гражд класс 3",IF(Таблица2[[#This Row],[Капитальность]]<0.77,"гражд класс 2","гражд класс 1"))),"прочие")) -> прочие | W23: =Таблица2[[#This Row],[Площадь, м2]]*Таблица2[[#This Row],[Капитальность]] -> 2.52 | X23: =IF(AB23<4%,5,IF(AB23<9%,4.5,IF(AB23<14%,4,IF(AB23<24%,3.5,IF(AB23<40%,3,IF(AB23<60%,2.5,IF(AB23<80%,2,1))))))) -> 4 | Y23: =X23*Таблица2[[#This Row],[Площадь, м2]] -> 201.6 | Z23: =Y23*Таблица2[[#This Row],[Капитальность]] -> 10.08 | AB23: 0.1
A24: Объект оценки 3 | B24: 49.5 | C24: Навес | D24: прочие | F24: {=_xlfn.XLOOKUP(1,(Таблица2[[#This Row],[Тип]]=коэф_произв[Тип])*(Таблица2[[#This Row],[Высота]]=коэф_произв[Значение])*('Таблица объектов'!E$1=коэф_произв[Характеристика]),коэф_произв[Коэффициент],"",0)} | H24: {=_xlfn.XLOOKUP(1,(Таблица2[[#This Row],[Тип]]=коэф_произв[Тип])*(Таблица2[[#This Row],[Наличие / Возможность кран-балки]]=коэф_произв[Значение])*('Таблица объектов'!G$1=коэф_произв[Характеристика]),коэф_произв[Коэффициент],"",0)} | J24: {=_xlfn.XLOOKUP(1,(Таблица2[[#This Row],[Тип]]=коэф_произв[Тип])*(Таблица2[[#This Row],[Конструкция]]=коэф_произв[Значение])*('Таблица объектов'!I$1=коэф_произв[Характеристика]),коэф_произв[Коэффициент],"",0)} | L24: {=_xlfn.XLOOKUP(1,(Таблица2[[#This Row],[Тип]]=коэф_произв[Тип])*(Таблица2[[#This Row],[Полы]]=коэф_произв[Значение])*('Таблица объектов'!K$1=коэф_произв[Характеристика]),коэф_произв[Коэффициент],"",0)} | N24: {=_xlfn.XLOOKUP(1,(Таблица2[[#This Row],[Тип]]=коэф_произв[Тип])*(Таблица2[[#This Row],[Инженерное оснащение]]=коэф_произв[Значение])*('Таблица объектов'!M$1=коэф_произв[Характеристика]),коэф_произв[Коэффициент],"",0)} | P24: {=_xlfn.XLOOKUP(1,(Таблица2[[#This Row],[Тип]]=коэф_произв[Тип])*(Таблица2[[#This Row],[Архитектура]]=коэф_произв[Значение])*('Таблица объектов'!O$1=коэф_произв[Характеристика]),коэф_произв[Коэффициент],"",0)} | R24: {=_xlfn.XLOOKUP(1,(Таблица2[[#This Row],[Тип]]=коэф_произв[Тип])*(Таблица2[[#This Row],[Планировка]]=коэф_произв[Значение])*('Таблица объектов'!Q$1=коэф_произв[Характеристика]),коэф_произв[Коэффициент],"",0)} | T24: {=_xlfn.XLOOKUP(1,(Таблица2[[#This Row],[Тип]]=коэф_произв[Тип])*(Таблица2[[#This Row],[Уровень отделки]]=коэф_произв[Значение])*('Таблица объектов'!S$1=коэф_произв[Характеристика]),коэф_произв[Коэффициент],"",0)} | U24: =IF(Таблица2[[#This Row],[Тип]]="прочие",0.05,PRODUCT(Таблица2[[#This Row],[Уровень отделки коэф.]],Таблица2[[#This Row],[Планировка коэф.]],Таблица2[[#This Row],[Архитектура коэф.]],Таблица2[[#This Row],[Инженерное оснащение коэф.]],Таблица2[[#This Row],[Полы коэф.]],Таблица2[[#This Row],[Конструкция коэф.]],Таблица2[[#This Row],[Наличие / Возможность кран-балки коэф.]],Таблица2[[#This Row],[Высота коэф.]])) -> 0.05 | V24: =IF(Таблица2[[#This Row],[Тип]]="произв",IF(Таблица2[[#This Row],[Капитальность]]<0.33,"произв класс 4",IF(Таблица2[[#This Row],[Капитальность]]<0.55,"произв класс 3",IF(Таблица2[[#This Row],[Капитальность]]<0.77,"произв класс 2","произв класс 1"))),IF(Таблица2[[#This Row],[Тип]]="гражд",IF(Таблица2[[#This Row],[Капитальность]]<0.33,"гражд класс 4",IF(Таблица2[[#This Row],[Капитальность]]<0.55,"гражд класс 3",IF(Таблица2[[#This Row],[Капитальность]]<0.77,"гражд класс 2","гражд класс 1"))),"прочие")) -> прочие | W24: =Таблица2[[#This Row],[Площадь, м2]]*Таблица2[[#This Row],[Капитальность]] -> 2.475 | X24: =IF(AB24<4%,5,IF(AB24<9%,4.5,IF(AB24<14%,4,IF(AB24<24%,3.5,IF(AB24<40%,3,IF(AB24<60%,2.5,IF(AB24<80%,2,1))))))) -> 4 | Y24: =X24*Таблица2[[#This Row],[Площадь, м2]] -> 198 | Z24: =Y24*Таблица2[[#This Row],[Капитальность]] -> 9.9 | AB24: 0.1
A25: Объект оценки 3 | B25: 161.1 | C25: Навес | D25: прочие | F25: {=_xlfn.XLOOKUP(1,(Таблица2[[#This Row],[Тип]]=коэф_произв[Тип])*(Таблица2[[#This Row],[Высота]]=коэф_произв[Значение])*('Таблица объектов'!E$1=коэф_произв[Характеристика]),коэф_произв[Коэффициент],"",0)} | H25: {=_xlfn.XLOOKUP(1,(Таблица2[[#This Row],[Тип]]=коэф_произв[Тип])*(Таблица2[[#This Row],[Наличие / Возможность кран-балки]]=коэф_произв[Значение])*('Таблица объектов'!G$1=коэф_произв[Характеристика]),коэф_произв[Коэффициент],"",0)} | J25: {=_xlfn.XLOOKUP(1,(Таблица2[[#This Row],[Тип]]=коэф_произв[Тип])*(Таблица2[[#This Row],[Конструкция]]=коэф_произв[Значение])*('Таблица объектов'!I$1=коэф_произв[Характеристика]),коэф_произв[Коэффициент],"",0)} | L25: {=_xlfn.XLOOKUP(1,(Таблица2[[#This Row],[Тип]]=коэф_произв[Тип])*(Таблица2[[#This Row],[Полы]]=коэф_произв[Значение])*('Таблица объектов'!K$1=коэф_произв[Характеристика]),коэф_произв[Коэффициент],"",0)} | N25: {=_xlfn.XLOOKUP(1,(Таблица2[[#This Row],[Тип]]=коэф_произв[Тип])*(Таблица2[[#This Row],[Инженерное оснащение]]=коэф_произв[Значение])*('Таблица объектов'!M$1=коэф_произв[Характеристика]),коэф_произв[Коэффициент],"",0)} | P25: {=_xlfn.XLOOKUP(1,(Таблица2[[#This Row],[Тип]]=коэф_произв[Тип])*(Таблица2[[#This Row],[Архитектура]]=коэф_произв[Значение])*('Таблица объектов'!O$1=коэф_произв[Характеристика]),коэф_произв[Коэффициент],"",0)} | R25: {=_xlfn.XLOOKUP(1,(Таблица2[[#This Row],[Тип]]=коэф_произв[Тип])*(Таблица2[[#This Row],[Планировка]]=коэф_произв[Значение])*('Таблица объектов'!Q$1=коэф_произв[Характеристика]),коэф_произв[Коэффициент],"",0)} | T25: {=_xlfn.XLOOKUP(1,(Таблица2[[#This Row],[Тип]]=коэф_произв[Тип])*(Таблица2[[#This Row],[Уровень отделки]]=коэф_произв[Значение])*('Таблица объектов'!S$1=коэф_произв[Характеристика]),коэф_произв[Коэффициент],"",0)} | U25: =IF(Таблица2[[#This Row],[Тип]]="прочие",0.05,PRODUCT(Таблица2[[#This Row],[Уровень отделки коэф.]],Таблица2[[#This Row],[Планировка коэф.]],Таблица2[[#This Row],[Архитектура коэф.]],Таблица2[[#This Row],[Инженерное оснащение коэф.]],Таблица2[[#This Row],[Полы коэф.]],Таблица2[[#This Row],[Конструкция коэф.]],Таблица2[[#This Row],[Наличие / Возможность кран-балки коэф.]],Таблица2[[#This Row],[Высота коэф.]])) -> 0.05 | V25: =IF(Таблица2[[#This Row],[Тип]]="произв",IF(Таблица2[[#This Row],[Капитальность]]<0.33,"произв класс 4",IF(Таблица2[[#This Row],[Капитальность]]<0.55,"произв класс 3",IF(Таблица2[[#This Row],[Капитальность]]<0.77,"произв класс 2","произв класс 1"))),IF(Таблица2[[#This Row],[Тип]]="гражд",IF(Таблица2[[#This Row],[Капитальность]]<0.33,"гражд класс 4",IF(Таблица2[[#This Row],[Капитальность]]<0.55,"гражд класс 3",IF(Таблица2[[#This Row],[Капитальность]]<0.77,"гражд класс 2","гражд класс 1"))),"прочие")) -> прочие | W25: =Таблица2[[#This Row],[Площадь, м2]]*Таблица2[[#This Row],[Капитальность]] -> 8.055 | X25: =IF(AB25<4%,5,IF(AB25<9%,4.5,IF(AB25<14%,4,IF(AB25<24%,3.5,IF(AB25<40%,3,IF(AB25<60%,2.5,IF(AB25<80%,2,1))))))) -> 3 | Y25: =X25*Таблица2[[#This Row],[Площадь, м2]] -> 483.3 | Z25: =Y25*Таблица2[[#This Row],[Капитальность]] -> 24.165 | AB25: 0.25
A26: Объект оценки 3 | B26: 37.4 | C26: Навес | D26: прочие | F26: {=_xlfn.XLOOKUP(1,(Таблица2[[#This Row],[Тип]]=коэф_произв[Тип])*(Таблица2[[#This Row],[Высота]]=коэф_произв[Значение])*('Таблица объектов'!E$1=коэф_произв[Характеристика]),коэф_произв[Коэффициент],"",0)} | H26: {=_xlfn.XLOOKUP(1,(Таблица2[[#This Row],[Тип]]=коэф_произв[Тип])*(Таблица2[[#This Row],[Наличие / Возможность кран-балки]]=коэф_произв[Значение])*('Таблица объектов'!G$1=коэф_произв[Характеристика]),коэф_произв[Коэффициент],"",0)} | J26: {=_xlfn.XLOOKUP(1,(Таблица2[[#This Row],[Тип]]=коэф_произв[Тип])*(Таблица2[[#This Row],[Конструкция]]=коэф_произв[Значение])*('Таблица объектов'!I$1=коэф_произв[Характеристика]),коэф_произв[Коэффициент],"",0)} | L26: {=_xlfn.XLOOKUP(1,(Таблица2[[#This Row],[Тип]]=коэф_произв[Тип])*(Таблица2[[#This Row],[Полы]]=коэф_произв[Значение])*('Таблица объектов'!K$1=коэф_произв[Характеристика]),коэф_произв[Коэффициент],"",0)} | N26: {=_xlfn.XLOOKUP(1,(Таблица2[[#This Row],[Тип]]=коэф_произв[Тип])*(Таблица2[[#This Row],[Инженерное оснащение]]=коэф_произв[Значение])*('Таблица объектов'!M$1=коэф_произв[Характеристика]),коэф_произв[Коэффициент],"",0)} | P26: {=_xlfn.XLOOKUP(1,(Таблица2[[#This Row],[Тип]]=коэф_произв[Тип])*(Таблица2[[#This Row],[Архитектура]]=коэф_произв[Значение])*('Таблица объектов'!O$1=коэф_произв[Характеристика]),коэф_произв[Коэффициент],"",0)} | R26: {=_xlfn.XLOOKUP(1,(Таблица2[[#This Row],[Тип]]=коэф_произв[Тип])*(Таблица2[[#This Row],[Планировка]]=коэф_произв[Значение])*('Таблица объектов'!Q$1=коэф_произв[Характеристика]),коэф_произв[Коэффициент],"",0)} | T26: {=_xlfn.XLOOKUP(1,(Таблица2[[#This Row],[Тип]]=коэф_произв[Тип])*(Таблица2[[#This Row],[Уровень отделки]]=коэф_произв[Значение])*('Таблица объектов'!S$1=коэф_произв[Характеристика]),коэф_произв[Коэффициент],"",0)} | U26: =IF(Таблица2[[#This Row],[Тип]]="прочие",0.05,PRODUCT(Таблица2[[#This Row],[Уровень отделки коэф.]],Таблица2[[#This Row],[Планировка коэф.]],Таблица2[[#This Row],[Архитектура коэф.]],Таблица2[[#This Row],[Инженерное оснащение коэф.]],Таблица2[[#This Row],[Полы коэф.]],Таблица2[[#This Row],[Конструкция коэф.]],Таблица2[[#This Row],[Наличие / Возможность кран-балки коэф.]],Таблица2[[#This Row],[Высота коэф.]])) -> 0.05 | V26: =IF(Таблица2[[#This Row],[Тип]]="произв",IF(Таблица2[[#This Row],[Капитальность]]<0.33,"произв класс 4",IF(Таблица2[[#This Row],[Капитальность]]<0.55,"произв класс 3",IF(Таблица2[[#This Row],[Капитальность]]<0.77,"произв класс 2","произв класс 1"))),IF(Таблица2[[#This Row],[Тип]]="гражд",IF(Таблица2[[#This Row],[Капитальность]]<0.33,"гражд класс 4",IF(Таблица2[[#This Row],[Капитальность]]<0.55,"гражд класс 3",IF(Таблица2[[#This Row],[Капитальность]]<0.77,"гражд класс 2","гражд класс 1"))),"прочие")) -> прочие | W26: =Таблица2[[#This Row],[Площадь, м2]]*Таблица2[[#This Row],[Капитальность]] -> 1.87 | X26: =IF(AB26<4%,5,IF(AB26<9%,4.5,IF(AB26<14%,4,IF(AB26<24%,3.5,IF(AB26<40%,3,IF(AB26<60%,2.5,IF(AB26<80%,2,1))))))) -> 3 | Y26: =X26*Таблица2[[#This Row],[Площадь, м2]] -> 112.2 | Z26: =Y26*Таблица2[[#This Row],[Капитальность]] -> 5.61 | AB26: 0.25
A27: Объект оценки 3 | B27: 53.8 | C27: Навес | D27: прочие | F27: {=_xlfn.XLOOKUP(1,(Таблица2[[#This Row],[Тип]]=коэф_произв[Тип])*(Таблица2[[#This Row],[Высота]]=коэф_произв[Значение])*('Таблица объектов'!E$1=коэф_произв[Характеристика]),коэф_произв[Коэффициент],"",0)} | H27: {=_xlfn.XLOOKUP(1,(Таблица2[[#This Row],[Тип]]=коэф_произв[Тип])*(Таблица2[[#This Row],[Наличие / Возможность кран-балки]]=коэф_произв[Значение])*('Таблица объектов'!G$1=коэф_произв[Характеристика]),коэф_произв[Коэффициент],"",0)} | J27: {=_xlfn.XLOOKUP(1,(Таблица2[[#This Row],[Тип]]=коэф_произв[Тип])*(Таблица2[[#This Row],[Конструкция]]=коэф_произв[Значение])*('Таблица объектов'!I$1=коэф_произв[Характеристика]),коэф_произв[Коэффициент],"",0)} | L27: {=_xlfn.XLOOKUP(1,(Таблица2[[#This Row],[Тип]]=коэф_произв[Тип])*(Таблица2[[#This Row],[Полы]]=коэф_произв[Значение])*('Таблица объектов'!K$1=коэф_произв[Характеристика]),коэф_произв[Коэффициент],"",0)} | N27: {=_xlfn.XLOOKUP(1,(Таблица2[[#This Row],[Тип]]=коэф_произв[Тип])*(Таблица2[[#This Row],[Инженерное оснащение]]=коэф_произв[Значение])*('Таблица объектов'!M$1=коэф_произв[Характеристика]),коэф_произв[Коэффициент],"",0)} | P27: {=_xlfn.XLOOKUP(1,(Таблица2[[#This Row],[Тип]]=коэф_произв[Тип])*(Таблица2[[#This Row],[Архитектура]]=коэф_произв[Значение])*('Таблица объектов'!O$1=коэф_произв[Характеристика]),коэф_произв[Коэффициент],"",0)} | R27: {=_xlfn.XLOOKUP(1,(Таблица2[[#This Row],[Тип]]=коэф_произв[Тип])*(Таблица2[[#This Row],[Планировка]]=коэф_произв[Значение])*('Таблица объектов'!Q$1=коэф_произв[Характеристика]),коэф_произв[Коэффициент],"",0)} | T27: {=_xlfn.XLOOKUP(1,(Таблица2[[#This Row],[Тип]]=коэф_произв[Тип])*(Таблица2[[#This Row],[Уровень отделки]]=коэф_произв[Значение])*('Таблица объектов'!S$1=коэф_произв[Характеристика]),коэф_произв[Коэффициент],"",0)} | U27: =IF(Таблица2[[#This Row],[Тип]]="прочие",0.05,PRODUCT(Таблица2[[#This Row],[Уровень отделки коэф.]],Таблица2[[#This Row],[Планировка коэф.]],Таблица2[[#This Row],[Архитектура коэф.]],Таблица2[[#This Row],[Инженерное оснащение коэф.]],Таблица2[[#This Row],[Полы коэф.]],Таблица2[[#This Row],[Конструкция коэф.]],Таблица2[[#This Row],[Наличие / Возможность кран-балки коэф.]],Таблица2[[#This Row],[Высота коэф.]])) -> 0.05 | V27: =IF(Таблица2[[#This Row],[Тип]]="произв",IF(Таблица2[[#This Row],[Капитальность]]<0.33,"произв класс 4",IF(Таблица2[[#This Row],[Капитальность]]<0.55,"произв класс 3",IF(Таблица2[[#This Row],[Капитальность]]<0.77,"произв класс 2","произв класс 1"))),IF(Таблица2[[#This Row],[Тип]]="гражд",IF(Таблица2[[#This Row],[Капитальность]]<0.33,"гражд класс 4",IF(Таблица2[[#This Row],[Капитальность]]<0.55,"гражд класс 3",IF(Таблица2[[#This Row],[Капитальность]]<0.77,"гражд класс 2","гражд класс 1"))),"прочие")) -> прочие | W27: =Таблица2[[#This Row],[Площадь, м2]]*Таблица2[[#This Row],[Капитальность]] -> 2.69 | X27: =IF(AB27<4%,5,IF(AB27<9%,4.5,IF(AB27<14%,4,IF(AB27<24%,3.5,IF(AB27<40%,3,IF(AB27<60%,2.5,IF(AB27<80%,2,1))))))) -> 3 | Y27: =X27*Таблица2[[#This Row],[Площадь, м2]] -> 161.4 | Z27: =Y27*Таблица2[[#This Row],[Капитальность]] -> 8.07 | AB27: 0.25
A28: Объект оценки 3 | B28: 82.6 | C28: Навес | D28: прочие | F28: {=_xlfn.XLOOKUP(1,(Таблица2[[#This Row],[Тип]]=коэф_произв[Тип])*(Таблица2[[#This Row],[Высота]]=коэф_произв[Значение])*('Таблица объектов'!E$1=коэф_произв[Характеристика]),коэф_произв[Коэффициент],"",0)} | H28: {=_xlfn.XLOOKUP(1,(Таблица2[[#This Row],[Тип]]=коэф_произв[Тип])*(Таблица2[[#This Row],[Наличие / Возможность кран-балки]]=коэф_произв[Значение])*('Таблица объектов'!G$1=коэф_произв[Характеристика]),коэф_произв[Коэффициент],"",0)} | J28: {=_xlfn.XLOOKUP(1,(Таблица2[[#This Row],[Тип]]=коэф_произв[Тип])*(Таблица2[[#This Row],[Конструкция]]=коэф_произв[Значение])*('Таблица объектов'!I$1=коэф_произв[Характеристика]),коэф_произв[Коэффициент],"",0)} | L28: {=_xlfn.XLOOKUP(1,(Таблица2[[#This Row],[Тип]]=коэф_произв[Тип])*(Таблица2[[#This Row],[Полы]]=коэф_произв[Значение])*('Таблица объектов'!K$1=коэф_произв[Характеристика]),коэф_произв[Коэффициент],"",0)} | N28: {=_xlfn.XLOOKUP(1,(Таблица2[[#This Row],[Тип]]=коэф_произв[Тип])*(Таблица2[[#This Row],[Инженерное оснащение]]=коэф_произв[Значение])*('Таблица объектов'!M$1=коэф_произв[Характеристика]),коэф_произв[Коэффициент],"",0)} | P28: {=_xlfn.XLOOKUP(1,(Таблица2[[#This Row],[Тип]]=коэф_произв[Тип])*(Таблица2[[#This Row],[Архитектура]]=коэф_произв[Значение])*('Таблица объектов'!O$1=коэф_произв[Характеристика]),коэф_произв[Коэффициент],"",0)} | R28: {=_xlfn.XLOOKUP(1,(Таблица2[[#This Row],[Тип]]=коэф_произв[Тип])*(Таблица2[[#This Row],[Планировка]]=коэф_произв[Значение])*('Таблица объектов'!Q$1=коэф_произв[Характеристика]),коэф_произв[Коэффициент],"",0)} | T28: {=_xlfn.XLOOKUP(1,(Таблица2[[#This Row],[Тип]]=коэф_произв[Тип])*(Таблица2[[#This Row],[Уровень отделки]]=коэф_произв[Значение])*('Таблица объектов'!S$1=коэф_произв[Характеристика]),коэф_произв[Коэффициент],"",0)} | U28: =IF(Таблица2[[#This Row],[Тип]]="прочие",0.05,PRODUCT(Таблица2[[#This Row],[Уровень отделки коэф.]],Таблица2[[#This Row],[Планировка коэф.]],Таблица2[[#This Row],[Архитектура коэф.]],Таблица2[[#This Row],[Инженерное оснащение коэф.]],Таблица2[[#This Row],[Полы коэф.]],Таблица2[[#This Row],[Конструкция коэф.]],Таблица2[[#This Row],[Наличие / Возможность кран-балки коэф.]],Таблица2[[#This Row],[Высота коэф.]])) -> 0.05 | V28: =IF(Таблица2[[#This Row],[Тип]]="произв",IF(Таблица2[[#This Row],[Капитальность]]<0.33,"произв класс 4",IF(Таблица2[[#This Row],[Капитальность]]<0.55,"произв класс 3",IF(Таблица2[[#This Row],[Капитальность]]<0.77,"произв класс 2","произв класс 1"))),IF(Таблица2[[#This Row],[Тип]]="гражд",IF(Таблица2[[#This Row],[Капитальность]]<0.33,"гражд класс 4",IF(Таблица2[[#This Row],[Капитальность]]<0.55,"гражд класс 3",IF(Таблица2[[#This Row],[Капитальность]]<0.77,"гражд класс 2","гражд класс 1"))),"прочие")) -> прочие | W28: =Таблица2[[#This Row],[Площадь, м2]]*Таблица2[[#This Row],[Капитальность]] -> 4.13 | X28: =IF(AB28<4%,5,IF(AB28<9%,4.5,IF(AB28<14%,4,IF(AB28<24%,3.5,IF(AB28<40%,3,IF(AB28<60%,2.5,IF(AB28<80%,2,1))))))) -> 3 | Y28: =X28*Таблица2[[#This Row],[Площадь, м2]] -> 247.8 | Z28: =Y28*Таблица2[[#This Row],[Капитальность]] -> 12.39 | AB28: 0.3
A29: Объект оценки 3 | B29: 4.94 | C29: Комната охраны | D29: прочие | F29: {=_xlfn.XLOOKUP(1,(Таблица2[[#This Row],[Тип]]=коэф_произв[Тип])*(Таблица2[[#This Row],[Высота]]=коэф_произв[Значение])*('Таблица объектов'!E$1=коэф_произв[Характеристика]),коэф_произв[Коэффициент],"",0)} | H29: {=_xlfn.XLOOKUP(1,(Таблица2[[#This Row],[Тип]]=коэф_произв[Тип])*(Таблица2[[#This Row],[Наличие / Возможность кран-балки]]=коэф_произв[Значение])*('Таблица объектов'!G$1=коэф_произв[Характеристика]),коэф_произв[Коэффициент],"",0)} | J29: {=_xlfn.XLOOKUP(1,(Таблица2[[#This Row],[Тип]]=коэф_произв[Тип])*(Таблица2[[#This Row],[Конструкция]]=коэф_произв[Значение])*('Таблица объектов'!I$1=коэф_произв[Характеристика]),коэф_произв[Коэффициент],"",0)} | L29: {=_xlfn.XLOOKUP(1,(Таблица2[[#This Row],[Тип]]=коэф_произв[Тип])*(Таблица2[[#This Row],[Полы]]=коэф_произв[Значение])*('Таблица объектов'!K$1=коэф_произв[Характеристика]),коэф_произв[Коэффициент],"",0)} | N29: {=_xlfn.XLOOKUP(1,(Таблица2[[#This Row],[Тип]]=коэф_произв[Тип])*(Таблица2[[#This Row],[Инженерное оснащение]]=коэф_произв[Значение])*('Таблица объектов'!M$1=коэф_произв[Характеристика]),коэф_произв[Коэффициент],"",0)} | P29: {=_xlfn.XLOOKUP(1,(Таблица2[[#This Row],[Тип]]=коэф_произв[Тип])*(Таблица2[[#This Row],[Архитектура]]=коэф_произв[Значение])*('Таблица объектов'!O$1=коэф_произв[Характеристика]),коэф_произв[Коэффициент],"",0)} | R29: {=_xlfn.XLOOKUP(1,(Таблица2[[#This Row],[Тип]]=коэф_произв[Тип])*(Таблица2[[#This Row],[Планировка]]=коэф_произв[Значение])*('Таблица объектов'!Q$1=коэф_произв[Характеристика]),коэф_произв[Коэффициент],"",0)} | T29: {=_xlfn.XLOOKUP(1,(Таблица2[[#This Row],[Тип]]=коэф_произв[Тип])*(Таблица2[[#This Row],[Уровень отделки]]=коэф_произв[Значение])*('Таблица объектов'!S$1=коэф_произв[Характеристика]),коэф_произв[Коэффициент],"",0)} | U29: =IF(Таблица2[[#This Row],[Тип]]="прочие",0.05,PRODUCT(Таблица2[[#This Row],[Уровень отделки коэф.]],Таблица2[[#This Row],[Планировка коэф.]],Таблица2[[#This Row],[Архитектура коэф.]],Таблица2[[#This Row],[Инженерное оснащение коэф.]],Таблица2[[#This Row],[Полы коэф.]],Таблица2[[#This Row],[Конструкция коэф.]],Таблица2[[#This Row],[Наличие / Возможность кран-балки коэф.]],Таблица2[[#This Row],[Высота коэф.]])) -> 0.05 | V29: =IF(Таблица2[[#This Row],[Тип]]="произв",IF(Таблица2[[#This Row],[Капитальность]]<0.33,"произв класс 4",IF(Таблица2[[#This Row],[Капитальность]]<0.55,"произв класс 3",IF(Таблица2[[#This Row],[Капитальность]]<0.77,"произв класс 2","произв класс 1"))),IF(Таблица2[[#This Row],[Тип]]="гражд",IF(Таблица2[[#This Row],[Капитальность]]<0.33,"гражд класс 4",IF(Таблица2[[#This Row],[Капитальность]]<0.55,"гражд класс 3",IF(Таблица2[[#This Row],[Капитальность]]<0.77,"гражд класс 2","гражд класс 1"))),"прочие")) -> прочие | W29: =Таблица2[[#This Row],[Площадь, м2]]*Таблица2[[#This Row],[Капитальность]] -> 0.247 | X29: =IF(AB29<4%,5,IF(AB29<9%,4.5,IF(AB29<14%,4,IF(AB29<24%,3.5,IF(AB29<40%,3,IF(AB29<60%,2.5,IF(AB29<80%,2,1))))))) -> 3.5 | Y29: =X29*Таблица2[[#This Row],[Площадь, м2]] -> 17.29 | Z29: =Y29*Таблица2[[#This Row],[Капитальность]] -> 0.8645 | AB29: 0.2
A30: Объект оценки 3 | B30: 158.08 | C30: Гараж металлический | D30: произв | E30: 3-5 м. | F30: {=_xlfn.XLOOKUP(1,(Таблица2[[#This Row],[Тип]]=коэф_произв[Тип])*(Таблица2[[#This Row],[Высота]]=коэф_произв[Значение])*('Таблица объектов'!E$1=коэф_произв[Характеристика]),коэф_произв[Коэффициент],"",0)} -> 0.6 | G30: Нет | H30: {=_xlfn.XLOOKUP(1,(Таблица2[[#This Row],[Тип]]=коэф_произв[Тип])*(Таблица2[[#This Row],[Наличие / Возможность кран-балки]]=коэф_произв[Значение])*('Таблица объектов'!G$1=коэф_произв[Характеристика]),коэф_произв[Коэффициент],"",0)} -> 0.9 | I30: Блочные бескаркасные или металлокаркасные холодные | J30: {=_xlfn.XLOOKUP(1,(Таблица2[[#This Row],[Тип]]=коэф_произв[Тип])*(Таблица2[[#This Row],[Конструкция]]=коэф_произв[Значение])*('Таблица объектов'!I$1=коэф_произв[Характеристика]),коэф_произв[Коэффициент],"",0)} -> 0.5 | K30: Отсутствуют | L30: {=_xlfn.XLOOKUP(1,(Таблица2[[#This Row],[Тип]]=коэф_произв[Тип])*(Таблица2[[#This Row],[Полы]]=коэф_произв[Значение])*('Таблица объектов'!K$1=коэф_произв[Характеристика]),коэф_произв[Коэффициент],"",0)} -> 0.8 | M30: Отсутствует или минимальное (минимальная разводка освещения, водопровода) | N30: {=_xlfn.XLOOKUP(1,(Таблица2[[#This Row],[Тип]]=коэф_произв[Тип])*(Таблица2[[#This Row],[Инженерное оснащение]]=коэф_произв[Значение])*('Таблица объектов'!M$1=коэф_произв[Характеристика]),коэф_произв[Коэффициент],"",0)} -> 0.8 | P30: {=_xlfn.XLOOKUP(1,(Таблица2[[#This Row],[Тип]]=коэф_произв[Тип])*(Таблица2[[#This Row],[Архитектура]]=коэф_произв[Значение])*('Таблица объектов'!O$1=коэф_произв[Характеристика]),коэф_произв[Коэффициент],"",0)} | R30: {=_xlfn.XLOOKUP(1,(Таблица2[[#This Row],[Тип]]=коэф_произв[Тип])*(Таблица2[[#This Row],[Планировка]]=коэф_произв[Значение])*('Таблица объектов'!Q$1=коэф_произв[Характеристика]),коэф_произв[Коэффициент],"",0)} | T30: {=_xlfn.XLOOKUP(1,(Таблица2[[#This Row],[Тип]]=коэф_произв[Тип])*(Таблица2[[#This Row],[Уровень отделки]]=коэф_произв[Значение])*('Таблица объектов'!S$1=коэф_произв[Характеристика]),коэф_произв[Коэффициент],"",0)} | U30: =IF(Таблица2[[#This Row],[Тип]]="прочие",0.05,PRODUCT(Таблица2[[#This Row],[Уровень отделки коэф.]],Таблица2[[#This Row],[Планировка коэф.]],Таблица2[[#This Row],[Архитектура коэф.]],Таблица2[[#This Row],[Инженерное оснащение коэф.]],Таблица2[[#This Row],[Полы коэф.]],Таблица2[[#This Row],[Конструкция коэф.]],Таблица2[[#This Row],[Наличие / Возможность кран-балки коэф.]],Таблица2[[#This Row],[Высота коэф.]])) -> 0.1728 | V30: =IF(Таблица2[[#This Row],[Тип]]="произв",IF(Таблица2[[#This Row],[Капитальность]]<0.33,"произв класс 4",IF(Таблица2[[#This Row],[Капитальность]]<0.55,"произв класс 3",IF(Таблица2[[#This Row],[Капитальность]]<0.77,"произв класс 2","произв класс 1"))),IF(Таблица2[[#This Row],[Тип]]="гражд",IF(Таблица2[[#This Row],[Капитальность]]<0.33,"гражд класс 4",IF(Таблица2[[#This Row],[Капитальность]]<0.55,"гражд класс 3",IF(Таблица2[[#This Row],[Капитальность]]<0.77,"гражд класс 2","гражд класс 1"))),"прочие")) -> произв класс 4 | W30: =Таблица2[[#This Row],[Площадь, м2]]*Таблица2[[#This Row],[Капитальность]] -> 27.316224 | X30: =IF(AB30<4%,5,IF(AB30<9%,4.5,IF(AB30<14%,4,IF(AB30<24%,3.5,IF(AB30<40%,3,IF(AB30<60%,2.5,IF(AB30<80%,2,1))))))) -> 2.5 | Y30: =X30*Таблица2[[#This Row],[Площадь, м2]] -> 395.2 | Z30: =Y30*Таблица2[[#This Row],[Капитальность]] -> 68.29056 | AB30: 0.566
A31: Объект оценки 4 | B31: 1576.1 | C31: Производственное нежилое помещение | D31: произв | E31: 5-8 м. | F31: {=_xlfn.XLOOKUP(1,(Таблица2[[#This Row],[Тип]]=коэф_произв[Тип])*(Таблица2[[#This Row],[Высота]]=коэф_произв[Значение])*('Таблица объектов'!E$1=коэф_произв[Характеристика]),коэф_произв[Коэффициент],"",0)} -> 0.8 | G31: Не установлено (по умолчанию) | H31: {=_xlfn.XLOOKUP(1,(Таблица2[[#This Row],[Тип]]=коэф_произв[Тип])*(Таблица2[[#This Row],[Наличие / Возможность кран-балки]]=коэф_произв[Значение])*('Таблица объектов'!G$1=коэф_произв[Характеристика]),коэф_произв[Коэффициент],"",0)} -> 0.95 | I31: Блочные по железобетонному каркасу, утепленные | J31: {=_xlfn.XLOOKUP(1,(Таблица2[[#This Row],[Тип]]=коэф_произв[Тип])*(Таблица2[[#This Row],[Конструкция]]=коэф_произв[Значение])*('Таблица объектов'!I$1=коэф_произв[Характеристика]),коэф_произв[Коэффициент],"",0)} -> 1 | K31: Простые | L31: {=_xlfn.XLOOKUP(1,(Таблица2[[#This Row],[Тип]]=коэф_произв[Тип])*(Таблица2[[#This Row],[Полы]]=коэф_произв[Значение])*('Таблица объектов'!K$1=коэф_произв[Характеристика]),коэф_произв[Коэффициент],"",0)} -> 0.9 | M31: Стандартное (по всем помещениям разводка освещения, водопровод, канализация) | N31: {=_xlfn.XLOOKUP(1,(Таблица2[[#This Row],[Тип]]=коэф_произв[Тип])*(Таблица2[[#This Row],[Инженерное оснащение]]=коэф_произв[Значение])*('Таблица объектов'!M$1=коэф_произв[Характеристика]),коэф_произв[Коэффициент],"",0)} -> 0.9 | P31: {=_xlfn.XLOOKUP(1,(Таблица2[[#This Row],[Тип]]=коэф_произв[Тип])*(Таблица2[[#This Row],[Архитектура]]=коэф_произв[Значение])*('Таблица объектов'!O$1=коэф_произв[Характеристика]),коэф_произв[Коэффициент],"",0)} | R31: {=_xlfn.XLOOKUP(1,(Таблица2[[#This Row],[Тип]]=коэф_произв[Тип])*(Таблица2[[#This Row],[Планировка]]=коэф_произв[Значение])*('Таблица объектов'!Q$1=коэф_произв[Характеристика]),коэф_произв[Коэффициент],"",0)} | T31: {=_xlfn.XLOOKUP(1,(Таблица2[[#This Row],[Тип]]=коэф_произв[Тип])*(Таблица2[[#This Row],[Уровень отделки]]=коэф_произв[Значение])*('Таблица объектов'!S$1=коэф_произв[Характеристика]),коэф_произв[Коэффициент],"",0)} | U31: =IF(Таблица2[[#This Row],[Тип]]="прочие",0.05,PRODUCT(Таблица2[[#This Row],[Уровень отделки коэф.]],Таблица2[[#This Row],[Планировка коэф.]],Таблица2[[#This Row],[Архитектура коэф.]],Таблица2[[#This Row],[Инженерное оснащение коэф.]],Таблица2[[#This Row],[Полы коэф.]],Таблица2[[#This Row],[Конструкция коэф.]],Таблица2[[#This Row],[Наличие / Возможность кран-балки коэф.]],Таблица2[[#This Row],[Высота коэф.]])) -> 0.6156 | V31: =IF(Таблица2[[#This Row],[Тип]]="произв",IF(Таблица2[[#This Row],[Капитальность]]<0.33,"произв класс 4",IF(Таблица2[[#This Row],[Капитальность]]<0.55,"произв класс 3",IF(Таблица2[[#This Row],[Капитальность]]<0.77,"произв класс 2","произв класс 1"))),IF(Таблица2[[#This Row],[Тип]]="гражд",IF(Таблица2[[#This Row],[Капитальность]]<0.33,"гражд класс 4",IF(Таблица2[[#This Row],[Капитальность]]<0.55,"гражд класс 3",IF(Таблица2[[#This Row],[Капитальность]]<0.77,"гражд класс 2","гражд класс 1"))),"прочие")) -> произв класс 2 | W31: =Таблица2[[#This Row],[Площадь, м2]]*Таблица2[[#This Row],[Капитальность]] -> 970.24716 | X31: =IF(AB31<4%,5,IF(AB31<9%,4.5,IF(AB31<14%,4,IF(AB31<24%,3.5,IF(AB31<40%,3,IF(AB31<60%,2.5,IF(AB31<80%,2,1))))))) -> 3 | Y31: =X31*Таблица2[[#This Row],[Площадь, м2]] -> 4728.3 | Z31: =Y31*Таблица2[[#This Row],[Капитальность]] -> 2910.7415 | AB31: 0.337
A32: Объект оценки 4 | B32: 221.2 | C32: Производственное нежилое помещение | D32: гражд | E32: 3,2-4 м. | F32: {=_xlfn.XLOOKUP(1,(Таблица2[[#This Row],[Тип]]=коэф_произв[Тип])*(Таблица2[[#This Row],[Высота]]=коэф_произв[Значение])*('Таблица объектов'!E$1=коэф_произв[Характеристика]),коэф_произв[Коэффициент],"",0)} -> 0.8 | H32: {=_xlfn.XLOOKUP(1,(Таблица2[[#This Row],[Тип]]=коэф_произв[Тип])*(Таблица2[[#This Row],[Наличие / Возможность кран-балки]]=коэф_произв[Значение])*('Таблица объектов'!G$1=коэф_произв[Характеристика]),коэф_произв[Коэффициент],"",0)} | I32: Смешанная | J32: {=_xlfn.XLOOKUP(1,(Таблица2[[#This Row],[Тип]]=коэф_произв[Тип])*(Таблица2[[#This Row],[Конструкция]]=коэф_произв[Значение])*('Таблица объектов'!I$1=коэф_произв[Характеристика]),коэф_произв[Коэффициент],"",0)} -> 0.9 | L32: {=_xlfn.XLOOKUP(1,(Таблица2[[#This Row],[Тип]]=коэф_произв[Тип])*(Таблица2[[#This Row],[Полы]]=коэф_произв[Значение])*('Таблица объектов'!K$1=коэф_произв[Характеристика]),коэф_произв[Коэффициент],"",0)} | M32: Стандартное (по всем помещениям разводка освещения, водопровод, канализация) | N32: {=_xlfn.XLOOKUP(1,(Таблица2[[#This Row],[Тип]]=коэф_произв[Тип])*(Таблица2[[#This Row],[Инженерное оснащение]]=коэф_произв[Значение])*('Таблица объектов'!M$1=коэф_произв[Характеристика]),коэф_произв[Коэффициент],"",0)} -> 0.9 | O32: Устаревшая/ Современная | P32: {=_xlfn.XLOOKUP(1,(Таблица2[[#This Row],[Тип]]=коэф_произв[Тип])*(Таблица2[[#This Row],[Архитектура]]=коэф_произв[Значение])*('Таблица объектов'!O$1=коэф_произв[Характеристика]),коэф_произв[Коэффициент],"",0)} -> 0.9 | Q32: Смешанная | R32: {=_xlfn.XLOOKUP(1,(Таблица2[[#This Row],[Тип]]=коэф_произв[Тип])*(Таблица2[[#This Row],[Планировка]]=коэф_произв[Значение])*('Таблица объектов'!Q$1=коэф_произв[Характеристика]),коэф_произв[Коэффициент],"",0)} -> 0.95 | S32: Простая (потолки и стены оштукатурены, окрашены или отделаны дешевыми материалами (МДФ), полы линолеумные | T32: {=_xlfn.XLOOKUP(1,(Таблица2[[#This Row],[Тип]]=коэф_произв[Тип])*(Таблица2[[#This Row],[Уровень отделки]]=коэф_произв[Значение])*('Таблица объектов'!S$1=коэф_произв[Характеристика]),коэф_произв[Коэффициент],"",0)} -> 0.7 | U32: =IF(Таблица2[[#This Row],[Тип]]="прочие",0.05,PRODUCT(Таблица2[[#This Row],[Уровень отделки коэф.]],Таблица2[[#This Row],[Планировка коэф.]],Таблица2[[#This Row],[Архитектура коэф.]],Таблица2[[#This Row],[Инженерное оснащение коэф.]],Таблица2[[#This Row],[Полы коэф.]],Таблица2[[#This Row],[Конструкция коэф.]],Таблица2[[#This Row],[Наличие / Возможность кран-балки коэф.]],Таблица2[[#This Row],[Высота коэф.]])) -> 0.387828 | V32: =IF(Таблица2[[#This Row],[Тип]]="произв",IF(Таблица2[[#This Row],[Капитальность]]<0.33,"произв класс 4",IF(Таблица2[[#This Row],[Капитальность]]<0.55,"произв класс 3",IF(Таблица2[[#This Row],[Капитальность]]<0.77,"произв класс 2","произв класс 1"))),IF(Таблица2[[#This Row],[Тип]]="гражд",IF(Таблица2[[#This Row],[Капитальность]]<0.33,"гражд класс 4",IF(Таблица2[[#This Row],[Капитальность]]<0.55,"гражд класс 3",IF(Таблица2[[#This Row],[Капитальность]]<0.77,"гражд класс 2","гражд класс 1"))),"прочие")) -> гражд класс 3 | W32: =Таблица2[[#This Row],[Площадь, м2]]*Таблица2[[#This Row],[Капитальность]] -> 85.787554 | X32: =IF(AB32<4%,5,IF(AB32<9%,4.5,IF(AB32<14%,4,IF(AB32<24%,3.5,IF(AB32<40%,3,IF(AB32<60%,2.5,IF(AB32<80%,2,1))))))) -> 3 | Y32: =X32*Таблица2[[#This Row],[Площадь, м2]] -> 663.6 | Z32: =Y32*Таблица2[[#This Row],[Капитальность]] -> 257.36266 | AB32: 0.337
A33: Объект оценки 4 | B33: 1281.5 | C33: Производственное помещение | D33: произв | E33: 3-5 м. | F33: {=_xlfn.XLOOKUP(1,(Таблица2[[#This Row],[Тип]]=коэф_произв[Тип])*(Таблица2[[#This Row],[Высота]]=коэф_произв[Значение])*('Таблица объектов'!E$1=коэф_произв[Характеристика]),коэф_произв[Коэффициент],"",0)} -> 0.6 | G33: Нет | H33: {=_xlfn.XLOOKUP(1,(Таблица2[[#This Row],[Тип]]=коэф_произв[Тип])*(Таблица2[[#This Row],[Наличие / Возможность кран-балки]]=коэф_произв[Значение])*('Таблица объектов'!G$1=коэф_произв[Характеристика]),коэф_произв[Коэффициент],"",0)} -> 0.9 | I33: Блочные по железобетонному каркасу, утепленные | J33: 0.85 | K33: Простые | L33: {=_xlfn.XLOOKUP(1,(Таблица2[[#This Row],[Тип]]=коэф_произв[Тип])*(Таблица2[[#This Row],[Полы]]=коэф_произв[Значение])*('Таблица объектов'!K$1=коэф_произв[Характеристика]),коэф_произв[Коэффициент],"",0)} -> 0.9 | M33: Отсутствует или минимальное (минимальная разводка освещения, водопровода) | N33: {=_xlfn.XLOOKUP(1,(Таблица2[[#This Row],[Тип]]=коэф_произв[Тип])*(Таблица2[[#This Row],[Инженерное оснащение]]=коэф_произв[Значение])*('Таблица объектов'!M$1=коэф_произв[Характеристика]),коэф_произв[Коэффициент],"",0)} -> 0.8 | P33: {=_xlfn.XLOOKUP(1,(Таблица2[[#This Row],[Тип]]=коэф_произв[Тип])*(Таблица2[[#This Row],[Архитектура]]=коэф_произв[Значение])*('Таблица объектов'!O$1=коэф_произв[Характеристика]),коэф_произв[Коэффициент],"",0)} | R33: {=_xlfn.XLOOKUP(1,(Таблица2[[#This Row],[Тип]]=коэф_произв[Тип])*(Таблица2[[#This Row],[Планировка]]=коэф_произв[Значение])*('Таблица объектов'!Q$1=коэф_произв[Характеристика]),коэф_произв[Коэффициент],"",0)} | T33: {=_xlfn.XLOOKUP(1,(Таблица2[[#This Row],[Тип]]=коэф_произв[Тип])*(Таблица2[[#This Row],[Уровень отделки]]=коэф_произв[Значение])*('Таблица объектов'!S$1=коэф_произв[Характеристика]),коэф_произв[Коэффициент],"",0)} | U33: =IF(Таблица2[[#This Row],[Тип]]="прочие",0.05,PRODUCT(Таблица2[[#This Row],[Уровень отделки коэф.]],Таблица2[[#This Row],[Планировка коэф.]],Таблица2[[#This Row],[Архитектура коэф.]],Таблица2[[#This Row],[Инженерное оснащение коэф.]],Таблица2[[#This Row],[Полы коэф.]],Таблица2[[#This Row],[Конструкция коэф.]],Таблица2[[#This Row],[Наличие / Возможность кран-балки коэф.]],Таблица2[[#This Row],[Высота коэф.]])) -> 0.33048 | V33: =IF(Таблица2[[#This Row],[Тип]]="произв",IF(Таблица2[[#This Row],[Капитальность]]<0.33,"произв класс 4",IF(Таблица2[[#This Row],[Капитальность]]<0.55,"произв класс 3",IF(Таблица2[[#This Row],[Капитальность]]<0.77,"произв класс 2","произв класс 1"))),IF(Таблица2[[#This Row],[Тип]]="гражд",IF(Таблица2[[#This Row],[Капитальность]]<0.33,"гражд класс 4",IF(Таблица2[[#This Row],[Капитальность]]<0.55,"гражд класс 3",IF(Таблица2[[#This Row],[Капитальность]]<0.77,"гражд класс 2","гражд класс 1"))),"прочие")) -> произв класс 3 | W33: =Таблица2[[#This Row],[Площадь, м2]]*Таблица2[[#This Row],[Капитальность]] -> 423.51012 | X33: =IF(AB33<4%,5,IF(AB33<9%,4.5,IF(AB33<14%,4,IF(AB33<24%,3.5,IF(AB33<40%,3,IF(AB33<60%,2.5,IF(AB33<80%,2,1))))))) -> 5 | Y33: =X33*Таблица2[[#This Row],[Площадь, м2]] -> 6407.5 | Z33: =Y33*Таблица2[[#This Row],[Капитальность]] -> 2117.5506 | AB33: 0.009
A34: Объект оценки 4 | B34: 857.3 | C34: Производственное помещение | D34: произв | E34: 5-8 м. | F34: {=_xlfn.XLOOKUP(1,(Таблица2[[#This Row],[Тип]]=коэф_произв[Тип])*(Таблица2[[#This Row],[Высота]]=коэф_произв[Значение])*('Таблица объектов'!E$1=коэф_произв[Характеристика]),коэф_произв[Коэффициент],"",0)} -> 0.8 | G34: Нет | H34: {=_xlfn.XLOOKUP(1,(Таблица2[[#This Row],[Тип]]=коэф_произв[Тип])*(Таблица2[[#This Row],[Наличие / Возможность кран-балки]]=коэф_произв[Значение])*('Таблица объектов'!G$1=коэф_произв[Характеристика]),коэф_произв[Коэффициент],"",0)} -> 0.9 | I34: Блочные по железобетонному каркасу, без утепления | J34: {=_xlfn.XLOOKUP(1,(Таблица2[[#This Row],[Тип]]=коэф_произв[Тип])*(Таблица2[[#This Row],[Конструкция]]=коэф_произв[Значение])*('Таблица объектов'!I$1=коэф_произв[Характеристика]),коэф_произв[Коэффициент],"",0)} -> 0.7 | K34: Простые | L34: {=_xlfn.XLOOKUP(1,(Таблица2[[#This Row],[Тип]]=коэф_произв[Тип])*(Таблица2[[#This Row],[Полы]]=коэф_произв[Значение])*('Таблица объектов'!K$1=коэф_произв[Характеристика]),коэф_произв[Коэффициент],"",0)} -> 0.9 | M34: Отсутствует или минимальное (минимальная разводка освещения, водопровода) | N34: {=_xlfn.XLOOKUP(1,(Таблица2[[#This Row],[Тип]]=коэф_произв[Тип])*(Таблица2[[#This Row],[Инженерное оснащение]]=коэф_произв[Значение])*('Таблица объектов'!M$1=коэф_произв[Характеристика]),коэф_произв[Коэффициент],"",0)} -> 0.8 | P34: {=_xlfn.XLOOKUP(1,(Таблица2[[#This Row],[Тип]]=коэф_произв[Тип])*(Таблица2[[#This Row],[Архитектура]]=коэф_произв[Значение])*('Таблица объектов'!O$1=коэф_произв[Характеристика]),коэф_произв[Коэффициент],"",0)} | R34: {=_xlfn.XLOOKUP(1,(Таблица2[[#This Row],[Тип]]=коэф_произв[Тип])*(Таблица2[[#This Row],[Планировка]]=коэф_произв[Значение])*('Таблица объектов'!Q$1=коэф_произв[Характеристика]),коэф_произв[Коэффициент],"",0)} | T34: {=_xlfn.XLOOKUP(1,(Таблица2[[#This Row],[Тип]]=коэф_произв[Тип])*(Таблица2[[#This Row],[Уровень отделки]]=коэф_произв[Значение])*('Таблица объектов'!S$1=коэф_произв[Характеристика]),коэф_произв[Коэффициент],"",0)} | U34: =IF(Таблица2[[#This Row],[Тип]]="прочие",0.05,PRODUCT(Таблица2[[#This Row],[Уровень отделки коэф.]],Таблица2[[#This Row],[Планировка коэф.]],Таблица2[[#This Row],[Архитектура коэф.]],Таблица2[[#This Row],[Инженерное оснащение коэф.]],Таблица2[[#This Row],[Полы коэф.]],Таблица2[[#This Row],[Конструкция коэф.]],Таблица2[[#This Row],[Наличие / Возможность кран-балки коэф.]],Таблица2[[#This Row],[Высота коэф.]])) -> 0.36288 | V34: =IF(Таблица2[[#This Row],[Тип]]="произв",IF(Таблица2[[#This Row],[Капитальность]]<0.33,"произв класс 4",IF(Таблица2[[#This Row],[Капитальность]]<0.55,"произв класс 3",IF(Таблица2[[#This Row],[Капитальность]]<0.77,"произв класс 2","произв класс 1"))),IF(Таблица2[[#This Row],[Тип]]="гражд",IF(Таблица2[[#This Row],[Капитальность]]<0.33,"гражд класс 4",IF(Таблица2[[#This Row],[Капитальность]]<0.55,"гражд класс 3",IF(Таблица2[[#This Row],[Капитальность]]<0.77,"гражд класс 2","гражд класс 1"))),"прочие")) -> произв класс 3 | W34: =Таблица2[[#This Row],[Площадь, м2]]*Таблица2[[#This Row],[Капитальность]] -> 311.09702 | X34: =IF(AB34<4%,5,IF(AB34<9%,4.5,IF(AB34<14%,4,IF(AB34<24%,3.5,IF(AB34<40%,3,IF(AB34<60%,2.5,IF(AB34<80%,2,1))))))) -> 5 | Y34: =X34*Таблица2[[#This Row],[Площадь, м2]] -> 4286.5 | Z34: =Y34*Таблица2[[#This Row],[Капитальность]] -> 1555.4851 | AB34: 0.009
A35: Объект оценки 4 | B35: 2380.9 | C35: Производственное помещение | D35: произв | E35: 5-8 м. | F35: {=_xlfn.XLOOKUP(1,(Таблица2[[#This Row],[Тип]]=коэф_произв[Тип])*(Таблица2[[#This Row],[Высота]]=коэф_произв[Значение])*('Таблица объектов'!E$1=коэф_произв[Характеристика]),коэф_произв[Коэффициент],"",0)} -> 0.8 | G35: Нет | H35: {=_xlfn.XLOOKUP(1,(Таблица2[[#This Row],[Тип]]=коэф_произв[Тип])*(Таблица2[[#This Row],[Наличие / Возможность кран-балки]]=коэф_произв[Значение])*('Таблица объектов'!G$1=коэф_произв[Характеристика]),коэф_произв[Коэффициент],"",0)} -> 0.9 | I35: Блочные по железобетонному каркасу, утепленные | J35: 0.85 | K35: Простые | L35: {=_xlfn.XLOOKUP(1,(Таблица2[[#This Row],[Тип]]=коэф_произв[Тип])*(Таблица2[[#This Row],[Полы]]=коэф_произв[Значение])*('Таблица объектов'!K$1=коэф_произв[Характеристика]),коэф_произв[Коэффициент],"",0)} -> 0.9 | M35: Отсутствует или минимальное (минимальная разводка освещения, водопровода) | N35: {=_xlfn.XLOOKUP(1,(Таблица2[[#This Row],[Тип]]=коэф_произв[Тип])*(Таблица2[[#This Row],[Инженерное оснащение]]=коэф_произв[Значение])*('Таблица объектов'!M$1=коэф_произв[Характеристика]),коэф_произв[Коэффициент],"",0)} -> 0.8 | P35: {=_xlfn.XLOOKUP(1,(Таблица2[[#This Row],[Тип]]=коэф_произв[Тип])*(Таблица2[[#This Row],[Архитектура]]=коэф_произв[Значение])*('Таблица объектов'!O$1=коэф_произв[Характеристика]),коэф_произв[Коэффициент],"",0)} | R35: {=_xlfn.XLOOKUP(1,(Таблица2[[#This Row],[Тип]]=коэф_произв[Тип])*(Таблица2[[#This Row],[Планировка]]=коэф_произв[Значение])*('Таблица объектов'!Q$1=коэф_произв[Характеристика]),коэф_произв[Коэффициент],"",0)} | T35: {=_xlfn.XLOOKUP(1,(Таблица2[[#This Row],[Тип]]=коэф_произв[Тип])*(Таблица2[[#This Row],[Уровень отделки]]=коэф_произв[Значение])*('Таблица объектов'!S$1=коэф_произв[Характеристика]),коэф_произв[Коэффициент],"",0)} | U35: =IF(Таблица2[[#This Row],[Тип]]="прочие",0.05,PRODUCT(Таблица2[[#This Row],[Уровень отделки коэф.]],Таблица2[[#This Row],[Планировка коэф.]],Таблица2[[#This Row],[Архитектура коэф.]],Таблица2[[#This Row],[Инженерное оснащение коэф.]],Таблица2[[#This Row],[Полы коэф.]],Таблица2[[#This Row],[Конструкция коэф.]],Таблица2[[#This Row],[Наличие / Возможность кран-балки коэф.]],Таблица2[[#This Row],[Высота коэф.]])) -> 0.44064 | V35: =IF(Таблица2[[#This Row],[Тип]]="произв",IF(Таблица2[[#This Row],[Капитальность]]<0.33,"произв класс 4",IF(Таблица2[[#This Row],[Капитальность]]<0.55,"произв класс 3",IF(Таблица2[[#This Row],[Капитальность]]<0.77,"произв класс 2","произв класс 1"))),IF(Таблица2[[#This Row],[Тип]]="гражд",IF(Таблица2[[#This Row],[Капитальность]]<0.33,"гражд класс 4",IF(Таблица2[[#This Row],[Капитальность]]<0.55,"гражд класс 3",IF(Таблица2[[#This Row],[Капитальность]]<0.77,"гражд класс 2","гражд класс 1"))),"прочие")) -> произв класс 3 | W35: =Таблица2[[#This Row],[Площадь, м2]]*Таблица2[[#This Row],[Капитальность]] -> 1049.1198 | X35: =IF(AB35<4%,5,IF(AB35<9%,4.5,IF(AB35<14%,4,IF(AB35<24%,3.5,IF(AB35<40%,3,IF(AB35<60%,2.5,IF(AB35<80%,2,1))))))) -> 5 | Y35: =X35*Таблица2[[#This Row],[Площадь, м2]] -> 11904.5 | Z35: =Y35*Таблица2[[#This Row],[Капитальность]] -> 5245.5989 | AB35: 0.009
A36: Объект оценки 4 | B36: 138.7 | C36: Площадка | D36: произв | E36: 3-5 м. | F36: {=_xlfn.XLOOKUP(1,(Таблица2[[#This Row],[Тип]]=коэф_произв[Тип])*(Таблица2[[#This Row],[Высота]]=коэф_произв[Значение])*('Таблица объектов'!E$1=коэф_произв[Характеристика]),коэф_произв[Коэффициент],"",0)} -> 0.6 | G36: Нет | H36: {=_xlfn.XLOOKUP(1,(Таблица2[[#This Row],[Тип]]=коэф_произв[Тип])*(Таблица2[[#This Row],[Наличие / Возможность кран-балки]]=коэф_произв[Значение])*('Таблица объектов'!G$1=коэф_произв[Характеристика]),коэф_произв[Коэффициент],"",0)} -> 0.9 | I36: Блочные бескаркасные или металлокаркасные холодные | J36: {=_xlfn.XLOOKUP(1,(Таблица2[[#This Row],[Тип]]=коэф_произв[Тип])*(Таблица2[[#This Row],[Конструкция]]=коэф_произв[Значение])*('Таблица объектов'!I$1=коэф_произв[Характеристика]),коэф_произв[Коэффициент],"",0)} -> 0.5 | K36: Усиленные для техники или специальные | L36: {=_xlfn.XLOOKUP(1,(Таблица2[[#This Row],[Тип]]=коэф_произв[Тип])*(Таблица2[[#This Row],[Полы]]=коэф_произв[Значение])*('Таблица объектов'!K$1=коэф_произв[Характеристика]),коэф_произв[Коэффициент],"",0)} -> 1 | M36: Отсутствует или минимальное (минимальная разводка освещения, водопровода) | N36: {=_xlfn.XLOOKUP(1,(Таблица2[[#This Row],[Тип]]=коэф_произв[Тип])*(Таблица2[[#This Row],[Инженерное оснащение]]=коэф_произв[Значение])*('Таблица объектов'!M$1=коэф_произв[Характеристика]),коэф_произв[Коэффициент],"",0)} -> 0.8 | P36: {=_xlfn.XLOOKUP(1,(Таблица2[[#This Row],[Тип]]=коэф_произв[Тип])*(Таблица2[[#This Row],[Архитектура]]=коэф_произв[Значение])*('Таблица объектов'!O$1=коэф_произв[Характеристика]),коэф_произв[Коэффициент],"",0)} | R36: {=_xlfn.XLOOKUP(1,(Таблица2[[#This Row],[Тип]]=коэф_произв[Тип])*(Таблица2[[#This Row],[Планировка]]=коэф_произв[Значение])*('Таблица объектов'!Q$1=коэф_произв[Характеристика]),коэф_произв[Коэффициент],"",0)} | T36: {=_xlfn.XLOOKUP(1,(Таблица2[[#This Row],[Тип]]=коэф_произв[Тип])*(Таблица2[[#This Row],[Уровень отделки]]=коэф_произв[Значение])*('Таблица объектов'!S$1=коэф_произв[Характеристика]),коэф_произв[Коэффициент],"",0)} | U36: =IF(Таблица2[[#This Row],[Тип]]="прочие",0.05,PRODUCT(Таблица2[[#This Row],[Уровень отделки коэф.]],Таблица2[[#This Row],[Планировка коэф.]],Таблица2[[#This Row],[Архитектура коэф.]],Таблица2[[#This Row],[Инженерное оснащение коэф.]],Таблица2[[#This Row],[Полы коэф.]],Таблица2[[#This Row],[Конструкция коэф.]],Таблица2[[#This Row],[Наличие / Возможность кран-балки коэф.]],Таблица2[[#This Row],[Высота коэф.]])) -> 0.216 | V36: =IF(Таблица2[[#This Row],[Тип]]="произв",IF(Таблица2[[#This Row],[Капитальность]]<0.33,"произв класс 4",IF(Таблица2[[#This Row],[Капитальность]]<0.55,"произв класс 3",IF(Таблица2[[#This Row],[Капитальность]]<0.77,"произв класс 2","произв класс 1"))),IF(Таблица2[[#This Row],[Тип]]="гражд",IF(Таблица2[[#This Row],[Капитальность]]<0.33,"гражд класс 4",IF(Таблица2[[#This Row],[Капитальность]]<0.55,"гражд класс 3",IF(Таблица2[[#This Row],[Капитальность]]<0.77,"гражд класс 2","гражд класс 1"))),"прочие")) -> произв класс 4 | W36: =Таблица2[[#This Row],[Площадь, м2]]*Таблица2[[#This Row],[Капитальность]] -> 29.9592 | X36: =IF(AB36<4%,5,IF(AB36<9%,4.5,IF(AB36<14%,4,IF(AB36<24%,3.5,IF(AB36<40%,3,IF(AB36<60%,2.5,IF(AB36<80%,2,1))))))) -> 4 | Y36: =X36*Таблица2[[#This Row],[Площадь, м2]] -> 554.8 | Z36: =Y36*Таблица2[[#This Row],[Капитальность]] -> 119.8368 | AB36: 0.1
A37: Объект оценки 4 | B37: 24.8 | C37: Навес | D37: прочие | F37: {=_xlfn.XLOOKUP(1,(Таблица2[[#This Row],[Тип]]=коэф_произв[Тип])*(Таблица2[[#This Row],[Высота]]=коэф_произв[Значение])*('Таблица объектов'!E$1=коэф_произв[Характеристика]),коэф_произв[Коэффициент],"",0)} | H37: {=_xlfn.XLOOKUP(1,(Таблица2[[#This Row],[Тип]]=коэф_произв[Тип])*(Таблица2[[#This Row],[Наличие / Возможность кран-балки]]=коэф_произв[Значение])*('Таблица объектов'!G$1=коэф_произв[Характеристика]),коэф_произв[Коэффициент],"",0)} | J37: {=_xlfn.XLOOKUP(1,(Таблица2[[#This Row],[Тип]]=коэф_произв[Тип])*(Таблица2[[#This Row],[Конструкция]]=коэф_произв[Значение])*('Таблица объектов'!I$1=коэф_произв[Характеристика]),коэф_произв[Коэффициент],"",0)} | L37: {=_xlfn.XLOOKUP(1,(Таблица2[[#This Row],[Тип]]=коэф_произв[Тип])*(Таблица2[[#This Row],[Полы]]=коэф_произв[Значение])*('Таблица объектов'!K$1=коэф_произв[Характеристика]),коэф_произв[Коэффициент],"",0)} | N37: {=_xlfn.XLOOKUP(1,(Таблица2[[#This Row],[Тип]]=коэф_произв[Тип])*(Таблица2[[#This Row],[Инженерное оснащение]]=коэф_произв[Значение])*('Таблица объектов'!M$1=коэф_произв[Характеристика]),коэф_произв[Коэффициент],"",0)} | P37: {=_xlfn.XLOOKUP(1,(Таблица2[[#This Row],[Тип]]=коэф_произв[Тип])*(Таблица2[[#This Row],[Архитектура]]=коэф_произв[Значение])*('Таблица объектов'!O$1=коэф_произв[Характеристика]),коэф_произв[Коэффициент],"",0)} | R37: {=_xlfn.XLOOKUP(1,(Таблица2[[#This Row],[Тип]]=коэф_произв[Тип])*(Таблица2[[#This Row],[Планировка]]=коэф_произв[Значение])*('Таблица объектов'!Q$1=коэф_произв[Характеристика]),коэф_произв[Коэффициент],"",0)} | T37: {=_xlfn.XLOOKUP(1,(Таблица2[[#This Row],[Тип]]=коэф_произв[Тип])*(Таблица2[[#This Row],[Уровень отделки]]=коэф_произв[Значение])*('Таблица объектов'!S$1=коэф_произв[Характеристика]),коэф_произв[Коэффициент],"",0)} | U37: =IF(Таблица2[[#This Row],[Тип]]="прочие",0.05,PRODUCT(Таблица2[[#This Row],[Уровень отделки коэф.]],Таблица2[[#This Row],[Планировка коэф.]],Таблица2[[#This Row],[Архитектура коэф.]],Таблица2[[#This Row],[Инженерное оснащение коэф.]],Таблица2[[#This Row],[Полы коэф.]],Таблица2[[#This Row],[Конструкция коэф.]],Таблица2[[#This Row],[Наличие / Возможность кран-балки коэф.]],Таблица2[[#This Row],[Высота коэф.]])) -> 0.05 | V37: =IF(Таблица2[[#This Row],[Тип]]="произв",IF(Таблица2[[#This Row],[Капитальность]]<0.33,"произв класс 4",IF(Таблица2[[#This Row],[Капитальность]]<0.55,"произв класс 3",IF(Таблица2[[#This Row],[Капитальность]]<0.77,"произв класс 2","произв класс 1"))),IF(Таблица2[[#This Row],[Тип]]="гражд",IF(Таблица2[[#This Row],[Капитальность]]<0.33,"гражд класс 4",IF(Таблица2[[#This Row],[Капитальность]]<0.55,"гражд класс 3",IF(Таблица2[[#This Row],[Капитальность]]<0.77,"гражд класс 2","гражд класс 1"))),"прочие")) -> прочие | W37: =Таблица2[[#This Row],[Площадь, м2]]*Таблица2[[#This Row],[Капитальность]] -> 1.24 | X37: =IF(AB37<4%,5,IF(AB37<9%,4.5,IF(AB37<14%,4,IF(AB37<24%,3.5,IF(AB37<40%,3,IF(AB37<60%,2.5,IF(AB37<80%,2,1))))))) -> 3.5 | Y37: =X37*Таблица2[[#This Row],[Площадь, м2]] -> 86.8 | Z37: =Y37*Таблица2[[#This Row],[Капитальность]] -> 4.34 | AB37: 0.2
A38: Объект оценки 4 | B38: 24.82 | C38: КПП | D38: гражд | E38: До 2,6 м. | F38: {=_xlfn.XLOOKUP(1,(Таблица2[[#This Row],[Тип]]=коэф_произв[Тип])*(Таблица2[[#This Row],[Высота]]=коэф_произв[Значение])*('Таблица объектов'!E$1=коэф_произв[Характеристика]),коэф_произв[Коэффициент],"",0)} -> 0.6 | H38: {=_xlfn.XLOOKUP(1,(Таблица2[[#This Row],[Тип]]=коэф_произв[Тип])*(Таблица2[[#This Row],[Наличие / Возможность кран-балки]]=коэф_произв[Значение])*('Таблица объектов'!G$1=коэф_произв[Характеристика]),коэф_произв[Коэффициент],"",0)} | I38: Некапитальная | J38: {=_xlfn.XLOOKUP(1,(Таблица2[[#This Row],[Тип]]=коэф_произв[Тип])*(Таблица2[[#This Row],[Конструкция]]=коэф_произв[Значение])*('Таблица объектов'!I$1=коэф_произв[Характеристика]),коэф_произв[Коэффициент],"",0)} -> 0.8 | L38: {=_xlfn.XLOOKUP(1,(Таблица2[[#This Row],[Тип]]=коэф_произв[Тип])*(Таблица2[[#This Row],[Полы]]=коэф_произв[Значение])*('Таблица объектов'!K$1=коэф_произв[Характеристика]),коэф_произв[Коэффициент],"",0)} | M38: Отсутствует или минимальное (минимальная разводка освещения, водопровода) | N38: {=_xlfn.XLOOKUP(1,(Таблица2[[#This Row],[Тип]]=коэф_произв[Тип])*(Таблица2[[#This Row],[Инженерное оснащение]]=коэф_произв[Значение])*('Таблица объектов'!M$1=коэф_произв[Характеристика]),коэф_произв[Коэффициент],"",0)} -> 0.8 | O38: Устаревшая/ Современная | P38: {=_xlfn.XLOOKUP(1,(Таблица2[[#This Row],[Тип]]=коэф_произв[Тип])*(Таблица2[[#This Row],[Архитектура]]=коэф_произв[Значение])*('Таблица объектов'!O$1=коэф_произв[Характеристика]),коэф_произв[Коэффициент],"",0)} -> 0.9 | Q38: Свободная | R38: {=_xlfn.XLOOKUP(1,(Таблица2[[#This Row],[Тип]]=коэф_произв[Тип])*(Таблица2[[#This Row],[Планировка]]=коэф_произв[Значение])*('Таблица объектов'!Q$1=коэф_произв[Характеристика]),коэф_произв[Коэффициент],"",0)} -> 0.9 | S38: Простая (потолки и стены оштукатурены, окрашены или отделаны дешевыми материалами (МДФ), полы линолеумные | T38: {=_xlfn.XLOOKUP(1,(Таблица2[[#This Row],[Тип]]=коэф_произв[Тип])*(Таблица2[[#This Row],[Уровень отделки]]=коэф_произв[Значение])*('Таблица объектов'!S$1=коэф_произв[Характеристика]),коэф_произв[Коэффициент],"",0)} -> 0.7 | U38: =IF(Таблица2[[#This Row],[Тип]]="прочие",0.05,PRODUCT(Таблица2[[#This Row],[Уровень отделки коэф.]],Таблица2[[#This Row],[Планировка коэф.]],Таблица2[[#This Row],[Архитектура коэф.]],Таблица2[[#This Row],[Инженерное оснащение коэф.]],Таблица2[[#This Row],[Полы коэф.]],Таблица2[[#This Row],[Конструкция коэф.]],Таблица2[[#This Row],[Наличие / Возможность кран-балки коэф.]],Таблица2[[#This Row],[Высота коэф.]])) -> 0.217728 | V38: =IF(Таблица2[[#This Row],[Тип]]="произв",IF(Таблица2[[#This Row],[Капитальность]]<0.33,"произв класс 4",IF(Таблица2[[#This Row],[Капитальность]]<0.55,"произв класс 3",IF(Таблица2[[#This Row],[Капитальность]]<0.77,"произв класс 2","произв класс 1"))),IF(Таблица2[[#This Row],[Тип]]="гражд",IF(Таблица2[[#This Row],[Капитальность]]<0.33,"гражд класс 4",IF(Таблица2[[#This Row],[Капитальность]]<0.55,"гражд класс 3",IF(Таблица2[[#This Row],[Капитальность]]<0.77,"гражд класс 2","гражд класс 1"))),"прочие")) -> гражд класс 4 | W38: =Таблица2[[#This Row],[Площадь, м2]]*Таблица2[[#This Row],[Капитальность]] -> 5.404009 | X38: =IF(AB38<4%,5,IF(AB38<9%,4.5,IF(AB38<14%,4,IF(AB38<24%,3.5,IF(AB38<40%,3,IF(AB38<60%,2.5,IF(AB38<80%,2,1))))))) -> 3.5 | Y38: =X38*Таблица2[[#This Row],[Площадь, м2]] -> 86.87 | Z38: =Y38*Таблица2[[#This Row],[Капитальность]] -> 18.914031 | AB38: 0.2
A39: Аналог 1 | B39: 2700 | C39: Нежилое помещение | D39: произв | E39: 3-5 м. | F39: {=_xlfn.XLOOKUP(1,(Таблица2[[#This Row],[Тип]]=коэф_произв[Тип])*(Таблица2[[#This Row],[Высота]]=коэф_произв[Значение])*('Таблица объектов'!E$1=коэф_произв[Характеристика]),коэф_произв[Коэффициент],"",0)} -> 0.6 | G39: Не установлено (по умолчанию) | H39: {=_xlfn.XLOOKUP(1,(Таблица2[[#This Row],[Тип]]=коэф_произв[Тип])*(Таблица2[[#This Row],[Наличие / Возможность кран-балки]]=коэф_произв[Значение])*('Таблица объектов'!G$1=коэф_произв[Характеристика]),коэф_произв[Коэффициент],"",0)} -> 0.95 | I39: Блочные по железобетонному каркасу, без утепления | J39: {=_xlfn.XLOOKUP(1,(Таблица2[[#This Row],[Тип]]=коэф_произв[Тип])*(Таблица2[[#This Row],[Конструкция]]=коэф_произв[Значение])*('Таблица объектов'!I$1=коэф_произв[Характеристика]),коэф_произв[Коэффициент],"",0)} -> 0.7 | K39: Простые | L39: {=_xlfn.XLOOKUP(1,(Таблица2[[#This Row],[Тип]]=коэф_произв[Тип])*(Таблица2[[#This Row],[Полы]]=коэф_произв[Значение])*('Таблица объектов'!K$1=коэф_произв[Характеристика]),коэф_произв[Коэффициент],"",0)} -> 0.9 | M39: Стандартное (по всем помещениям разводка освещения, водопровод, канализация) | N39: {=_xlfn.XLOOKUP(1,(Таблица2[[#This Row],[Тип]]=коэф_произв[Тип])*(Таблица2[[#This Row],[Инженерное оснащение]]=коэф_произв[Значение])*('Таблица объектов'!M$1=коэф_произв[Характеристика]),коэф_произв[Коэффициент],"",0)} -> 0.9 | P39: {=_xlfn.XLOOKUP(1,(Таблица2[[#This Row],[Тип]]=коэф_произв[Тип])*(Таблица2[[#This Row],[Архитектура]]=коэф_произв[Значение])*('Таблица объектов'!O$1=коэф_произв[Характеристика]),коэф_произв[Коэффициент],"",0)} | R39: {=_xlfn.XLOOKUP(1,(Таблица2[[#This Row],[Тип]]=коэф_произв[Тип])*(Таблица2[[#This Row],[Планировка]]=коэф_произв[Значение])*('Таблица объектов'!Q$1=коэф_произв[Характеристика]),коэф_произв[Коэффициент],"",0)} | T39: {=_xlfn.XLOOKUP(1,(Таблица2[[#This Row],[Тип]]=коэф_произв[Тип])*(Таблица2[[#This Row],[Уровень отделки]]=коэф_произв[Значение])*('Таблица объектов'!S$1=коэф_произв[Характеристика]),коэф_произв[Коэффициент],"",0)} | U39: =IF(Таблица2[[#This Row],[Тип]]="прочие",0.05,PRODUCT(Таблица2[[#This Row],[Уровень отделки коэф.]],Таблица2[[#This Row],[Планировка коэф.]],Таблица2[[#This Row],[Архитектура коэф.]],Таблица2[[#This Row],[Инженерное оснащение коэф.]],Таблица2[[#This Row],[Полы коэф.]],Таблица2[[#This Row],[Конструкция коэф.]],Таблица2[[#This Row],[Наличие / Возможность кран-балки коэф.]],Таблица2[[#This Row],[Высота коэф.]])) -> 0.32319 | V39: =IF(Таблица2[[#This Row],[Тип]]="произв",IF(Таблица2[[#This Row],[Капитальность]]<0.33,"произв класс 4",IF(Таблица2[[#This Row],[Капитальность]]<0.55,"произв класс 3",IF(Таблица2[[#This Row],[Капитальность]]<0.77,"произв класс 2","произв класс 1"))),IF(Таблица2[[#This Row],[Тип]]="гражд",IF(Таблица2[[#This Row],[Капитальность]]<0.33,"гражд класс 4",IF(Таблица2[[#This Row],[Капитальность]]<0.55,"гражд класс 3",IF(Таблица2[[#This Row],[Капитальность]]<0.77,"гражд класс 2","гражд класс 1"))),"прочие")) -> произв класс 4 | W39: =Таблица2[[#This Row],[Площадь, м2]]*Таблица2[[#This Row],[Капитальность]] -> 872.613 | Z39: =Y39*Таблица2[[#This Row],[Капитальность]] -> 0
A40: Аналог 2 | B40: 360 | C40: АБК | D40: гражд | E40: 3,2-4 м. | F40: {=_xlfn.XLOOKUP(1,(Таблица2[[#This Row],[Тип]]=коэф_произв[Тип])*(Таблица2[[#This Row],[Высота]]=коэф_произв[Значение])*('Таблица объектов'!E$1=коэф_произв[Характеристика]),коэф_произв[Коэффициент],"",0)} -> 0.8 | H40: {=_xlfn.XLOOKUP(1,(Таблица2[[#This Row],[Тип]]=коэф_произв[Тип])*(Таблица2[[#This Row],[Наличие / Возможность кран-балки]]=коэф_произв[Значение])*('Таблица объектов'!G$1=коэф_произв[Характеристика]),коэф_произв[Коэффициент],"",0)} | I40: Капитальная | J40: {=_xlfn.XLOOKUP(1,(Таблица2[[#This Row],[Тип]]=коэф_произв[Тип])*(Таблица2[[#This Row],[Конструкция]]=коэф_произв[Значение])*('Таблица объектов'!I$1=коэф_произв[Характеристика]),коэф_произв[Коэффициент],"",0)} -> 1 | L40: {=_xlfn.XLOOKUP(1,(Таблица2[[#This Row],[Тип]]=коэф_произв[Тип])*(Таблица2[[#This Row],[Полы]]=коэф_произв[Значение])*('Таблица объектов'!K$1=коэф_произв[Характеристика]),коэф_произв[Коэффициент],"",0)} | M40: Стандартное (по всем помещениям разводка освещения, водопровод, канализация) | N40: {=_xlfn.XLOOKUP(1,(Таблица2[[#This Row],[Тип]]=коэф_произв[Тип])*(Таблица2[[#This Row],[Инженерное оснащение]]=коэф_произв[Значение])*('Таблица объектов'!M$1=коэф_произв[Характеристика]),коэф_произв[Коэффициент],"",0)} -> 0.9 | O40: Устаревшая/ Современная | P40: {=_xlfn.XLOOKUP(1,(Таблица2[[#This Row],[Тип]]=коэф_произв[Тип])*(Таблица2[[#This Row],[Архитектура]]=коэф_произв[Значение])*('Таблица объектов'!O$1=коэф_произв[Характеристика]),коэф_произв[Коэффициент],"",0)} -> 0.9 | Q40: Смешанная | R40: {=_xlfn.XLOOKUP(1,(Таблица2[[#This Row],[Тип]]=коэф_произв[Тип])*(Таблица2[[#This Row],[Планировка]]=коэф_произв[Значение])*('Таблица объектов'!Q$1=коэф_произв[Характеристика]),коэф_произв[Коэффициент],"",0)} -> 0.95 | S40: Простая (потолки и стены оштукатурены, окрашены или отделаны дешевыми материалами (МДФ), полы линолеумные | T40: {=_xlfn.XLOOKUP(1,(Таблица2[[#This Row],[Тип]]=коэф_произв[Тип])*(Таблица2[[#This Row],[Уровень отделки]]=коэф_произв[Значение])*('Таблица объектов'!S$1=коэф_произв[Характеристика]),коэф_произв[Коэффициент],"",0)} -> 0.7 | U40: =IF(Таблица2[[#This Row],[Тип]]="прочие",0.05,PRODUCT(Таблица2[[#This Row],[Уровень отделки коэф.]],Таблица2[[#This Row],[Планировка коэф.]],Таблица2[[#This Row],[Архитектура коэф.]],Таблица2[[#This Row],[Инженерное оснащение коэф.]],Таблица2[[#This Row],[Полы коэф.]],Таблица2[[#This Row],[Конструкция коэф.]],Таблица2[[#This Row],[Наличие / Возможность кран-балки коэф.]],Таблица2[[#This Row],[Высота коэф.]])) -> 0.43092 | V40: =IF(Таблица2[[#This Row],[Тип]]="произв",IF(Таблица2[[#This Row],[Капитальность]]<0.33,"произв класс 4",IF(Таблица2[[#This Row],[Капитальность]]<0.55,"произв класс 3",IF(Таблица2[[#This Row],[Капитальность]]<0.77,"произв класс 2","произв класс 1"))),IF(Таблица2[[#This Row],[Тип]]="гражд",IF(Таблица2[[#This Row],[Капитальность]]<0.33,"гражд класс 4",IF(Таблица2[[#This Row],[Капитальность]]<0.55,"гражд класс 3",IF(Таблица2[[#This Row],[Капитальность]]<0.77,"гражд класс 2","гражд класс 1"))),"прочие")) -> гражд класс 3 | W40: =Таблица2[[#This Row],[Площадь, м2]]*Таблица2[[#This Row],[Капитальность]] -> 155.1312 | Z40: =Y40*Таблица2[[#This Row],[Капитальность]] -> 0
A41: Аналог 2 | B41: 5523.8 | C41: Производственное помещение | D41: произв | E41: 5-8 м. | F41: {=_xlfn.XLOOKUP(1,(Таблица2[[#This Row],[Тип]]=коэф_произв[Тип])*(Таблица2[[#This Row],[Высота]]=коэф_произв[Значение])*('Таблица объектов'!E$1=коэф_произв[Характеристика]),коэф_произв[Коэффициент],"",0)} -> 0.8 | G41: Да | H41: {=_xlfn.XLOOKUP(1,(Таблица2[[#This Row],[Тип]]=коэф_произв[Тип])*(Таблица2[[#This Row],[Наличие / Возможность кран-балки]]=коэф_произв[Значение])*('Таблица объектов'!G$1=коэф_произв[Характеристика]),коэф_произв[Коэффициент],"",0)} -> 1 | I41: Блочные по железобетонному каркасу, без утепления | J41: {=_xlfn.XLOOKUP(1,(Таблица2[[#This Row],[Тип]]=коэф_произв[Тип])*(Таблица2[[#This Row],[Конструкция]]=коэф_произв[Значение])*('Таблица объектов'!I$1=коэф_произв[Характеристика]),коэф_произв[Коэффициент],"",0)} -> 0.7 | K41: Простые | L41: {=_xlfn.XLOOKUP(1,(Таблица2[[#This Row],[Тип]]=коэф_произв[Тип])*(Таблица2[[#This Row],[Полы]]=коэф_произв[Значение])*('Таблица объектов'!K$1=коэф_произв[Характеристика]),коэф_произв[Коэффициент],"",0)} -> 0.9 | M41: Отсутствует или минимальное (минимальная разводка освещения, водопровода) | N41: {=_xlfn.XLOOKUP(1,(Таблица2[[#This Row],[Тип]]=коэф_произв[Тип])*(Таблица2[[#This Row],[Инженерное оснащение]]=коэф_произв[Значение])*('Таблица объектов'!M$1=коэф_произв[Характеристика]),коэф_произв[Коэффициент],"",0)} -> 0.8 | P41: {=_xlfn.XLOOKUP(1,(Таблица2[[#This Row],[Тип]]=коэф_произв[Тип])*(Таблица2[[#This Row],[Архитектура]]=коэф_произв[Значение])*('Таблица объектов'!O$1=коэф_произв[Характеристика]),коэф_произв[Коэффициент],"",0)} | R41: {=_xlfn.XLOOKUP(1,(Таблица2[[#This Row],[Тип]]=коэф_произв[Тип])*(Таблица2[[#This Row],[Планировка]]=коэф_произв[Значение])*('Таблица объектов'!Q$1=коэф_произв[Характеристика]),коэф_произв[Коэффициент],"",0)} | T41: {=_xlfn.XLOOKUP(1,(Таблица2[[#This Row],[Тип]]=коэф_произв[Тип])*(Таблица2[[#This Row],[Уровень отделки]]=коэф_произв[Значение])*('Таблица объектов'!S$1=коэф_произв[Характеристика]),коэф_произв[Коэффициент],"",0)} | U41: =IF(Таблица2[[#This Row],[Тип]]="прочие",0.05,PRODUCT(Таблица2[[#This Row],[Уровень отделки коэф.]],Таблица2[[#This Row],[Планировка коэф.]],Таблица2[[#This Row],[Архитектура коэф.]],Таблица2[[#This Row],[Инженерное оснащение коэф.]],Таблица2[[#This Row],[Полы коэф.]],Таблица2[[#This Row],[Конструкция коэф.]],Таблица2[[#This Row],[Наличие / Возможность кран-балки коэф.]],Таблица2[[#This Row],[Высота коэф.]])) -> 0.4032 | V41: =IF(Таблица2[[#This Row],[Тип]]="произв",IF(Таблица2[[#This Row],[Капитальность]]<0.33,"произв класс 4",IF(Таблица2[[#This Row],[Капитальность]]<0.55,"произв класс 3",IF(Таблица2[[#This Row],[Капитальность]]<0.77,"произв класс 2","произв класс 1"))),IF(Таблица2[[#This Row],[Тип]]="гражд",IF(Таблица2[[#This Row],[Капитальность]]<0.33,"гражд класс 4",IF(Таблица2[[#This Row],[Капитальность]]<0.55,"гражд класс 3",IF(Таблица2[[#This Row],[Капитальность]]<0.77,"гражд класс 2","гражд класс 1"))),"прочие")) -> произв класс 3 | W41: =Таблица2[[#This Row],[Площадь, м2]]*Таблица2[[#This Row],[Капитальность]] -> 2227.1962 | Z41: =Y41*Таблица2[[#This Row],[Капитальность]] -> 0
A42: Аналог 2 | B42: 1112.2 | C42: Производственное помещение | D42: произв | E42: 3-5 м. | F42: {=_xlfn.XLOOKUP(1,(Таблица2[[#This Row],[Тип]]=коэф_произв[Тип])*(Таблица2[[#This Row],[Высота]]=коэф_произв[Значение])*('Таблица объектов'!E$1=коэф_произв[Характеристика]),коэф_произв[Коэффициент],"",0)} -> 0.6 | G42: Не установлено (по умолчанию) | H42: {=_xlfn.XLOOKUP(1,(Таблица2[[#This Row],[Тип]]=коэф_произв[Тип])*(Таблица2[[#This Row],[Наличие / Возможность кран-балки]]=коэф_произв[Значение])*('Таблица объектов'!G$1=коэф_произв[Характеристика]),коэф_произв[Коэффициент],"",0)} -> 0.95 | I42: Блочные по железобетонному каркасу, без утепления | J42: {=_xlfn.XLOOKUP(1,(Таблица2[[#This Row],[Тип]]=коэф_произв[Тип])*(Таблица2[[#This Row],[Конструкция]]=коэф_произв[Значение])*('Таблица объектов'!I$1=коэф_произв[Характеристика]),коэф_произв[Коэффициент],"",0)} -> 0.7 | K42: Простые | L42: {=_xlfn.XLOOKUP(1,(Таблица2[[#This Row],[Тип]]=коэф_произв[Тип])*(Таблица2[[#This Row],[Полы]]=коэф_произв[Значение])*('Таблица объектов'!K$1=коэф_произв[Характеристика]),коэф_произв[Коэффициент],"",0)} -> 0.9 | M42: Отсутствует или минимальное (минимальная разводка освещения, водопровода) | N42: {=_xlfn.XLOOKUP(1,(Таблица2[[#This Row],[Тип]]=коэф_произв[Тип])*(Таблица2[[#This Row],[Инженерное оснащение]]=коэф_произв[Значение])*('Таблица объектов'!M$1=коэф_произв[Характеристика]),коэф_произв[Коэффициент],"",0)} -> 0.8 | P42: {=_xlfn.XLOOKUP(1,(Таблица2[[#This Row],[Тип]]=коэф_произв[Тип])*(Таблица2[[#This Row],[Архитектура]]=коэф_произв[Значение])*('Таблица объектов'!O$1=коэф_произв[Характеристика]),коэф_произв[Коэффициент],"",0)} | R42: {=_xlfn.XLOOKUP(1,(Таблица2[[#This Row],[Тип]]=коэф_произв[Тип])*(Таблица2[[#This Row],[Планировка]]=коэф_произв[Значение])*('Таблица объектов'!Q$1=коэф_произв[Характеристика]),коэф_произв[Коэффициент],"",0)} | T42: {=_xlfn.XLOOKUP(1,(Таблица2[[#This Row],[Тип]]=коэф_произв[Тип])*(Таблица2[[#This Row],[Уровень отделки]]=коэф_произв[Значение])*('Таблица объектов'!S$1=коэф_произв[Характеристика]),коэф_произв[Коэффициент],"",0)} | U42: =IF(Таблица2[[#This Row],[Тип]]="прочие",0.05,PRODUCT(Таблица2[[#This Row],[Уровень отделки коэф.]],Таблица2[[#This Row],[Планировка коэф.]],Таблица2[[#This Row],[Архитектура коэф.]],Таблица2[[#This Row],[Инженерное оснащение коэф.]],Таблица2[[#This Row],[Полы коэф.]],Таблица2[[#This Row],[Конструкция коэф.]],Таблица2[[#This Row],[Наличие / Возможность кран-балки коэф.]],Таблица2[[#This Row],[Высота коэф.]])) -> 0.28728 | V42: =IF(Таблица2[[#This Row],[Тип]]="произв",IF(Таблица2[[#This Row],[Капитальность]]<0.33,"произв класс 4",IF(Таблица2[[#This Row],[Капитальность]]<0.55,"произв класс 3",IF(Таблица2[[#This Row],[Капитальность]]<0.77,"произв класс 2","произв класс 1"))),IF(Таблица2[[#This Row],[Тип]]="гражд",IF(Таблица2[[#This Row],[Капитальность]]<0.33,"гражд класс 4",IF(Таблица2[[#This Row],[Капитальность]]<0.55,"гражд класс 3",IF(Таблица2[[#This Row],[Капитальность]]<0.77,"гражд класс 2","гражд класс 1"))),"прочие")) -> произв класс 4 | W42: =Таблица2[[#This Row],[Площадь, м2]]*Таблица2[[#This Row],[Капитальность]] -> 319.51282 | Z42: =Y42*Таблица2[[#This Row],[Капитальность]] -> 0
A43: Аналог 3 | B43: 1390 | C43: АБК | D43: гражд | E43: 3,2-4 м. | F43: {=_xlfn.XLOOKUP(1,(Таблица2[[#This Row],[Тип]]=коэф_произв[Тип])*(Таблица2[[#This Row],[Высота]]=коэф_произв[Значение])*('Таблица объектов'!E$1=коэф_произв[Характеристика]),коэф_произв[Коэффициент],"",0)} -> 0.8 | H43: {=_xlfn.XLOOKUP(1,(Таблица2[[#This Row],[Тип]]=коэф_произв[Тип])*(Таблица2[[#This Row],[Наличие / Возможность кран-балки]]=коэф_произв[Значение])*('Таблица объектов'!G$1=коэф_произв[Характеристика]),коэф_произв[Коэффициент],"",0)} | I43: Капитальная | J43: {=_xlfn.XLOOKUP(1,(Таблица2[[#This Row],[Тип]]=коэф_произв[Тип])*(Таблица2[[#This Row],[Конструкция]]=коэф_произв[Значение])*('Таблица объектов'!I$1=коэф_произв[Характеристика]),коэф_произв[Коэффициент],"",0)} -> 1 | L43: {=_xlfn.XLOOKUP(1,(Таблица2[[#This Row],[Тип]]=коэф_произв[Тип])*(Таблица2[[#This Row],[Полы]]=коэф_произв[Значение])*('Таблица объектов'!K$1=коэф_произв[Характеристика]),коэф_произв[Коэффициент],"",0)} | M43: Стандартное (по всем помещениям разводка освещения, водопровод, канализация) | N43: {=_xlfn.XLOOKUP(1,(Таблица2[[#This Row],[Тип]]=коэф_произв[Тип])*(Таблица2[[#This Row],[Инженерное оснащение]]=коэф_произв[Значение])*('Таблица объектов'!M$1=коэф_произв[Характеристика]),коэф_произв[Коэффициент],"",0)} -> 0.9 | O43: Устаревшая | P43: {=_xlfn.XLOOKUP(1,(Таблица2[[#This Row],[Тип]]=коэф_произв[Тип])*(Таблица2[[#This Row],[Архитектура]]=коэф_произв[Значение])*('Таблица объектов'!O$1=коэф_произв[Характеристика]),коэф_произв[Коэффициент],"",0)} -> 0.8 | Q43: Смешанная | R43: {=_xlfn.XLOOKUP(1,(Таблица2[[#This Row],[Тип]]=коэф_произв[Тип])*(Таблица2[[#This Row],[Планировка]]=коэф_произв[Значение])*('Таблица объектов'!Q$1=коэф_произв[Характеристика]),коэф_произв[Коэффициент],"",0)} -> 0.95 | S43: Простая (потолки и стены оштукатурены, окрашены или отделаны дешевыми материалами (МДФ), полы линолеумные | T43: {=_xlfn.XLOOKUP(1,(Таблица2[[#This Row],[Тип]]=коэф_произв[Тип])*(Таблица2[[#This Row],[Уровень отделки]]=коэф_произв[Значение])*('Таблица объектов'!S$1=коэф_произв[Характеристика]),коэф_произв[Коэффициент],"",0)} -> 0.7 | U43: =IF(Таблица2[[#This Row],[Тип]]="прочие",0.05,PRODUCT(Таблица2[[#This Row],[Уровень отделки коэф.]],Таблица2[[#This Row],[Планировка коэф.]],Таблица2[[#This Row],[Архитектура коэф.]],Таблица2[[#This Row],[Инженерное оснащение коэф.]],Таблица2[[#This Row],[Полы коэф.]],Таблица2[[#This Row],[Конструкция коэф.]],Таблица2[[#This Row],[Наличие / Возможность кран-балки коэф.]],Таблица2[[#This Row],[Высота коэф.]])) -> 0.38304 | V43: =IF(Таблица2[[#This Row],[Тип]]="произв",IF(Таблица2[[#This Row],[Капитальность]]<0.33,"произв класс 4",IF(Таблица2[[#This Row],[Капитальность]]<0.55,"произв класс 3",IF(Таблица2[[#This Row],[Капитальность]]<0.77,"произв класс 2","произв класс 1"))),IF(Таблица2[[#This Row],[Тип]]="гражд",IF(Таблица2[[#This Row],[Капитальность]]<0.33,"гражд класс 4",IF(Таблица2[[#This Row],[Капитальность]]<0.55,"гражд класс 3",IF(Таблица2[[#This Row],[Капитальность]]<0.77,"гражд класс 2","гражд класс 1"))),"прочие")) -> гражд класс 3 | W43: =Таблица2[[#This Row],[Площадь, м2]]*Таблица2[[#This Row],[Капитальность]] -> 532.4256 | Z43: =Y43*Таблица2[[#This Row],[Капитальность]] -> 0
A44: Аналог 3 | B44: 1947.1 | C44: Производственное помещение | D44: произв | E44: 5-8 м. | F44: {=_xlfn.XLOOKUP(1,(Таблица2[[#This Row],[Тип]]=коэф_произв[Тип])*(Таблица2[[#This Row],[Высота]]=коэф_произв[Значение])*('Таблица объектов'!E$1=коэф_произв[Характеристика]),коэф_произв[Коэффициент],"",0)} -> 0.8 | G44: Да | H44: {=_xlfn.XLOOKUP(1,(Таблица2[[#This Row],[Тип]]=коэф_произв[Тип])*(Таблица2[[#This Row],[Наличие / Возможность кран-балки]]=коэф_произв[Значение])*('Таблица объектов'!G$1=коэф_произв[Характеристика]),коэф_произв[Коэффициент],"",0)} -> 1 | I44: Блочные по железобетонному каркасу, утепленные | J44: {=_xlfn.XLOOKUP(1,(Таблица2[[#This Row],[Тип]]=коэф_произв[Тип])*(Таблица2[[#This Row],[Конструкция]]=коэф_произв[Значение])*('Таблица объектов'!I$1=коэф_произв[Характеристика]),коэф_произв[Коэффициент],"",0)} -> 1 | K44: Простые | L44: {=_xlfn.XLOOKUP(1,(Таблица2[[#This Row],[Тип]]=коэф_произв[Тип])*(Таблица2[[#This Row],[Полы]]=коэф_произв[Значение])*('Таблица объектов'!K$1=коэф_произв[Характеристика]),коэф_произв[Коэффициент],"",0)} -> 0.9 | M44: Отсутствует или минимальное (минимальная разводка освещения, водопровода) | N44: {=_xlfn.XLOOKUP(1,(Таблица2[[#This Row],[Тип]]=коэф_произв[Тип])*(Таблица2[[#This Row],[Инженерное оснащение]]=коэф_произв[Значение])*('Таблица объектов'!M$1=коэф_произв[Характеристика]),коэф_произв[Коэффициент],"",0)} -> 0.8 | P44: {=_xlfn.XLOOKUP(1,(Таблица2[[#This Row],[Тип]]=коэф_произв[Тип])*(Таблица2[[#This Row],[Архитектура]]=коэф_произв[Значение])*('Таблица объектов'!O$1=коэф_произв[Характеристика]),коэф_произв[Коэффициент],"",0)} | R44: {=_xlfn.XLOOKUP(1,(Таблица2[[#This Row],[Тип]]=коэф_произв[Тип])*(Таблица2[[#This Row],[Планировка]]=коэф_произв[Значение])*('Таблица объектов'!Q$1=коэф_произв[Характеристика]),коэф_произв[Коэффициент],"",0)} | T44: {=_xlfn.XLOOKUP(1,(Таблица2[[#This Row],[Тип]]=коэф_произв[Тип])*(Таблица2[[#This Row],[Уровень отделки]]=коэф_произв[Значение])*('Таблица объектов'!S$1=коэф_произв[Характеристика]),коэф_произв[Коэффициент],"",0)} | U44: =IF(Таблица2[[#This Row],[Тип]]="прочие",0.05,PRODUCT(Таблица2[[#This Row],[Уровень отделки коэф.]],Таблица2[[#This Row],[Планировка коэф.]],Таблица2[[#This Row],[Архитектура коэф.]],Таблица2[[#This Row],[Инженерное оснащение коэф.]],Таблица2[[#This Row],[Полы коэф.]],Таблица2[[#This Row],[Конструкция коэф.]],Таблица2[[#This Row],[Наличие / Возможность кран-балки коэф.]],Таблица2[[#This Row],[Высота коэф.]])) -> 0.576 | V44: =IF(Таблица2[[#This Row],[Тип]]="произв",IF(Таблица2[[#This Row],[Капитальность]]<0.33,"произв класс 4",IF(Таблица2[[#This Row],[Капитальность]]<0.55,"произв класс 3",IF(Таблица2[[#This Row],[Капитальность]]<0.77,"произв класс 2","произв класс 1"))),IF(Таблица2[[#This Row],[Тип]]="гражд",IF(Таблица2[[#This Row],[Капитальность]]<0.33,"гражд класс 4",IF(Таблица2[[#This Row],[Капитальность]]<0.55,"гражд класс 3",IF(Таблица2[[#This Row],[Капитальность]]<0.77,"гражд класс 2","гражд класс 1"))),"прочие")) -> произв класс 2 | W44: =Таблица2[[#This Row],[Площадь, м2]]*Таблица2[[#This Row],[Капитальность]] -> 1121.5296 | Z44: =Y44*Таблица2[[#This Row],[Капитальность]] -> 0
A45: Аналог 4 | B45: 877.7 | C45: АБК | D45: гражд | E45: 3,2-4 м. | F45: {=_xlfn.XLOOKUP(1,(Таблица2[[#This Row],[Тип]]=коэф_произв[Тип])*(Таблица2[[#This Row],[Высота]]=коэф_произв[Значение])*('Таблица объектов'!E$1=коэф_произв[Характеристика]),коэф_произв[Коэффициент],"",0)} -> 0.8 | H45: {=_xlfn.XLOOKUP(1,(Таблица2[[#This Row],[Тип]]=коэф_произв[Тип])*(Таблица2[[#This Row],[Наличие / Возможность кран-балки]]=коэф_произв[Значение])*('Таблица объектов'!G$1=коэф_произв[Характеристика]),коэф_произв[Коэффициент],"",0)} | I45: Смешанная | J45: {=_xlfn.XLOOKUP(1,(Таблица2[[#This Row],[Тип]]=коэф_произв[Тип])*(Таблица2[[#This Row],[Конструкция]]=коэф_произв[Значение])*('Таблица объектов'!I$1=коэф_произв[Характеристика]),коэф_произв[Коэффициент],"",0)} -> 0.9 | L45: {=_xlfn.XLOOKUP(1,(Таблица2[[#This Row],[Тип]]=коэф_произв[Тип])*(Таблица2[[#This Row],[Полы]]=коэф_произв[Значение])*('Таблица объектов'!K$1=коэф_произв[Характеристика]),коэф_произв[Коэффициент],"",0)} | M45: Стандартное (по всем помещениям разводка освещения, водопровод, канализация) | N45: {=_xlfn.XLOOKUP(1,(Таблица2[[#This Row],[Тип]]=коэф_произв[Тип])*(Таблица2[[#This Row],[Инженерное оснащение]]=коэф_произв[Значение])*('Таблица объектов'!M$1=коэф_произв[Характеристика]),коэф_произв[Коэффициент],"",0)} -> 0.9 | P45: {=_xlfn.XLOOKUP(1,(Таблица2[[#This Row],[Тип]]=коэф_произв[Тип])*(Таблица2[[#This Row],[Архитектура]]=коэф_произв[Значение])*('Таблица объектов'!O$1=коэф_произв[Характеристика]),коэф_произв[Коэффициент],"",0)} | Q45: Смешанная | R45: {=_xlfn.XLOOKUP(1,(Таблица2[[#This Row],[Тип]]=коэф_произв[Тип])*(Таблица2[[#This Row],[Планировка]]=коэф_произв[Значение])*('Таблица объектов'!Q$1=коэф_произв[Характеристика]),коэф_произв[Коэффициент],"",0)} -> 0.95 | S45: Простая (потолки и стены оштукатурены, окрашены или отделаны дешевыми материалами (МДФ), полы линолеумные | T45: {=_xlfn.XLOOKUP(1,(Таблица2[[#This Row],[Тип]]=коэф_произв[Тип])*(Таблица2[[#This Row],[Уровень отделки]]=коэф_произв[Значение])*('Таблица объектов'!S$1=коэф_произв[Характеристика]),коэф_произв[Коэффициент],"",0)} -> 0.7 | U45: =IF(Таблица2[[#This Row],[Тип]]="прочие",0.05,PRODUCT(Таблица2[[#This Row],[Уровень отделки коэф.]],Таблица2[[#This Row],[Планировка коэф.]],Таблица2[[#This Row],[Архитектура коэф.]],Таблица2[[#This Row],[Инженерное оснащение коэф.]],Таблица2[[#This Row],[Полы коэф.]],Таблица2[[#This Row],[Конструкция коэф.]],Таблица2[[#This Row],[Наличие / Возможность кран-балки коэф.]],Таблица2[[#This Row],[Высота коэф.]])) -> 0.43092 | V45: =IF(Таблица2[[#This Row],[Тип]]="произв",IF(Таблица2[[#This Row],[Капитальность]]<0.33,"произв класс 4",IF(Таблица2[[#This Row],[Капитальность]]<0.55,"произв класс 3",IF(Таблица2[[#This Row],[Капитальность]]<0.77,"произв класс 2","произв класс 1"))),IF(Таблица2[[#This Row],[Тип]]="гражд",IF(Таблица2[[#This Row],[Капитальность]]<0.33,"гражд класс 4",IF(Таблица2[[#This Row],[Капитальность]]<0.55,"гражд класс 3",IF(Таблица2[[#This Row],[Капитальность]]<0.77,"гражд класс 2","гражд класс 1"))),"прочие")) -> гражд класс 3 | W45: =Таблица2[[#This Row],[Площадь, м2]]*Таблица2[[#This Row],[Капитальность]] -> 378.21848 | Z45: =Y45*Таблица2[[#This Row],[Капитальность]] -> 0
A46: Аналог 4 | B46: 4822.3 | C46: Нежилое помещение | D46: произв | E46: 5-8 м. | F46: {=_xlfn.XLOOKUP(1,(Таблица2[[#This Row],[Тип]]=коэф_произв[Тип])*(Таблица2[[#This Row],[Высота]]=коэф_произв[Значение])*('Таблица объектов'!E$1=коэф_произв[Характеристика]),коэф_произв[Коэффициент],"",0)} -> 0.8 | G46: Нет | H46: {=_xlfn.XLOOKUP(1,(Таблица2[[#This Row],[Тип]]=коэф_произв[Тип])*(Таблица2[[#This Row],[Наличие / Возможность кран-балки]]=коэф_произв[Значение])*('Таблица объектов'!G$1=коэф_произв[Характеристика]),коэф_произв[Коэффициент],"",0)} -> 0.9 | I46: Блочные бескаркасные или металлокаркасные холодные | J46: {=_xlfn.XLOOKUP(1,(Таблица2[[#This Row],[Тип]]=коэф_произв[Тип])*(Таблица2[[#This Row],[Конструкция]]=коэф_произв[Значение])*('Таблица объектов'!I$1=коэф_произв[Характеристика]),коэф_произв[Коэффициент],"",0)} -> 0.5 | K46: Простые | L46: {=_xlfn.XLOOKUP(1,(Таблица2[[#This Row],[Тип]]=коэф_произв[Тип])*(Таблица2[[#This Row],[Полы]]=коэф_произв[Значение])*('Таблица объектов'!K$1=коэф_произв[Характеристика]),коэф_произв[Коэффициент],"",0)} -> 0.9 | M46: Отсутствует или минимальное (минимальная разводка освещения, водопровода) | N46: {=_xlfn.XLOOKUP(1,(Таблица2[[#This Row],[Тип]]=коэф_произв[Тип])*(Таблица2[[#This Row],[Инженерное оснащение]]=коэф_произв[Значение])*('Таблица объектов'!M$1=коэф_произв[Характеристика]),коэф_произв[Коэффициент],"",0)} -> 0.8 | P46: {=_xlfn.XLOOKUP(1,(Таблица2[[#This Row],[Тип]]=коэф_произв[Тип])*(Таблица2[[#This Row],[Архитектура]]=коэф_произв[Значение])*('Таблица объектов'!O$1=коэф_произв[Характеристика]),коэф_произв[Коэффициент],"",0)} | R46: {=_xlfn.XLOOKUP(1,(Таблица2[[#This Row],[Тип]]=коэф_произв[Тип])*(Таблица2[[#This Row],[Планировка]]=коэф_произв[Значение])*('Таблица объектов'!Q$1=коэф_произв[Характеристика]),коэф_произв[Коэффициент],"",0)} | T46: {=_xlfn.XLOOKUP(1,(Таблица2[[#This Row],[Тип]]=коэф_произв[Тип])*(Таблица2[[#This Row],[Уровень отделки]]=коэф_произв[Значение])*('Таблица объектов'!S$1=коэф_произв[Характеристика]),коэф_произв[Коэффициент],"",0)} | U46: =IF(Таблица2[[#This Row],[Тип]]="прочие",0.05,PRODUCT(Таблица2[[#This Row],[Уровень отделки коэф.]],Таблица2[[#This Row],[Планировка коэф.]],Таблица2[[#This Row],[Архитектура коэф.]],Таблица2[[#This Row],[Инженерное оснащение коэф.]],Таблица2[[#This Row],[Полы коэф.]],Таблица2[[#This Row],[Конструкция коэф.]],Таблица2[[#This Row],[Наличие / Возможность кран-балки коэф.]],Таблица2[[#This Row],[Высота коэф.]])) -> 0.2592 | V46: =IF(Таблица2[[#This Row],[Тип]]="произв",IF(Таблица2[[#This Row],[Капитальность]]<0.33,"произв класс 4",IF(Таблица2[[#This Row],[Капитальность]]<0.55,"произв класс 3",IF(Таблица2[[#This Row],[Капитальность]]<0.77,"произв класс 2","произв класс 1"))),IF(Таблица2[[#This Row],[Тип]]="гражд",IF(Таблица2[[#This Row],[Капитальность]]<0.33,"гражд класс 4",IF(Таблица2[[#This Row],[Капитальность]]<0.55,"гражд класс 3",IF(Таблица2[[#This Row],[Капитальность]]<0.77,"гражд класс 2","гражд класс 1"))),"прочие")) -> произв класс 4 | W46: =Таблица2[[#This Row],[Площадь, м2]]*Таблица2[[#This Row],[Капитальность]] -> 1249.9402 | Z46: =Y46*Таблица2[[#This Row],[Капитальность]] -> 0
A47: Аналог 5 | B47: 74.8 | C47: АБК | D47: гражд | E47: До 2,6 м. | F47: {=_xlfn.XLOOKUP(1,(Таблица2[[#This Row],[Тип]]=коэф_произв[Тип])*(Таблица2[[#This Row],[Высота]]=коэф_произв[Значение])*('Таблица объектов'!E$1=коэф_произв[Характеристика]),коэф_произв[Коэффициент],"",0)} -> 0.6 | H47: {=_xlfn.XLOOKUP(1,(Таблица2[[#This Row],[Тип]]=коэф_произв[Тип])*(Таблица2[[#This Row],[Наличие / Возможность кран-балки]]=коэф_произв[Значение])*('Таблица объектов'!G$1=коэф_произв[Характеристика]),коэф_произв[Коэффициент],"",0)} | I47: Капитальная | J47: {=_xlfn.XLOOKUP(1,(Таблица2[[#This Row],[Тип]]=коэф_произв[Тип])*(Таблица2[[#This Row],[Конструкция]]=коэф_произв[Значение])*('Таблица объектов'!I$1=коэф_произв[Характеристика]),коэф_произв[Коэффициент],"",0)} -> 1 | L47: {=_xlfn.XLOOKUP(1,(Таблица2[[#This Row],[Тип]]=коэф_произв[Тип])*(Таблица2[[#This Row],[Полы]]=коэф_произв[Значение])*('Таблица объектов'!K$1=коэф_произв[Характеристика]),коэф_произв[Коэффициент],"",0)} | M47: Стандартное (по всем помещениям разводка освещения, водопровод, канализация) | N47: {=_xlfn.XLOOKUP(1,(Таблица2[[#This Row],[Тип]]=коэф_произв[Тип])*(Таблица2[[#This Row],[Инженерное оснащение]]=коэф_произв[Значение])*('Таблица объектов'!M$1=коэф_произв[Характеристика]),коэф_произв[Коэффициент],"",0)} -> 0.9 | O47: Современная | P47: {=_xlfn.XLOOKUP(1,(Таблица2[[#This Row],[Тип]]=коэф_произв[Тип])*(Таблица2[[#This Row],[Архитектура]]=коэф_произв[Значение])*('Таблица объектов'!O$1=коэф_произв[Характеристика]),коэф_произв[Коэффициент],"",0)} -> 1 | Q47: Смешанная | R47: {=_xlfn.XLOOKUP(1,(Таблица2[[#This Row],[Тип]]=коэф_произв[Тип])*(Таблица2[[#This Row],[Планировка]]=коэф_произв[Значение])*('Таблица объектов'!Q$1=коэф_произв[Характеристика]),коэф_произв[Коэффициент],"",0)} -> 0.95 | S47: Стандартная (современная отделка с применением актуальных материалов) | T47: {=_xlfn.XLOOKUP(1,(Таблица2[[#This Row],[Тип]]=коэф_произв[Тип])*(Таблица2[[#This Row],[Уровень отделки]]=коэф_произв[Значение])*('Таблица объектов'!S$1=коэф_произв[Характеристика]),коэф_произв[Коэффициент],"",0)} -> 0.8 | U47: =IF(Таблица2[[#This Row],[Тип]]="прочие",0.05,PRODUCT(Таблица2[[#This Row],[Уровень отделки коэф.]],Таблица2[[#This Row],[Планировка коэф.]],Таблица2[[#This Row],[Архитектура коэф.]],Таблица2[[#This Row],[Инженерное оснащение коэф.]],Таблица2[[#This Row],[Полы коэф.]],Таблица2[[#This Row],[Конструкция коэф.]],Таблица2[[#This Row],[Наличие / Возможность кран-балки коэф.]],Таблица2[[#This Row],[Высота коэф.]])) -> 0.4104 | V47: =IF(Таблица2[[#This Row],[Тип]]="произв",IF(Таблица2[[#This Row],[Капитальность]]<0.33,"произв класс 4",IF(Таблица2[[#This Row],[Капитальность]]<0.55,"произв класс 3",IF(Таблица2[[#This Row],[Капитальность]]<0.77,"произв класс 2","произв класс 1"))),IF(Таблица2[[#This Row],[Тип]]="гражд",IF(Таблица2[[#This Row],[Капитальность]]<0.33,"гражд класс 4",IF(Таблица2[[#This Row],[Капитальность]]<0.55,"гражд класс 3",IF(Таблица2[[#This Row],[Капитальность]]<0.77,"гражд класс 2","гражд класс 1"))),"прочие")) -> гражд класс 3 | W47: =Таблица2[[#This Row],[Площадь, м2]]*Таблица2[[#This Row],[Капитальность]] -> 30.69792 | Z47: =Y47*Таблица2[[#This Row],[Капитальность]] -> 0
A48: Аналог 5 | B48: 1561.2 | C48: Производственное помещение | D48: произв | E48: 5-8 м. | F48: {=_xlfn.XLOOKUP(1,(Таблица2[[#This Row],[Тип]]=коэф_произв[Тип])*(Таблица2[[#This Row],[Высота]]=коэф_произв[Значение])*('Таблица объектов'!E$1=коэф_произв[Характеристика]),коэф_произв[Коэффициент],"",0)} -> 0.8 | G48: Не установлено (по умолчанию) | H48: {=_xlfn.XLOOKUP(1,(Таблица2[[#This Row],[Тип]]=коэф_произв[Тип])*(Таблица2[[#This Row],[Наличие / Возможность кран-балки]]=коэф_произв[Значение])*('Таблица объектов'!G$1=коэф_произв[Характеристика]),коэф_произв[Коэффициент],"",0)} -> 0.95 | I48: Блочные по железобетонному каркасу, без утепления | J48: {=_xlfn.XLOOKUP(1,(Таблица2[[#This Row],[Тип]]=коэф_произв[Тип])*(Таблица2[[#This Row],[Конструкция]]=коэф_произв[Значение])*('Таблица объектов'!I$1=коэф_произв[Характеристика]),коэф_произв[Коэффициент],"",0)} -> 0.7 | K48: Простые | L48: {=_xlfn.XLOOKUP(1,(Таблица2[[#This Row],[Тип]]=коэф_произв[Тип])*(Таблица2[[#This Row],[Полы]]=коэф_произв[Значение])*('Таблица объектов'!K$1=коэф_произв[Характеристика]),коэф_произв[Коэффициент],"",0)} -> 0.9 | M48: Стандартное (по всем помещениям разводка освещения, водопровод, канализация) | N48: {=_xlfn.XLOOKUP(1,(Таблица2[[#This Row],[Тип]]=коэф_произв[Тип])*(Таблица2[[#This Row],[Инженерное оснащение]]=коэф_произв[Значение])*('Таблица объектов'!M$1=коэф_произв[Характеристика]),коэф_произв[Коэффициент],"",0)} -> 0.9 | P48: {=_xlfn.XLOOKUP(1,(Таблица2[[#This Row],[Тип]]=коэф_произв[Тип])*(Таблица2[[#This Row],[Архитектура]]=коэф_произв[Значение])*('Таблица объектов'!O$1=коэф_произв[Характеристика]),коэф_произв[Коэффициент],"",0)} | R48: {=_xlfn.XLOOKUP(1,(Таблица2[[#This Row],[Тип]]=коэф_произв[Тип])*(Таблица2[[#This Row],[Планировка]]=коэф_произв[Значение])*('Таблица объектов'!Q$1=коэф_произв[Характеристика]),коэф_произв[Коэффициент],"",0)} | T48: {=_xlfn.XLOOKUP(1,(Таблица2[[#This Row],[Тип]]=коэф_произв[Тип])*(Таблица2[[#This Row],[Уровень отделки]]=коэф_произв[Значение])*('Таблица объектов'!S$1=коэф_произв[Характеристика]),коэф_произв[Коэффициент],"",0)} | U48: =IF(Таблица2[[#This Row],[Тип]]="прочие",0.05,PRODUCT(Таблица2[[#This Row],[Уровень отделки коэф.]],Таблица2[[#This Row],[Планировка коэф.]],Таблица2[[#This Row],[Архитектура коэф.]],Таблица2[[#This Row],[Инженерное оснащение коэф.]],Таблица2[[#This Row],[Полы коэф.]],Таблица2[[#This Row],[Конструкция коэф.]],Таблица2[[#This Row],[Наличие / Возможность кран-балки коэф.]],Таблица2[[#This Row],[Высота коэф.]])) -> 0.43092 | V48: =IF(Таблица2[[#This Row],[Тип]]="произв",IF(Таблица2[[#This Row],[Капитальность]]<0.33,"произв класс 4",IF(Таблица2[[#This Row],[Капитальность]]<0.55,"произв класс 3",IF(Таблица2[[#This Row],[Капитальность]]<0.77,"произв класс 2","произв класс 1"))),IF(Таблица2[[#This Row],[Тип]]="гражд",IF(Таблица2[[#This Row],[Капитальность]]<0.33,"гражд класс 4",IF(Таблица2[[#This Row],[Капитальность]]<0.55,"гражд класс 3",IF(Таблица2[[#This Row],[Капитальность]]<0.77,"гражд класс 2","гражд класс 1"))),"прочие")) -> произв класс 3 | W48: =Таблица2[[#This Row],[Площадь, м2]]*Таблица2[[#This Row],[Капитальность]] -> 672.7523 | Z48: =Y48*Таблица2[[#This Row],[Капитальность]] -> 0
A49: Аналог 5 | B49: 840 | C49: Производственное помещение | D49: произв | E49: 3-5 м. | F49: {=_xlfn.XLOOKUP(1,(Таблица2[[#This Row],[Тип]]=коэф_произв[Тип])*(Таблица2[[#This Row],[Высота]]=коэф_произв[Значение])*('Таблица объектов'!E$1=коэф_произв[Характеристика]),коэф_произв[Коэффициент],"",0)} -> 0.6 | G49: Нет | H49: {=_xlfn.XLOOKUP(1,(Таблица2[[#This Row],[Тип]]=коэф_произв[Тип])*(Таблица2[[#This Row],[Наличие / Возможность кран-балки]]=коэф_произв[Значение])*('Таблица объектов'!G$1=коэф_произв[Характеристика]),коэф_произв[Коэффициент],"",0)} -> 0.9 | I49: Блочные по железобетонному каркасу, без утепления | J49: {=_xlfn.XLOOKUP(1,(Таблица2[[#This Row],[Тип]]=коэф_произв[Тип])*(Таблица2[[#This Row],[Конструкция]]=коэф_произв[Значение])*('Таблица объектов'!I$1=коэф_произв[Характеристика]),коэф_произв[Коэффициент],"",0)} -> 0.7 | K49: Простые | L49: {=_xlfn.XLOOKUP(1,(Таблица2[[#This Row],[Тип]]=коэф_произв[Тип])*(Таблица2[[#This Row],[Полы]]=коэф_произв[Значение])*('Таблица объектов'!K$1=коэф_произв[Характеристика]),коэф_произв[Коэффициент],"",0)} -> 0.9 | M49: Стандартное (по всем помещениям разводка освещения, водопровод, канализация) | N49: {=_xlfn.XLOOKUP(1,(Таблица2[[#This Row],[Тип]]=коэф_произв[Тип])*(Таблица2[[#This Row],[Инженерное оснащение]]=коэф_произв[Значение])*('Таблица объектов'!M$1=коэф_произв[Характеристика]),коэф_произв[Коэффициент],"",0)} -> 0.9 | P49: {=_xlfn.XLOOKUP(1,(Таблица2[[#This Row],[Тип]]=коэф_произв[Тип])*(Таблица2[[#This Row],[Архитектура]]=коэф_произв[Значение])*('Таблица объектов'!O$1=коэф_произв[Характеристика]),коэф_произв[Коэффициент],"",0)} | R49: {=_xlfn.XLOOKUP(1,(Таблица2[[#This Row],[Тип]]=коэф_произв[Тип])*(Таблица2[[#This Row],[Планировка]]=коэф_произв[Значение])*('Таблица объектов'!Q$1=коэф_произв[Характеристика]),коэф_произв[Коэффициент],"",0)} | T49: {=_xlfn.XLOOKUP(1,(Таблица2[[#This Row],[Тип]]=коэф_произв[Тип])*(Таблица2[[#This Row],[Уровень отделки]]=коэф_произв[Значение])*('Таблица объектов'!S$1=коэф_произв[Характеристика]),коэф_произв[Коэффициент],"",0)} | U49: =IF(Таблица2[[#This Row],[Тип]]="прочие",0.05,PRODUCT(Таблица2[[#This Row],[Уровень отделки коэф.]],Таблица2[[#This Row],[Планировка коэф.]],Таблица2[[#This Row],[Архитектура коэф.]],Таблица2[[#This Row],[Инженерное оснащение коэф.]],Таблица2[[#This Row],[Полы коэф.]],Таблица2[[#This Row],[Конструкция коэф.]],Таблица2[[#This Row],[Наличие / Возможность кран-балки коэф.]],Таблица2[[#This Row],[Высота коэф.]])) -> 0.30618 | V49: =IF(Таблица2[[#This Row],[Тип]]="произв",IF(Таблица2[[#This Row],[Капитальность]]<0.33,"произв класс 4",IF(Таблица2[[#This Row],[Капитальность]]<0.55,"произв класс 3",IF(Таблица2[[#This Row],[Капитальность]]<0.77,"произв класс 2","произв класс 1"))),IF(Таблица2[[#This Row],[Тип]]="гражд",IF(Таблица2[[#This Row],[Капитальность]]<0.33,"гражд класс 4",IF(Таблица2[[#This Row],[Капитальность]]<0.55,"гражд класс 3",IF(Таблица2[[#This Row],[Капитальность]]<0.77,"гражд класс 2","гражд класс 1"))),"прочие")) -> произв класс 4 | W49: =Таблица2[[#This Row],[Площадь, м2]]*Таблица2[[#This Row],[Капитальность]] -> 257.1912 | Z49: =Y49*Таблица2[[#This Row],[Капитальность]] -> 0
A50: Аналог 6 | B50: 110 | C50: АБК | D50: гражд | E50: 2,6-3,2 м. | F50: {=_xlfn.XLOOKUP(1,(Таблица2[[#This Row],[Тип]]=коэф_произв[Тип])*(Таблица2[[#This Row],[Высота]]=коэф_произв[Значение])*('Таблица объектов'!E$1=коэф_произв[Характеристика]),коэф_произв[Коэффициент],"",0)} -> 0.7 | H50: {=_xlfn.XLOOKUP(1,(Таблица2[[#This Row],[Тип]]=коэф_произв[Тип])*(Таблица2[[#This Row],[Наличие / Возможность кран-балки]]=коэф_произв[Значение])*('Таблица объектов'!G$1=коэф_произв[Характеристика]),коэф_произв[Коэффициент],"",0)} | I50: Некапитальная | J50: {=_xlfn.XLOOKUP(1,(Таблица2[[#This Row],[Тип]]=коэф_произв[Тип])*(Таблица2[[#This Row],[Конструкция]]=коэф_произв[Значение])*('Таблица объектов'!I$1=коэф_произв[Характеристика]),коэф_произв[Коэффициент],"",0)} -> 0.8 | L50: {=_xlfn.XLOOKUP(1,(Таблица2[[#This Row],[Тип]]=коэф_произв[Тип])*(Таблица2[[#This Row],[Полы]]=коэф_произв[Значение])*('Таблица объектов'!K$1=коэф_произв[Характеристика]),коэф_произв[Коэффициент],"",0)} | M50: Отсутствует или минимальное (минимальная разводка освещения, водопровода) | N50: {=_xlfn.XLOOKUP(1,(Таблица2[[#This Row],[Тип]]=коэф_произв[Тип])*(Таблица2[[#This Row],[Инженерное оснащение]]=коэф_произв[Значение])*('Таблица объектов'!M$1=коэф_произв[Характеристика]),коэф_произв[Коэффициент],"",0)} -> 0.8 | O50: Устаревшая/ Современная | P50: {=_xlfn.XLOOKUP(1,(Таблица2[[#This Row],[Тип]]=коэф_произв[Тип])*(Таблица2[[#This Row],[Архитектура]]=коэф_произв[Значение])*('Таблица объектов'!O$1=коэф_произв[Характеристика]),коэф_произв[Коэффициент],"",0)} -> 0.9 | Q50: Свободная | R50: {=_xlfn.XLOOKUP(1,(Таблица2[[#This Row],[Тип]]=коэф_произв[Тип])*(Таблица2[[#This Row],[Планировка]]=коэф_произв[Значение])*('Таблица объектов'!Q$1=коэф_произв[Характеристика]),коэф_произв[Коэффициент],"",0)} -> 0.9 | S50: Простая (потолки и стены оштукатурены, окрашены или отделаны дешевыми материалами (МДФ), полы линолеумные | T50: {=_xlfn.XLOOKUP(1,(Таблица2[[#This Row],[Тип]]=коэф_произв[Тип])*(Таблица2[[#This Row],[Уровень отделки]]=коэф_произв[Значение])*('Таблица объектов'!S$1=коэф_произв[Характеристика]),коэф_произв[Коэффициент],"",0)} -> 0.7 | U50: =IF(Таблица2[[#This Row],[Тип]]="прочие",0.05,PRODUCT(Таблица2[[#This Row],[Уровень отделки коэф.]],Таблица2[[#This Row],[Планировка коэф.]],Таблица2[[#This Row],[Архитектура коэф.]],Таблица2[[#This Row],[Инженерное оснащение коэф.]],Таблица2[[#This Row],[Полы коэф.]],Таблица2[[#This Row],[Конструкция коэф.]],Таблица2[[#This Row],[Наличие / Возможность кран-балки коэф.]],Таблица2[[#This Row],[Высота коэф.]])) -> 0.254016 | V50: =IF(Таблица2[[#This Row],[Тип]]="произв",IF(Таблица2[[#This Row],[Капитальность]]<0.33,"произв класс 4",IF(Таблица2[[#This Row],[Капитальность]]<0.55,"произв класс 3",IF(Таблица2[[#This Row],[Капитальность]]<0.77,"произв класс 2","произв класс 1"))),IF(Таблица2[[#This Row],[Тип]]="гражд",IF(Таблица2[[#This Row],[Капитальность]]<0.33,"гражд класс 4",IF(Таблица2[[#This Row],[Капитальность]]<0.55,"гражд класс 3",IF(Таблица2[[#This Row],[Капитальность]]<0.77,"гражд класс 2","гражд класс 1"))),"прочие")) -> гражд класс 4 | W50: =Таблица2[[#This Row],[Площадь, м2]]*Таблица2[[#This Row],[Капитальность]] -> 27.94176 | Z50: =Y50*Таблица2[[#This Row],[Капитальность]] -> 0
A51: Аналог 6 | B51: 1300 | C51: Производственное помещение | D51: произв | E51: Более 8 м. (условно - 10 м в среднем) | F51: {=_xlfn.XLOOKUP(1,(Таблица2[[#This Row],[Тип]]=коэф_произв[Тип])*(Таблица2[[#This Row],[Высота]]=коэф_произв[Значение])*('Таблица объектов'!E$1=коэф_произв[Характеристика]),коэф_произв[Коэффициент],"",0)} -> 1 | G51: Нет | H51: {=_xlfn.XLOOKUP(1,(Таблица2[[#This Row],[Тип]]=коэф_произв[Тип])*(Таблица2[[#This Row],[Наличие / Возможность кран-балки]]=коэф_произв[Значение])*('Таблица объектов'!G$1=коэф_произв[Характеристика]),коэф_произв[Коэффициент],"",0)} -> 0.9 | I51: Блочные бескаркасные или металлокаркасные холодные | J51: {=_xlfn.XLOOKUP(1,(Таблица2[[#This Row],[Тип]]=коэф_произв[Тип])*(Таблица2[[#This Row],[Конструкция]]=коэф_произв[Значение])*('Таблица объектов'!I$1=коэф_произв[Характеристика]),коэф_произв[Коэффициент],"",0)} -> 0.5 | K51: Простые | L51: {=_xlfn.XLOOKUP(1,(Таблица2[[#This Row],[Тип]]=коэф_произв[Тип])*(Таблица2[[#This Row],[Полы]]=коэф_произв[Значение])*('Таблица объектов'!K$1=коэф_произв[Характеристика]),коэф_произв[Коэффициент],"",0)} -> 0.9 | M51: Отсутствует или минимальное (минимальная разводка освещения, водопровода) | N51: {=_xlfn.XLOOKUP(1,(Таблица2[[#This Row],[Тип]]=коэф_произв[Тип])*(Таблица2[[#This Row],[Инженерное оснащение]]=коэф_произв[Значение])*('Таблица объектов'!M$1=коэф_произв[Характеристика]),коэф_произв[Коэффициент],"",0)} -> 0.8 | P51: {=_xlfn.XLOOKUP(1,(Таблица2[[#This Row],[Тип]]=коэф_произв[Тип])*(Таблица2[[#This Row],[Архитектура]]=коэф_произв[Значение])*('Таблица объектов'!O$1=коэф_произв[Характеристика]),коэф_произв[Коэффициент],"",0)} | R51: {=_xlfn.XLOOKUP(1,(Таблица2[[#This Row],[Тип]]=коэф_произв[Тип])*(Таблица2[[#This Row],[Планировка]]=коэф_произв[Значение])*('Таблица объектов'!Q$1=коэф_произв[Характеристика]),коэф_произв[Коэффициент],"",0)} | T51: {=_xlfn.XLOOKUP(1,(Таблица2[[#This Row],[Тип]]=коэф_произв[Тип])*(Таблица2[[#This Row],[Уровень отделки]]=коэф_произв[Значение])*('Таблица объектов'!S$1=коэф_произв[Характеристика]),коэф_произв[Коэффициент],"",0)} | U51: =IF(Таблица2[[#This Row],[Тип]]="прочие",0.05,PRODUCT(Таблица2[[#This Row],[Уровень отделки коэф.]],Таблица2[[#This Row],[Планировка коэф.]],Таблица2[[#This Row],[Архитектура коэф.]],Таблица2[[#This Row],[Инженерное оснащение коэф.]],Таблица2[[#This Row],[Полы коэф.]],Таблица2[[#This Row],[Конструкция коэф.]],Таблица2[[#This Row],[Наличие / Возможность кран-балки коэф.]],Таблица2[[#This Row],[Высота коэф.]])) -> 0.324 | V51: =IF(Таблица2[[#This Row],[Тип]]="произв",IF(Таблица2[[#This Row],[Капитальность]]<0.33,"произв класс 4",IF(Таблица2[[#This Row],[Капитальность]]<0.55,"произв класс 3",IF(Таблица2[[#This Row],[Капитальность]]<0.77,"произв класс 2","произв класс 1"))),IF(Таблица2[[#This Row],[Тип]]="гражд",IF(Таблица2[[#This Row],[Капитальность]]<0.33,"гражд класс 4",IF(Таблица2[[#This Row],[Капитальность]]<0.55,"гражд класс 3",IF(Таблица2[[#This Row],[Капитальность]]<0.77,"гражд класс 2","гражд класс 1"))),"прочие")) -> произв класс 4 | W51: =Таблица2[[#This Row],[Площадь, м2]]*Таблица2[[#This Row],[Капитальность]] -> 421.2 | Z51: =Y51*Таблица2[[#This Row],[Капитальность]] -> 0
A52: Аналог 6 | B52: 460 | C52: Производственное помещение | D52: произв | E52: 5-8 м. | F52: {=_xlfn.XLOOKUP(1,(Таблица2[[#This Row],[Тип]]=коэф_произв[Тип])*(Таблица2[[#This Row],[Высота]]=коэф_произв[Значение])*('Таблица объектов'!E$1=коэф_произв[Характеристика]),коэф_произв[Коэффициент],"",0)} -> 0.8 | G52: Нет | H52: {=_xlfn.XLOOKUP(1,(Таблица2[[#This Row],[Тип]]=коэф_произв[Тип])*(Таблица2[[#This Row],[Наличие / Возможность кран-балки]]=коэф_произв[Значение])*('Таблица объектов'!G$1=коэф_произв[Характеристика]),коэф_произв[Коэффициент],"",0)} -> 0.9 | I52: Блочные бескаркасные или металлокаркасные холодные | J52: {=_xlfn.XLOOKUP(1,(Таблица2[[#This Row],[Тип]]=коэф_произв[Тип])*(Таблица2[[#This Row],[Конструкция]]=коэф_произв[Значение])*('Таблица объектов'!I$1=коэф_произв[Характеристика]),коэф_произв[Коэффициент],"",0)} -> 0.5 | K52: Простые | L52: {=_xlfn.XLOOKUP(1,(Таблица2[[#This Row],[Тип]]=коэф_произв[Тип])*(Таблица2[[#This Row],[Полы]]=коэф_произв[Значение])*('Таблица объектов'!K$1=коэф_произв[Характеристика]),коэф_произв[Коэффициент],"",0)} -> 0.9 | M52: Отсутствует или минимальное (минимальная разводка освещения, водопровода) | N52: {=_xlfn.XLOOKUP(1,(Таблица2[[#This Row],[Тип]]=коэф_произв[Тип])*(Таблица2[[#This Row],[Инженерное оснащение]]=коэф_произв[Значение])*('Таблица объектов'!M$1=коэф_произв[Характеристика]),коэф_произв[Коэффициент],"",0)} -> 0.8 | P52: {=_xlfn.XLOOKUP(1,(Таблица2[[#This Row],[Тип]]=коэф_произв[Тип])*(Таблица2[[#This Row],[Архитектура]]=коэф_произв[Значение])*('Таблица объектов'!O$1=коэф_произв[Характеристика]),коэф_произв[Коэффициент],"",0)} | R52: {=_xlfn.XLOOKUP(1,(Таблица2[[#This Row],[Тип]]=коэф_произв[Тип])*(Таблица2[[#This Row],[Планировка]]=коэф_произв[Значение])*('Таблица объектов'!Q$1=коэф_произв[Характеристика]),коэф_произв[Коэффициент],"",0)} | T52: {=_xlfn.XLOOKUP(1,(Таблица2[[#This Row],[Тип]]=коэф_произв[Тип])*(Таблица2[[#This Row],[Уровень отделки]]=коэф_произв[Значение])*('Таблица объектов'!S$1=коэф_произв[Характеристика]),коэф_произв[Коэффициент],"",0)} | U52: =IF(Таблица2[[#This Row],[Тип]]="прочие",0.05,PRODUCT(Таблица2[[#This Row],[Уровень отделки коэф.]],Таблица2[[#This Row],[Планировка коэф.]],Таблица2[[#This Row],[Архитектура коэф.]],Таблица2[[#This Row],[Инженерное оснащение коэф.]],Таблица2[[#This Row],[Полы коэф.]],Таблица2[[#This Row],[Конструкция коэф.]],Таблица2[[#This Row],[Наличие / Возможность кран-балки коэф.]],Таблица2[[#This Row],[Высота коэф.]])) -> 0.2592 | V52: =IF(Таблица2[[#This Row],[Тип]]="произв",IF(Таблица2[[#This Row],[Капитальность]]<0.33,"произв класс 4",IF(Таблица2[[#This Row],[Капитальность]]<0.55,"произв класс 3",IF(Таблица2[[#This Row],[Капитальность]]<0.77,"произв класс 2","произв класс 1"))),IF(Таблица2[[#This Row],[Тип]]="гражд",IF(Таблица2[[#This Row],[Капитальность]]<0.33,"гражд класс 4",IF(Таблица2[[#This Row],[Капитальность]]<0.55,"гражд класс 3",IF(Таблица2[[#This Row],[Капитальность]]<0.77,"гражд класс 2","гражд класс 1"))),"прочие")) -> произв класс 4 | W52: =Таблица2[[#This Row],[Площадь, м2]]*Таблица2[[#This Row],[Капитальность]] -> 119.232 | Z52: =Y52*Таблица2[[#This Row],[Капитальность]] -> 0
A53: Аналог 7 | B53: 500 | C53: АБК | D53: гражд | E53: 2,6-3,2 м. | F53: {=_xlfn.XLOOKUP(1,(Таблица2[[#This Row],[Тип]]=коэф_произв[Тип])*(Таблица2[[#This Row],[Высота]]=коэф_произв[Значение])*('Таблица объектов'!E$1=коэф_произв[Характеристика]),коэф_произв[Коэффициент],"",0)} -> 0.7 | H53: {=_xlfn.XLOOKUP(1,(Таблица2[[#This Row],[Тип]]=коэф_произв[Тип])*(Таблица2[[#This Row],[Наличие / Возможность кран-балки]]=коэф_произв[Значение])*('Таблица объектов'!G$1=коэф_произв[Характеристика]),коэф_произв[Коэффициент],"",0)} | I53: Капитальная | J53: {=_xlfn.XLOOKUP(1,(Таблица2[[#This Row],[Тип]]=коэф_произв[Тип])*(Таблица2[[#This Row],[Конструкция]]=коэф_произв[Значение])*('Таблица объектов'!I$1=коэф_произв[Характеристика]),коэф_произв[Коэффициент],"",0)} -> 1 | L53: {=_xlfn.XLOOKUP(1,(Таблица2[[#This Row],[Тип]]=коэф_произв[Тип])*(Таблица2[[#This Row],[Полы]]=коэф_произв[Значение])*('Таблица объектов'!K$1=коэф_произв[Характеристика]),коэф_произв[Коэффициент],"",0)} | M53: Отсутствует или минимальное (минимальная разводка освещения, водопровода) | N53: {=_xlfn.XLOOKUP(1,(Таблица2[[#This Row],[Тип]]=коэф_произв[Тип])*(Таблица2[[#This Row],[Инженерное оснащение]]=коэф_произв[Значение])*('Таблица объектов'!M$1=коэф_произв[Характеристика]),коэф_произв[Коэффициент],"",0)} -> 0.8 | O53: Устаревшая | P53: {=_xlfn.XLOOKUP(1,(Таблица2[[#This Row],[Тип]]=коэф_произв[Тип])*(Таблица2[[#This Row],[Архитектура]]=коэф_произв[Значение])*('Таблица объектов'!O$1=коэф_произв[Характеристика]),коэф_произв[Коэффициент],"",0)} -> 0.8 | Q53: Смешанная | R53: {=_xlfn.XLOOKUP(1,(Таблица2[[#This Row],[Тип]]=коэф_произв[Тип])*(Таблица2[[#This Row],[Планировка]]=коэф_произв[Значение])*('Таблица объектов'!Q$1=коэф_произв[Характеристика]),коэф_произв[Коэффициент],"",0)} -> 0.95 | S53: Простая (потолки и стены оштукатурены, окрашены или отделаны дешевыми материалами (МДФ), полы линолеумные | T53: {=_xlfn.XLOOKUP(1,(Таблица2[[#This Row],[Тип]]=коэф_произв[Тип])*(Таблица2[[#This Row],[Уровень отделки]]=коэф_произв[Значение])*('Таблица объектов'!S$1=коэф_произв[Характеристика]),коэф_произв[Коэффициент],"",0)} -> 0.7 | U53: =IF(Таблица2[[#This Row],[Тип]]="прочие",0.05,PRODUCT(Таблица2[[#This Row],[Уровень отделки коэф.]],Таблица2[[#This Row],[Планировка коэф.]],Таблица2[[#This Row],[Архитектура коэф.]],Таблица2[[#This Row],[Инженерное оснащение коэф.]],Таблица2[[#This Row],[Полы коэф.]],Таблица2[[#This Row],[Конструкция коэф.]],Таблица2[[#This Row],[Наличие / Возможность кран-балки коэф.]],Таблица2[[#This Row],[Высота коэф.]])) -> 0.29792 | V53: =IF(Таблица2[[#This Row],[Тип]]="произв",IF(Таблица2[[#This Row],[Капитальность]]<0.33,"произв класс 4",IF(Таблица2[[#This Row],[Капитальность]]<0.55,"произв класс 3",IF(Таблица2[[#This Row],[Капитальность]]<0.77,"произв класс 2","произв класс 1"))),IF(Таблица2[[#This Row],[Тип]]="гражд",IF(Таблица2[[#This Row],[Капитальность]]<0.33,"гражд класс 4",IF(Таблица2[[#This Row],[Капитальность]]<0.55,"гражд класс 3",IF(Таблица2[[#This Row],[Капитальность]]<0.77,"гражд класс 2","гражд класс 1"))),"прочие")) -> гражд класс 4 | W53: =Таблица2[[#This Row],[Площадь, м2]]*Таблица2[[#This Row],[Капитальность]] -> 148.96 | Z53: =Y53*Таблица2[[#This Row],[Капитальность]] -> 0
A54: Аналог 7 | B54: 700 | C54: Производственное помещение | D54: произв | E54: Более 8 м. (условно - 10 м в среднем) | F54: {=_xlfn.XLOOKUP(1,(Таблица2[[#This Row],[Тип]]=коэф_произв[Тип])*(Таблица2[[#This Row],[Высота]]=коэф_произв[Значение])*('Таблица объектов'!E$1=коэф_произв[Характеристика]),коэф_произв[Коэффициент],"",0)} -> 1 | G54: Не установлено (по умолчанию) | H54: {=_xlfn.XLOOKUP(1,(Таблица2[[#This Row],[Тип]]=коэф_произв[Тип])*(Таблица2[[#This Row],[Наличие / Возможность кран-балки]]=коэф_произв[Значение])*('Таблица объектов'!G$1=коэф_произв[Характеристика]),коэф_произв[Коэффициент],"",0)} -> 0.95 | I54: Блочные по железобетонному каркасу, без утепления | J54: {=_xlfn.XLOOKUP(1,(Таблица2[[#This Row],[Тип]]=коэф_произв[Тип])*(Таблица2[[#This Row],[Конструкция]]=коэф_произв[Значение])*('Таблица объектов'!I$1=коэф_произв[Характеристика]),коэф_произв[Коэффициент],"",0)} -> 0.7 | K54: Простые | L54: {=_xlfn.XLOOKUP(1,(Таблица2[[#This Row],[Тип]]=коэф_произв[Тип])*(Таблица2[[#This Row],[Полы]]=коэф_произв[Значение])*('Таблица объектов'!K$1=коэф_произв[Характеристика]),коэф_произв[Коэффициент],"",0)} -> 0.9 | M54: Отсутствует или минимальное (минимальная разводка освещения, водопровода) | N54: {=_xlfn.XLOOKUP(1,(Таблица2[[#This Row],[Тип]]=коэф_произв[Тип])*(Таблица2[[#This Row],[Инженерное оснащение]]=коэф_произв[Значение])*('Таблица объектов'!M$1=коэф_произв[Характеристика]),коэф_произв[Коэффициент],"",0)} -> 0.8 | P54: {=_xlfn.XLOOKUP(1,(Таблица2[[#This Row],[Тип]]=коэф_произв[Тип])*(Таблица2[[#This Row],[Архитектура]]=коэф_произв[Значение])*('Таблица объектов'!O$1=коэф_произв[Характеристика]),коэф_произв[Коэффициент],"",0)} | R54: {=_xlfn.XLOOKUP(1,(Таблица2[[#This Row],[Тип]]=коэф_произв[Тип])*(Таблица2[[#This Row],[Планировка]]=коэф_произв[Значение])*('Таблица объектов'!Q$1=коэф_произв[Характеристика]),коэф_произв[Коэффициент],"",0)} | T54: {=_xlfn.XLOOKUP(1,(Таблица2[[#This Row],[Тип]]=коэф_произв[Тип])*(Таблица2[[#This Row],[Уровень отделки]]=коэф_произв[Значение])*('Таблица объектов'!S$1=коэф_произв[Характеристика]),коэф_произв[Коэффициент],"",0)} | U54: =IF(Таблица2[[#This Row],[Тип]]="прочие",0.05,PRODUCT(Таблица2[[#This Row],[Уровень отделки коэф.]],Таблица2[[#This Row],[Планировка коэф.]],Таблица2[[#This Row],[Архитектура коэф.]],Таблица2[[#This Row],[Инженерное оснащение коэф.]],Таблица2[[#This Row],[Полы коэф.]],Таблица2[[#This Row],[Конструкция коэф.]],Таблица2[[#This Row],[Наличие / Возможность кран-балки коэф.]],Таблица2[[#This Row],[Высота коэф.]])) -> 0.4788 | V54: =IF(Таблица2[[#This Row],[Тип]]="произв",IF(Таблица2[[#This Row],[Капитальность]]<0.33,"произв класс 4",IF(Таблица2[[#This Row],[Капитальность]]<0.55,"произв класс 3",IF(Таблица2[[#This Row],[Капитальность]]<0.77,"произв класс 2","произв класс 1"))),IF(Таблица2[[#This Row],[Тип]]="гражд",IF(Таблица2[[#This Row],[Капитальность]]<0.33,"гражд класс 4",IF(Таблица2[[#This Row],[Капитальность]]<0.55,"гражд класс 3",IF(Таблица2[[#This Row],[Капитальность]]<0.77,"гражд класс 2","гражд класс 1"))),"прочие")) -> произв класс 3 | W54: =Таблица2[[#This Row],[Площадь, м2]]*Таблица2[[#This Row],[Капитальность]] -> 335.16 | Z54: =Y54*Таблица2[[#This Row],[Капитальность]] -> 0
A55: Аналог 7 | B55: 122 | C55: Производственное помещение | D55: произв | E55: 3-5 м. | F55: {=_xlfn.XLOOKUP(1,(Таблица2[[#This Row],[Тип]]=коэф_произв[Тип])*(Таблица2[[#This Row],[Высота]]=коэф_произв[Значение])*('Таблица объектов'!E$1=коэф_произв[Характеристика]),коэф_произв[Коэффициент],"",0)} -> 0.6 | G55: Нет | H55: {=_xlfn.XLOOKUP(1,(Таблица2[[#This Row],[Тип]]=коэф_произв[Тип])*(Таблица2[[#This Row],[Наличие / Возможность кран-балки]]=коэф_произв[Значение])*('Таблица объектов'!G$1=коэф_произв[Характеристика]),коэф_произв[Коэффициент],"",0)} -> 0.9 | I55: Блочные бескаркасные или металлокаркасные холодные | J55: {=_xlfn.XLOOKUP(1,(Таблица2[[#This Row],[Тип]]=коэф_произв[Тип])*(Таблица2[[#This Row],[Конструкция]]=коэф_произв[Значение])*('Таблица объектов'!I$1=коэф_произв[Характеристика]),коэф_произв[Коэффициент],"",0)} -> 0.5 | K55: Простые | L55: {=_xlfn.XLOOKUP(1,(Таблица2[[#This Row],[Тип]]=коэф_произв[Тип])*(Таблица2[[#This Row],[Полы]]=коэф_произв[Значение])*('Таблица объектов'!K$1=коэф_произв[Характеристика]),коэф_произв[Коэффициент],"",0)} -> 0.9 | M55: Отсутствует или минимальное (минимальная разводка освещения, водопровода) | N55: {=_xlfn.XLOOKUP(1,(Таблица2[[#This Row],[Тип]]=коэф_произв[Тип])*(Таблица2[[#This Row],[Инженерное оснащение]]=коэф_произв[Значение])*('Таблица объектов'!M$1=коэф_произв[Характеристика]),коэф_произв[Коэффициент],"",0)} -> 0.8 | P55: {=_xlfn.XLOOKUP(1,(Таблица2[[#This Row],[Тип]]=коэф_произв[Тип])*(Таблица2[[#This Row],[Архитектура]]=коэф_произв[Значение])*('Таблица объектов'!O$1=коэф_произв[Характеристика]),коэф_произв[Коэффициент],"",0)} | R55: {=_xlfn.XLOOKUP(1,(Таблица2[[#This Row],[Тип]]=коэф_произв[Тип])*(Таблица2[[#This Row],[Планировка]]=коэф_произв[Значение])*('Таблица объектов'!Q$1=коэф_произв[Характеристика]),коэф_произв[Коэффициент],"",0)} | T55: {=_xlfn.XLOOKUP(1,(Таблица2[[#This Row],[Тип]]=коэф_произв[Тип])*(Таблица2[[#This Row],[Уровень отделки]]=коэф_произв[Значение])*('Таблица объектов'!S$1=коэф_произв[Характеристика]),коэф_произв[Коэффициент],"",0)} | U55: =IF(Таблица2[[#This Row],[Тип]]="прочие",0.05,PRODUCT(Таблица2[[#This Row],[Уровень отделки коэф.]],Таблица2[[#This Row],[Планировка коэф.]],Таблица2[[#This Row],[Архитектура коэф.]],Таблица2[[#This Row],[Инженерное оснащение коэф.]],Таблица2[[#This Row],[Полы коэф.]],Таблица2[[#This Row],[Конструкция коэф.]],Таблица2[[#This Row],[Наличие / Возможность кран-балки коэф.]],Таблица2[[#This Row],[Высота коэф.]])) -> 0.1944 | V55: =IF(Таблица2[[#This Row],[Тип]]="произв",IF(Таблица2[[#This Row],[Капитальность]]<0.33,"произв класс 4",IF(Таблица2[[#This Row],[Капитальность]]<0.55,"произв класс 3",IF(Таблица2[[#This Row],[Капитальность]]<0.77,"произв класс 2","произв класс 1"))),IF(Таблица2[[#This Row],[Тип]]="гражд",IF(Таблица2[[#This Row],[Капитальность]]<0.33,"гражд класс 4",IF(Таблица2[[#This Row],[Капитальность]]<0.55,"гражд класс 3",IF(Таблица2[[#This Row],[Капитальность]]<0.77,"гражд класс 2","гражд класс 1"))),"прочие")) -> произв класс 4 | W55: =Таблица2[[#This Row],[Площадь, м2]]*Таблица2[[#This Row],[Капитальность]] -> 23.7168 | Z55: =Y55*Таблица2[[#This Row],[Капитальность]] -> 0
A56: Аналог 7 | B56: 85 | C56: Навес | D56: прочие | F56: {=_xlfn.XLOOKUP(1,(Таблица2[[#This Row],[Тип]]=коэф_произв[Тип])*(Таблица2[[#This Row],[Высота]]=коэф_произв[Значение])*('Таблица объектов'!E$1=коэф_произв[Характеристика]),коэф_произв[Коэффициент],"",0)} | H56: {=_xlfn.XLOOKUP(1,(Таблица2[[#This Row],[Тип]]=коэф_произв[Тип])*(Таблица2[[#This Row],[Наличие / Возможность кран-балки]]=коэф_произв[Значение])*('Таблица объектов'!G$1=коэф_произв[Характеристика]),коэф_произв[Коэффициент],"",0)} | J56: {=_xlfn.XLOOKUP(1,(Таблица2[[#This Row],[Тип]]=коэф_произв[Тип])*(Таблица2[[#This Row],[Конструкция]]=коэф_произв[Значение])*('Таблица объектов'!I$1=коэф_произв[Характеристика]),коэф_произв[Коэффициент],"",0)} | L56: {=_xlfn.XLOOKUP(1,(Таблица2[[#This Row],[Тип]]=коэф_произв[Тип])*(Таблица2[[#This Row],[Полы]]=коэф_произв[Значение])*('Таблица объектов'!K$1=коэф_произв[Характеристика]),коэф_произв[Коэффициент],"",0)} | N56: {=_xlfn.XLOOKUP(1,(Таблица2[[#This Row],[Тип]]=коэф_произв[Тип])*(Таблица2[[#This Row],[Инженерное оснащение]]=коэф_произв[Значение])*('Таблица объектов'!M$1=коэф_произв[Характеристика]),коэф_произв[Коэффициент],"",0)} | P56: {=_xlfn.XLOOKUP(1,(Таблица2[[#This Row],[Тип]]=коэф_произв[Тип])*(Таблица2[[#This Row],[Архитектура]]=коэф_произв[Значение])*('Таблица объектов'!O$1=коэф_произв[Характеристика]),коэф_произв[Коэффициент],"",0)} | R56: {=_xlfn.XLOOKUP(1,(Таблица2[[#This Row],[Тип]]=коэф_произв[Тип])*(Таблица2[[#This Row],[Планировка]]=коэф_произв[Значение])*('Таблица объектов'!Q$1=коэф_произв[Характеристика]),коэф_произв[Коэффициент],"",0)} | T56: {=_xlfn.XLOOKUP(1,(Таблица2[[#This Row],[Тип]]=коэф_произв[Тип])*(Таблица2[[#This Row],[Уровень отделки]]=коэф_произв[Значение])*('Таблица объектов'!S$1=коэф_произв[Характеристика]),коэф_произв[Коэффициент],"",0)} | U56: =IF(Таблица2[[#This Row],[Тип]]="прочие",0.05,PRODUCT(Таблица2[[#This Row],[Уровень отделки коэф.]],Таблица2[[#This Row],[Планировка коэф.]],Таблица2[[#This Row],[Архитектура коэф.]],Таблица2[[#This Row],[Инженерное оснащение коэф.]],Таблица2[[#This Row],[Полы коэф.]],Таблица2[[#This Row],[Конструкция коэф.]],Таблица2[[#This Row],[Наличие / Возможность кран-балки коэф.]],Таблица2[[#This Row],[Высота коэф.]])) -> 0.05 | V56: =IF(Таблица2[[#This Row],[Тип]]="произв",IF(Таблица2[[#This Row],[Капитальность]]<0.33,"произв класс 4",IF(Таблица2[[#This Row],[Капитальность]]<0.55,"произв класс 3",IF(Таблица2[[#This Row],[Капитальность]]<0.77,"произв класс 2","произв класс 1"))),IF(Таблица2[[#This Row],[Тип]]="гражд",IF(Таблица2[[#This Row],[Капитальность]]<0.33,"гражд класс 4",IF(Таблица2[[#This Row],[Капитальность]]<0.55,"гражд класс 3",IF(Таблица2[[#This Row],[Капитальность]]<0.77,"гражд класс 2","гражд класс 1"))),"прочие")) -> прочие | W56: =Таблица2[[#This Row],[Площадь, м2]]*Таблица2[[#This Row],[Капитальность]] -> 4.25 | Z56: =Y56*Таблица2[[#This Row],[Капитальность]] -> 0
A57: Аналог 8 | B57: 23.1 | C57: АБК | D57: гражд | E57: До 2,6 м. | F57: {=_xlfn.XLOOKUP(1,(Таблица2[[#This Row],[Тип]]=коэф_произв[Тип])*(Таблица2[[#This Row],[Высота]]=коэф_произв[Значение])*('Таблица объектов'!E$1=коэф_произв[Характеристика]),коэф_произв[Коэффициент],"",0)} -> 0.6 | H57: {=_xlfn.XLOOKUP(1,(Таблица2[[#This Row],[Тип]]=коэф_произв[Тип])*(Таблица2[[#This Row],[Наличие / Возможность кран-балки]]=коэф_произв[Значение])*('Таблица объектов'!G$1=коэф_произв[Характеристика]),коэф_произв[Коэффициент],"",0)} | I57: Некапитальная | J57: {=_xlfn.XLOOKUP(1,(Таблица2[[#This Row],[Тип]]=коэф_произв[Тип])*(Таблица2[[#This Row],[Конструкция]]=коэф_произв[Значение])*('Таблица объектов'!I$1=коэф_произв[Характеристика]),коэф_произв[Коэффициент],"",0)} -> 0.8 | L57: {=_xlfn.XLOOKUP(1,(Таблица2[[#This Row],[Тип]]=коэф_произв[Тип])*(Таблица2[[#This Row],[Полы]]=коэф_произв[Значение])*('Таблица объектов'!K$1=коэф_произв[Характеристика]),коэф_произв[Коэффициент],"",0)} | M57: Отсутствует или минимальное (минимальная разводка освещения, водопровода) | N57: {=_xlfn.XLOOKUP(1,(Таблица2[[#This Row],[Тип]]=коэф_произв[Тип])*(Таблица2[[#This Row],[Инженерное оснащение]]=коэф_произв[Значение])*('Таблица объектов'!M$1=коэф_произв[Характеристика]),коэф_произв[Коэффициент],"",0)} -> 0.8 | O57: Устаревшая/ Современная | P57: {=_xlfn.XLOOKUP(1,(Таблица2[[#This Row],[Тип]]=коэф_произв[Тип])*(Таблица2[[#This Row],[Архитектура]]=коэф_произв[Значение])*('Таблица объектов'!O$1=коэф_произв[Характеристика]),коэф_произв[Коэффициент],"",0)} -> 0.9 | Q57: Смешанная | R57: {=_xlfn.XLOOKUP(1,(Таблица2[[#This Row],[Тип]]=коэф_произв[Тип])*(Таблица2[[#This Row],[Планировка]]=коэф_произв[Значение])*('Таблица объектов'!Q$1=коэф_произв[Характеристика]),коэф_произв[Коэффициент],"",0)} -> 0.95 | S57: Простая (потолки и стены оштукатурены, окрашены или отделаны дешевыми материалами (МДФ), полы линолеумные | T57: {=_xlfn.XLOOKUP(1,(Таблица2[[#This Row],[Тип]]=коэф_произв[Тип])*(Таблица2[[#This Row],[Уровень отделки]]=коэф_произв[Значение])*('Таблица объектов'!S$1=коэф_произв[Характеристика]),коэф_произв[Коэффициент],"",0)} -> 0.7 | U57: =IF(Таблица2[[#This Row],[Тип]]="прочие",0.05,PRODUCT(Таблица2[[#This Row],[Уровень отделки коэф.]],Таблица2[[#This Row],[Планировка коэф.]],Таблица2[[#This Row],[Архитектура коэф.]],Таблица2[[#This Row],[Инженерное оснащение коэф.]],Таблица2[[#This Row],[Полы коэф.]],Таблица2[[#This Row],[Конструкция коэф.]],Таблица2[[#This Row],[Наличие / Возможность кран-балки коэф.]],Таблица2[[#This Row],[Высота коэф.]])) -> 0.229824 | V57: =IF(Таблица2[[#This Row],[Тип]]="произв",IF(Таблица2[[#This Row],[Капитальность]]<0.33,"произв класс 4",IF(Таблица2[[#This Row],[Капитальность]]<0.55,"произв класс 3",IF(Таблица2[[#This Row],[Капитальность]]<0.77,"произв класс 2","произв класс 1"))),IF(Таблица2[[#This Row],[Тип]]="гражд",IF(Таблица2[[#This Row],[Капитальность]]<0.33,"гражд класс 4",IF(Таблица2[[#This Row],[Капитальность]]<0.55,"гражд класс 3",IF(Таблица2[[#This Row],[Капитальность]]<0.77,"гражд класс 2","гражд класс 1"))),"прочие")) -> гражд класс 4 | W57: =Таблица2[[#This Row],[Площадь, м2]]*Таблица2[[#This Row],[Капитальность]] -> 5.3089344 | Z57: =Y57*Таблица2[[#This Row],[Капитальность]] -> 0
A58: Аналог 8 | B58: 1776.9 | C58: Производственное помещение | D58: произв | E58: 5-8 м. | F58: {=_xlfn.XLOOKUP(1,(Таблица2[[#This Row],[Тип]]=коэф_произв[Тип])*(Таблица2[[#This Row],[Высота]]=коэф_произв[Значение])*('Таблица объектов'!E$1=коэф_произв[Характеристика]),коэф_произв[Коэффициент],"",0)} -> 0.8 | G58: Нет | H58: {=_xlfn.XLOOKUP(1,(Таблица2[[#This Row],[Тип]]=коэф_произв[Тип])*(Таблица2[[#This Row],[Наличие / Возможность кран-балки]]=коэф_произв[Значение])*('Таблица объектов'!G$1=коэф_произв[Характеристика]),коэф_произв[Коэффициент],"",0)} -> 0.9 | I58: Металлокаркасные теплые | J58: {=_xlfn.XLOOKUP(1,(Таблица2[[#This Row],[Тип]]=коэф_произв[Тип])*(Таблица2[[#This Row],[Конструкция]]=коэф_произв[Значение])*('Таблица объектов'!I$1=коэф_произв[Характеристика]),коэф_произв[Коэффициент],"",0)} -> 0.8 | K58: Усиленные для техники или специальные | L58: {=_xlfn.XLOOKUP(1,(Таблица2[[#This Row],[Тип]]=коэф_произв[Тип])*(Таблица2[[#This Row],[Полы]]=коэф_произв[Значение])*('Таблица объектов'!K$1=коэф_произв[Характеристика]),коэф_произв[Коэффициент],"",0)} -> 1 | M58: Отсутствует или минимальное (минимальная разводка освещения, водопровода) | N58: {=_xlfn.XLOOKUP(1,(Таблица2[[#This Row],[Тип]]=коэф_произв[Тип])*(Таблица2[[#This Row],[Инженерное оснащение]]=коэф_произв[Значение])*('Таблица объектов'!M$1=коэф_произв[Характеристика]),коэф_произв[Коэффициент],"",0)} -> 0.8 | P58: {=_xlfn.XLOOKUP(1,(Таблица2[[#This Row],[Тип]]=коэф_произв[Тип])*(Таблица2[[#This Row],[Архитектура]]=коэф_произв[Значение])*('Таблица объектов'!O$1=коэф_произв[Характеристика]),коэф_произв[Коэффициент],"",0)} | R58: {=_xlfn.XLOOKUP(1,(Таблица2[[#This Row],[Тип]]=коэф_произв[Тип])*(Таблица2[[#This Row],[Планировка]]=коэф_произв[Значение])*('Таблица объектов'!Q$1=коэф_произв[Характеристика]),коэф_произв[Коэффициент],"",0)} | T58: {=_xlfn.XLOOKUP(1,(Таблица2[[#This Row],[Тип]]=коэф_произв[Тип])*(Таблица2[[#This Row],[Уровень отделки]]=коэф_произв[Значение])*('Таблица объектов'!S$1=коэф_произв[Характеристика]),коэф_произв[Коэффициент],"",0)} | U58: =IF(Таблица2[[#This Row],[Тип]]="прочие",0.05,PRODUCT(Таблица2[[#This Row],[Уровень отделки коэф.]],Таблица2[[#This Row],[Планировка коэф.]],Таблица2[[#This Row],[Архитектура коэф.]],Таблица2[[#This Row],[Инженерное оснащение коэф.]],Таблица2[[#This Row],[Полы коэф.]],Таблица2[[#This Row],[Конструкция коэф.]],Таблица2[[#This Row],[Наличие / Возможность кран-балки коэф.]],Таблица2[[#This Row],[Высота коэф.]])) -> 0.4608 | V58: =IF(Таблица2[[#This Row],[Тип]]="произв",IF(Таблица2[[#This Row],[Капитальность]]<0.33,"произв класс 4",IF(Таблица2[[#This Row],[Капитальность]]<0.55,"произв класс 3",IF(Таблица2[[#This Row],[Капитальность]]<0.77,"произв класс 2","произв класс 1"))),IF(Таблица2[[#This Row],[Тип]]="гражд",IF(Таблица2[[#This Row],[Капитальность]]<0.33,"гражд класс 4",IF(Таблица2[[#This Row],[Капитальность]]<0.55,"гражд класс 3",IF(Таблица2[[#This Row],[Капитальность]]<0.77,"гражд класс 2","гражд класс 1"))),"прочие")) -> произв класс 3 | W58: =Таблица2[[#This Row],[Площадь, м2]]*Таблица2[[#This Row],[Капитальность]] -> 818.79552 | Z58: =Y58*Таблица2[[#This Row],[Капитальность]] -> 0
A66: Наименование | B66: произв класс 4 | C66: произв класс 3 | D66: произв класс 2 | E66: произв класс 1 | F66: гражд класс 4 | G66: гражд класс 3 | H66: гражд класс 2 | I66: гражд класс 1 | J66: прочие | K66: Проверка
A67: Объект оценки 1 | B67: {=SUMIFS(Площадь,Объект_оценки_аналог,$A67,Класс,B$66)} -> 11633.8 | C67: {=SUMIFS(Площадь,Объект_оценки_аналог,$A67,Класс,C$66)} -> 9671.5 | D67: {=SUMIFS(Площадь,Объект_оценки_аналог,$A67,Класс,D$66)} -> 0 | E67: {=SUMIFS(Площадь,Объект_оценки_аналог,$A67,Класс,E$66)} -> 0 | F67: {=SUMIFS(Площадь,Объект_оценки_аналог,$A67,Класс,F$66)} -> 155.9 | G67: {=SUMIFS(Площадь,Объект_оценки_аналог,$A67,Класс,G$66)} -> 0 | H67: {=SUMIFS(Площадь,Объект_оценки_аналог,$A67,Класс,H$66)} -> 0 | I67: {=SUMIFS(Площадь,Объект_оценки_аналог,$A67,Класс,I$66)} -> 0 | J67: {=SUMIFS(Площадь,Объект_оценки_аналог,$A67,Класс,J$66)} -> 0 | K67: =SUM(B67:J67) -> 21461.2
A68: Объект оценки 2 | B68: {=SUMIFS(Площадь,Объект_оценки_аналог,$A68,Класс,B$66)} -> 0 | C68: {=SUMIFS(Площадь,Объект_оценки_аналог,$A68,Класс,C$66)} -> 19040.5 | D68: {=SUMIFS(Площадь,Объект_оценки_аналог,$A68,Класс,D$66)} -> 0 | E68: {=SUMIFS(Площадь,Объект_оценки_аналог,$A68,Класс,E$66)} -> 0 | F68: {=SUMIFS(Площадь,Объект_оценки_аналог,$A68,Класс,F$66)} -> 0 | G68: {=SUMIFS(Площадь,Объект_оценки_аналог,$A68,Класс,G$66)} -> 949.5 | H68: {=SUMIFS(Площадь,Объект_оценки_аналог,$A68,Класс,H$66)} -> 0 | I68: {=SUMIFS(Площадь,Объект_оценки_аналог,$A68,Класс,I$66)} -> 0 | J68: {=SUMIFS(Площадь,Объект_оценки_аналог,$A68,Класс,J$66)} -> 0 | K68: =SUM(B68:J68) -> 19990
A69: Объект оценки 3 | B69: {=SUMIFS(Площадь,Объект_оценки_аналог,$A69,Класс,B$66)} -> 216.58 | C69: {=SUMIFS(Площадь,Объект_оценки_аналог,$A69,Класс,C$66)} -> 11689.7 | D69: {=SUMIFS(Площадь,Объект_оценки_аналог,$A69,Класс,D$66)} -> 0 | E69: {=SUMIFS(Площадь,Объект_оценки_аналог,$A69,Класс,E$66)} -> 0 | F69: {=SUMIFS(Площадь,Объект_оценки_аналог,$A69,Класс,F$66)} -> 59.79 | G69: {=SUMIFS(Площадь,Объект_оценки_аналог,$A69,Класс,G$66)} -> 4524.3 | H69: {=SUMIFS(Площадь,Объект_оценки_аналог,$A69,Класс,H$66)} -> 0 | I69: {=SUMIFS(Площадь,Объект_оценки_аналог,$A69,Класс,I$66)} -> 0 | J69: {=SUMIFS(Площадь,Объект_оценки_аналог,$A69,Класс,J$66)} -> 598.265 | K69: =SUM(B69:J69) -> 17088.635
A70: Объект оценки 4 | B70: {=SUMIFS(Площадь,Объект_оценки_аналог,$A70,Класс,B$66)} -> 138.7 | C70: {=SUMIFS(Площадь,Объект_оценки_аналог,$A70,Класс,C$66)} -> 4519.7 | D70: {=SUMIFS(Площадь,Объект_оценки_аналог,$A70,Класс,D$66)} -> 1576.1 | E70: {=SUMIFS(Площадь,Объект_оценки_аналог,$A70,Класс,E$66)} -> 0 | F70: {=SUMIFS(Площадь,Объект_оценки_аналог,$A70,Класс,F$66)} -> 24.82 | G70: {=SUMIFS(Площадь,Объект_оценки_аналог,$A70,Класс,G$66)} -> 221.2 | H70: {=SUMIFS(Площадь,Объект_оценки_аналог,$A70,Класс,H$66)} -> 0 | I70: {=SUMIFS(Площадь,Объект_оценки_аналог,$A70,Класс,I$66)} -> 0 | J70: {=SUMIFS(Площадь,Объект_оценки_аналог,$A70,Класс,J$66)} -> 24.8 | K70: =SUM(B70:J70) -> 6505.32
A71: Аналог 1 | B71: {=SUMIFS(Площадь,Объект_оценки_аналог,$A71,Класс,B$66)} -> 2700 | C71: {=SUMIFS(Площадь,Объект_оценки_аналог,$A71,Класс,C$66)} -> 0 | D71: {=SUMIFS(Площадь,Объект_оценки_аналог,$A71,Класс,D$66)} -> 0 | E71: {=SUMIFS(Площадь,Объект_оценки_аналог,$A71,Класс,E$66)} -> 0 | F71: {=SUMIFS(Площадь,Объект_оценки_аналог,$A71,Класс,F$66)} -> 0 | G71: {=SUMIFS(Площадь,Объект_оценки_аналог,$A71,Класс,G$66)} -> 0 | H71: {=SUMIFS(Площадь,Объект_оценки_аналог,$A71,Класс,H$66)} -> 0 | I71: {=SUMIFS(Площадь,Объект_оценки_аналог,$A71,Класс,I$66)} -> 0 | J71: {=SUMIFS(Площадь,Объект_оценки_аналог,$A71,Класс,J$66)} -> 0 | K71: =SUM(B71:J71) -> 2700
A72: Аналог 2 | B72: {=SUMIFS(Площадь,Объект_оценки_аналог,$A72,Класс,B$66)} -> 1112.2 | C72: {=SUMIFS(Площадь,Объект_оценки_аналог,$A72,Класс,C$66)} -> 5523.8 | D72: {=SUMIFS(Площадь,Объект_оценки_аналог,$A72,Класс,D$66)} -> 0 | E72: {=SUMIFS(Площадь,Объект_оценки_аналог,$A72,Класс,E$66)} -> 0 | F72: {=SUMIFS(Площадь,Объект_оценки_аналог,$A72,Класс,F$66)} -> 0 | G72: {=SUMIFS(Площадь,Объект_оценки_аналог,$A72,Класс,G$66)} -> 360 | H72: {=SUMIFS(Площадь,Объект_оценки_аналог,$A72,Класс,H$66)} -> 0 | I72: {=SUMIFS(Площадь,Объект_оценки_аналог,$A72,Класс,I$66)} -> 0 | J72: {=SUMIFS(Площадь,Объект_оценки_аналог,$A72,Класс,J$66)} -> 0 | K72: =SUM(B72:J72) -> 6996
A73: Аналог 3 | B73: {=SUMIFS(Площадь,Объект_оценки_аналог,$A73,Класс,B$66)} -> 0 | C73: {=SUMIFS(Площадь,Объект_оценки_аналог,$A73,Класс,C$66)} -> 0 | D73: {=SUMIFS(Площадь,Объект_оценки_аналог,$A73,Класс,D$66)} -> 1947.1 | E73: {=SUMIFS(Площадь,Объект_оценки_аналог,$A73,Класс,E$66)} -> 0 | F73: {=SUMIFS(Площадь,Объект_оценки_аналог,$A73,Класс,F$66)} -> 0 | G73: {=SUMIFS(Площадь,Объект_оценки_аналог,$A73,Класс,G$66)} -> 1390 | H73: {=SUMIFS(Площадь,Объект_оценки_аналог,$A73,Класс,H$66)} -> 0 | I73: {=SUMIFS(Площадь,Объект_оценки_аналог,$A73,Класс,I$66)} -> 0 | J73: {=SUMIFS(Площадь,Объект_оценки_аналог,$A73,Класс,J$66)} -> 0 | K73: =SUM(B73:J73) -> 3337.1
A74: Аналог 4 | B74: {=SUMIFS(Площадь,Объект_оценки_аналог,$A74,Класс,B$66)} -> 4822.3 | C74: {=SUMIFS(Площадь,Объект_оценки_аналог,$A74,Класс,C$66)} -> 0 | D74: {=SUMIFS(Площадь,Объект_оценки_аналог,$A74,Класс,D$66)} -> 0 | E74: {=SUMIFS(Площадь,Объект_оценки_аналог,$A74,Класс,E$66)} -> 0 | F74: {=SUMIFS(Площадь,Объект_оценки_аналог,$A74,Класс,F$66)} -> 0 | G74: {=SUMIFS(Площадь,Объект_оценки_аналог,$A74,Класс,G$66)} -> 877.7 | H74: {=SUMIFS(Площадь,Объект_оценки_аналог,$A74,Класс,H$66)} -> 0 | I74: {=SUMIFS(Площадь,Объект_оценки_аналог,$A74,Класс,I$66)} -> 0 | J74: {=SUMIFS(Площадь,Объект_оценки_аналог,$A74,Класс,J$66)} -> 0 | K74: =SUM(B74:J74) -> 5700
A75: Аналог 5 | B75: {=SUMIFS(Площадь,Объект_оценки_аналог,$A75,Класс,B$66)} -> 840 | C75: {=SUMIFS(Площадь,Объект_оценки_аналог,$A75,Класс,C$66)} -> 1561.2 | D75: {=SUMIFS(Площадь,Объект_оценки_аналог,$A75,Класс,D$66)} -> 0 | E75: {=SUMIFS(Площадь,Объект_оценки_аналог,$A75,Класс,E$66)} -> 0 | F75: {=SUMIFS(Площадь,Объект_оценки_аналог,$A75,Класс,F$66)} -> 0 | G75: {=SUMIFS(Площадь,Объект_оценки_аналог,$A75,Класс,G$66)} -> 74.8 | H75: {=SUMIFS(Площадь,Объект_оценки_аналог,$A75,Класс,H$66)} -> 0 | I75: {=SUMIFS(Площадь,Объект_оценки_аналог,$A75,Класс,I$66)} -> 0 | J75: {=SUMIFS(Площадь,Объект_оценки_аналог,$A75,Класс,J$66)} -> 0 | K75: =SUM(B75:J75) -> 2476
A76: Аналог 6 | B76: {=SUMIFS(Площадь,Объект_оценки_аналог,$A76,Класс,B$66)} -> 1760 | C76: {=SUMIFS(Площадь,Объект_оценки_аналог,$A76,Класс,C$66)} -> 0 | D76: {=SUMIFS(Площадь,Объект_оценки_аналог,$A76,Класс,D$66)} -> 0 | E76: {=SUMIFS(Площадь,Объект_оценки_аналог,$A76,Класс,E$66)} -> 0 | F76: {=SUMIFS(Площадь,Объект_оценки_аналог,$A76,Класс,F$66)} -> 110 | G76: {=SUMIFS(Площадь,Объект_оценки_аналог,$A76,Класс,G$66)} -> 0 | H76: {=SUMIFS(Площадь,Объект_оценки_аналог,$A76,Класс,H$66)} -> 0 | I76: {=SUMIFS(Площадь,Объект_оценки_аналог,$A76,Класс,I$66)} -> 0 | J76: {=SUMIFS(Площадь,Объект_оценки_аналог,$A76,Класс,J$66)} -> 0 | K76: =SUM(B76:J76) -> 1870
A77: Аналог 7 | B77: {=SUMIFS(Площадь,Объект_оценки_аналог,$A77,Класс,B$66)} -> 122 | C77: {=SUMIFS(Площадь,Объект_оценки_аналог,$A77,Класс,C$66)} -> 700 | D77: {=SUMIFS(Площадь,Объект_оценки_аналог,$A77,Класс,D$66)} -> 0 | E77: {=SUMIFS(Площадь,Объект_оценки_аналог,$A77,Класс,E$66)} -> 0 | F77: {=SUMIFS(Площадь,Объект_оценки_аналог,$A77,Класс,F$66)} -> 500 | G77: {=SUMIFS(Площадь,Объект_оценки_аналог,$A77,Класс,G$66)} -> 0 | H77: {=SUMIFS(Площадь,Объект_оценки_аналог,$A77,Класс,H$66)} -> 0 | I77: {=SUMIFS(Площадь,Объект_оценки_аналог,$A77,Класс,I$66)} -> 0 | J77: {=SUMIFS(Площадь,Объект_оценки_аналог,$A77,Класс,J$66)} -> 85 | K77: =SUM(B77:J77) -> 1407
A78: Аналог 8 | B78: {=SUMIFS(Площадь,Объект_оценки_аналог,$A78,Класс,B$66)} -> 0 | C78: {=SUMIFS(Площадь,Объект_оценки_аналог,$A78,Класс,C$66)} -> 1776.9 | D78: {=SUMIFS(Площадь,Объект_оценки_аналог,$A78,Класс,D$66)} -> 0 | E78: {=SUMIFS(Площадь,Объект_оценки_аналог,$A78,Класс,E$66)} -> 0 | F78: {=SUMIFS(Площадь,Объект_оценки_аналог,$A78,Класс,F$66)} -> 23.1 | G78: {=SUMIFS(Площадь,Объект_оценки_аналог,$A78,Класс,G$66)} -> 0 | H78: {=SUMIFS(Площадь,Объект_оценки_аналог,$A78,Класс,H$66)} -> 0 | I78: {=SUMIFS(Площадь,Объект_оценки_аналог,$A78,Класс,I$66)} -> 0 | J78: {=SUMIFS(Площадь,Объект_оценки_аналог,$A78,Класс,J$66)} -> 0 | K78: =SUM(B78:J78) -> 1800

Sheet Шкалы
A2: Физический износ (в%) | B2: Состояние несменяемых конструкций зданий | C2: Состояние внутренних конструктивных элементов | E2: Состоние
A3: 0-20 | B3: Повреждений и деформаций нет. Нет также следов устранения дефектов | C3: Полы и потолки ровные, горизонтальные, трещины в покрытиях и отделке отсутствуют | E3: 5
A4: 21-40 | B4: Повреждений и дефектов, в том числе и искривлений, нет. Имеются местами следы различных ремонтов, в том числе небольших трещин в простенках и перемычках. | C4: Полы и потолки ровные, на потолках возможны волосяные трещины. На ступенях лестниц небольшое число повреждений. Окна и двери открываются с некоторым усилием. | E4: 4
A5: 41-60 | B5: Имеется много следов ремонтов трещин и участков наружной отделки. Имеются места искривления горизонтальных линий и следы их ликвидации. Износ кладки стен характеризуется трещинами между блоками. | C5: Полы в отдельных местах зыбкие и с отклонениями от горизонтали. В потолках много трещин, ранее заделанных и появившихся вновь. Отдельные отставания покрытия пола (паркета, плиток). Большое число поврежденных ступеней. | E5: 3
A6: 61-80 | B6: Имеются открытые трещины различного происхождения, в том числе от износа и перегрузки кладки поперек кирпичей. Большое искривление горизонтальных линий и местами отклонение стен от вертикали. | C6: Большое число отклонений от горизонтали в полах, зыбкость. Массовое повреждение и отсутствие покрытия пола. В потолках много мест с обвалившейся штукатуркой. Много перекошенных окон и дверей. Большое число поврежденных ступеней, перекосы маршей, щели между ступенями. | E6: 2
A7: 81-100 | B7: Здание в опасном состоянии. Участки стен разрушены, деформированы в проемах. Трещины по перемычкам, простенкам и по всей поверхности стен. Возможны большие искривления горизонтальных линий и выпучивание стен. | C7: Полы с большими перекосами и уклонами. Заметные прогибы потолков. Окна и двери с гнилью в узлах и брусьях. В маршах лестниц не хватает ступеней и перил. Внутренняя отделка полностью разрушена. | E7: 1

Sheet Выжимка
B1: Типы и классы помещений | C1: Объект оценки 1 | D1: Объект оценки 2 | E1: Объект оценки 3 | F1: Объект оценки 4 | G1: Аналог 1 | H1: Аналог 2 | I1: Аналог 3 | J1: Аналог 4 | K1: Аналог 5 | L1: Аналог 6 | M1: Аналог 7 | N1: Аналог 8
B2: Адрес | C2: г. Бишкек, ул. Алыкулова, д. 3/1 (ЕНИ №1-01-01-0003-0849) | D2: г. Бишкек, ул. Мурманская, 1 | E2: Триод | F2: г. Бишкек, ул. Интергельпо, д. 1/11, ЕНИ №1-01-02-0009-0470 | G2: Садыгалиева 4а/1 | H2: г. Бишкек, ул. Матросова, 1а/ ул. Карадарьинская | I2: г. Бишкек, ул. Республиканская, д. 146/1 | J2: г. Бишкек, ул. Месароша, д. 101/1 и ул. Кронштадтская, д. 21/1 | K2: г. Бишкек, ул. Матросова 1а, конец ул. Камчатская | L2: г. Бишкек, ул. Интергельпо, д. 1/38 | M2: г. Бишкек, ул. Мурманская, 122а/1 | N2: г. Бишкек, ул. Мурманская, д. 56/1
B3: =B32 -> произв класс 4 | C3: {=SUMIFS(Площадь,Объект_оценки_аналог,C$1,Класс,$B3)} -> 11633.8 | D3: {=SUMIFS(Площадь,Объект_оценки_аналог,D$1,Класс,$B3)} -> 0 | E3: {=SUMIFS(Площадь,Объект_оценки_аналог,E$1,Класс,$B3)} -> 216.58 | F3: {=SUMIFS(Площадь,Объект_оценки_аналог,F$1,Класс,$B3)} -> 138.7 | G3: {=SUMIFS(Площадь,Объект_оценки_аналог,G$1,Класс,$B3)} -> 2700 | H3: {=SUMIFS(Площадь,Объект_оценки_аналог,H$1,Класс,$B3)} -> 1112.2 | I3: {=SUMIFS(Площадь,Объект_оценки_аналог,I$1,Класс,$B3)} -> 0 | J3: {=SUMIFS(Площадь,Объект_оценки_аналог,J$1,Класс,$B3)} -> 4822.3 | ... N3: {=SUMIFS(Площадь,Объект_оценки_аналог,N$1,Класс,$B3)} -> 0
